Workbook
Name \P: #REF!
Name \P: #REF!
Name __bas8: #REF!
Name __bas8: #REF!
Name _10QRY_OCTCD_SUMMARY: #REF!
Name _10QRY_OCTCD_SUMMARY: #REF!
Name _10QRY_OCTST_SUMMARY: #REF!
Name _10QRY_OCTST_SUMMARY: #REF!
Name _1a_qr_CD_standard_rate_per_case: #REF!
Name _2007AC_Q1_Shipped_Paid_CD: #REF!
Name _2007AC_Q1_Shipped_Paid_ST: #REF!
Name _2a_qr_ST_rate_per_standard_case: #REF!
Name _6QRY_JUNCD_SUMMARY: #REF!
Name _6QRY_JUNST_SUMMARY: #REF!
Name _8QRY_AUGCD_SUMMARY: #REF!
Name _8QRY_AUGST_SUMMARY: #REF!
Name _9QRY_SEPCD_SUMMARY: #REF!
Name _9QRY_SEPST_SUMMARY: #REF!
Name _ACC0320: #REF!
Name _BAL0320: #REF!
Name _BAL0344: #REF!
Name _BAL0348: #REF!
Name _BAL0360: #REF!
Name _BAL0361: #REF!
Name _BAL0367: #REF!
Name _BAL0370: #REF!
Name _BAL0375: #REF!
Name _BAL0384: #REF!
Name _BAL0385: #REF!
Name _BAL0386: #REF!
Name _BAL0387: #REF!
Name _BAL0388: #REF!
Name _BAL0395: #REF!
Name _bal0397: #REF!
Name _BAL0399: #REF!
Name _BAL0400: #REF!
Name _BAL0810: #REF!
Name _BAL0811: #REF!
Name _BAL0815: #REF!
Name _BAL6791: #REF!
Name _bas8: #REF!
Name _BLA0811: #REF!
Name _top15: #REF!
Name _top15: #REF!
Name aaa: #REF!
Name aaa: #REF!
Name ACTUAL_RATE: #REF!
Name ACTUAL_RATE: #REF!
Name Adjustment: #REF!
Name Adjustment: #REF!
Name agdump: #REF!
Name agedump: #REF!
Name agencydump: #REF!
Name AGENCYLY: #REF!
Name AGENCYPLAN: #REF!
Name AllocationTable: #REF!
Name Americas_Apr: #REF!
Name Americas_Aug: #REF!
Name Americas_Backlog_Apr: #REF!
Name Americas_Backlog_Aug: #REF!

Sheet Recap
C2: M Phys CS | G2: Growth vs YAG | J2: Weight of Total
B3: Supply | D3: 2024 | E3: 2025 | F3: 2026 | G3: 2025 | H3: 2026 | J3: 2024 | K3: 2025 | L3: 2026
C4: VT | D4: =('Cases post Attain'!#REF!+'Cases post Attain'!#REF!)/1000000 -> #REF! | E4: =('Cases post Attain'!Q14+'Cases post Attain'!Q22)/1000000 -> 23.132218 | F4: =('Cases post Attain'!P14+'Cases post Attain'!P22)/1000000 -> 23.460657 | G4: =E4/D4-1 -> #REF! | H4: =F4/E4-1 -> 0.014198304 | J4: =D4/D$11 -> #REF! | K4: =E4/E$11 -> 0.20370898 | L4: =F4/F$11 -> 0.20629004
C5: SIK | D5: ='Cases post Attain'!#REF!/1000000 -> #REF! | E5: ='Cases post Attain'!Q41/1000000 -> 41.684951 | F5: ='Cases post Attain'!P41/1000000 -> 41.70427 | G5: =E5/D5-1 -> #REF! | H5: =F5/E5-1 -> 0.00046344022 | J5: =D5/D$11 -> #REF! | K5: =E5/E$11 -> 0.36708969 | L5: =F5/F$11 -> 0.36670651
C6: COV | D6: ='Cases post Attain'!#REF!/1000000 -> #REF! | E6: ='Cases post Attain'!Q53/1000000 -> 21.663802 | F6: ='Cases post Attain'!P53/1000000 -> 21.551506 | G6: =E6/D6-1 -> #REF! | H6: =F6/E6-1 -> -0.0051836022 | J6: =D6/D$11 -> #REF! | K6: =E6/E$11 -> 0.19077768 | L6: =F6/F$11 -> 0.18950284
C7: Total UL Sites | D7: =SUM(D4:D6) -> #REF! | E7: =SUM(E4:E6) -> 86.480972 | F7: =SUM(F4:F6) -> 86.716432 | G7: =E7/D7-1 -> #REF! | H7: =F7/E7-1 -> 0.0027226823 | J7: =D7/D$11 -> #REF! | K7: =E7/E$11 -> 0.76157636 | L7: =F7/F$11 -> 0.76249939
C8: SIM | D8: ='Cases post Attain'!#REF!/1000000 -> #REF! | E8: ='Cases post Attain'!Q185/1000000 -> 1.050083 | F8: ='Cases post Attain'!P185/1000000 -> 1.3736613 | G8: =E8/D8-1 -> #REF! | H8: =F8/E8-1 -> 0.30814547 | J8: =D8/D$11 -> #REF! | K8: =E8/E$11 -> 0.0092473335 | L8: =F8/F$11 -> 0.012078633
C9: Imports | D9: ='Cases post Attain'!#REF!/1000000 -> #REF! | E9: ='Cases post Attain'!Q186/1000000 -> 6.4899841 | F9: ='Cases post Attain'!P186/1000000 -> 6.7847887 | G9: =E9/D9-1 -> #REF! | H9: =F9/E9-1 -> 0.045424559 | J9: =D9/D$11 -> #REF! | K9: =E9/E$11 -> 0.05715267 | L9: =F9/F$11 -> 0.059658789
C10: CM | D10: ='Cases post Attain'!#REF!/1000000 -> #REF! | E10: ='Cases post Attain'!Q184/1000000 -> 19.534182 | F10: ='Cases post Attain'!P184/1000000 -> 18.851677 | G10: =E10/D10-1 -> #REF! | H10: =F10/E10-1 -> -0.034939041 | J10: =D10/D$11 -> #REF! | K10: =E10/E$11 -> 0.17202364 | L10: =F10/F$11 -> 0.16576319
C11: Total UL | D11: =SUM(D7:D10) -> #REF! | E11: =SUM(E7:E10) -> 113.55522 | F11: =SUM(F7:F10) -> 113.72656 | G11: =E11/D11-1 -> #REF! | H11: =F11/E11-1 -> 0.0015088481
B13: Demand | D13: 110.04314 | E13: 114.37354 | F13: 115.02552 | G13: =E13/D13-1 -> 0.039351813 | H13: =F13/E13-1 -> 0.0057004547
C15: Litons | G15: Growth vs YAG | J15: Weight of Total
B16: Supply | D16: 2024 | E16: 2025 | F16: 2026 | G16: 2025 | H16: 2026 | J16: 2024 | K16: 2025 | L16: 2026
C17: VT | D17: ='Litons Post Attain'!X14+'Litons Post Attain'!X22 -> 104785.87 | E17: ='Litons Post Attain'!Q14+'Litons Post Attain'!Q22 -> 90219.037 | F17: ='Litons Post Attain'!P14+'Litons Post Attain'!P22 -> 91781.613 | G17: =E17/D17-1 -> -0.13901523 | H17: =F17/E17-1 -> 0.017319805 | J17: =D17/D$24 -> 0.19226184 | K17: =E17/E$24 -> 0.16642088 | L17: =F17/F$24 -> 0.16881117
C18: SIK | D18: ='Litons Post Attain'!X41 -> 205930.96 | E18: ='Litons Post Attain'!Q41 -> 205006.34 | F18: ='Litons Post Attain'!P41 -> 203978.38 | G18: =E18/D18-1 -> -0.0044899845 | H18: =F18/E18-1 -> -0.0050142644 | J18: =D18/D$24 -> 0.37784356 | K18: =E18/E$24 -> 0.37816115 | L18: =F18/F$24 -> 0.37517133
C19: COV | D19: ='Litons Post Attain'!X53 -> 165582.14 | E19: ='Litons Post Attain'!Q53 -> 166103.48 | F19: ='Litons Post Attain'!P53 -> 164699.16 | G19: =E19/D19-1 -> 0.0031485448 | H19: =F19/E19-1 -> -0.0084544979 | J19: =D19/D$24 -> 0.30381127 | K19: =E19/E$24 -> 0.30639973 | L19: =F19/F$24 -> 0.30292624
C20: Total UL Sites | D20: =SUM(D17:D19) -> 476298.97 | E20: =SUM(E17:E19) -> 461328.86 | F20: =SUM(F17:F19) -> 460459.16 | G20: =E20/D20-1 -> -0.031430083 | H20: =F20/E20-1 -> -0.0018852093 | J20: =D20/D$24 -> 0.87391667 | K20: =E20/E$24 -> 0.85098176 | L20: =F20/F$24 -> 0.84690874
C21: SIM | D21: ='Litons Post Attain'!X185 -> 2692.3499 | E21: ='Litons Post Attain'!Q185 -> 6089.5978 | F21: ='Litons Post Attain'!P185 -> 7235.8502 | G21: =E21/D21-1 -> 1.2618152 | H21: =F21/E21-1 -> 0.18823123 | J21: =D21/D$24 -> 0.0049399423 | K21: =E21/E$24 -> 0.011233064 | L21: =F21/F$24 -> 0.013308683
C22: Imports | D22: ='Litons Post Attain'!X186 -> 25084.336 | E22: ='Litons Post Attain'!Q186 -> 20341.501 | F22: ='Litons Post Attain'!P186 -> 21261.39 | G22: =E22/D22-1 -> -0.18907556 | H22: =F22/E22-1 -> 0.045222262 | J22: =D22/D$24 -> 0.046024915 | K22: =E22/E$24 -> 0.037522575 | L22: =F22/F$24 -> 0.039105438
C23: CM | D23: ='Litons Post Attain'!X184 -> 40940.802 | E23: ='Litons Post Attain'!Q184 -> 54353.729 | F23: ='Litons Post Attain'!P184 -> 54737.552 | G23: =E23/D23-1 -> 0.32761759 | H23: =F23/E23-1 -> 0.0070615826 | J23: =D23/D$24 -> 0.075118469 | K23: =E23/E$24 -> 0.1002626 | L23: =F23/F$24 -> 0.10067714
C24: Total UL | D24: =SUM(D20:D23) -> 545016.46 | E24: =SUM(E20:E23) -> 542113.69 | F24: =SUM(F20:F23) -> 543693.95 | G24: =E24/D24-1 -> -0.0053260347 | H24: =F24/E24-1 -> 0.0029150031
B26: Demand | D26: 545782.12 | E26: 558648.09 | F26: 554103.58 | G26: =E26/D26-1 -> 0.023573437 | H26: =F26/E26-1 -> -0.0081348248
E29: =(E7*1000000) -> 86480972
E30: =E20/E29 -> 0.0053344551

Sheet Sup-Dmd
D3: Column Labels
D4: CM | G4: Import | J4: SIM | M4: UL | U4: 2026
C5: Row Labels | D5: Sum of 2024 MRF12 | E5: Sum of 2025 MRF8 | F5: Sum of 2026 MRF8 | G5: Sum of 2024 MRF12 | H5: Sum of 2025 MRF8 | I5: Sum of 2026 MRF8 | J5: Sum of 2024 MRF12 | K5: Sum of 2025 MRF8 | L5: Sum of 2026 MRF8 | M5: Sum of 2024 MRF12 | N5: Sum of 2025 MRF8 | O5: Sum of 2026 MRF8 | S5: SIM | T5: UL | U5: CM | V5: Import | W5: SIM | X5: UL
C6: 2.4 Gal | M6: 496558 | N6: 483586 | O6: 526240 | S6: =J6/F6-1 -> #DIV/0! | T6: =K6/G6-1 -> #DIV/0! | U6: =L6/H6-1 -> #DIV/0! | V6: =M6/I6-1 -> #DIV/0! | W6: =N6/J6-1 -> #DIV/0! | X6: =O6/K6-1 -> #DIV/0! | Y6: Course Correct Inventory in 2025
C7: 48oz | K7: 0 | L7: 0 | M7: 25940115 | N7: 25174238 | O7: 25596140 | S7: =J7/F7-1 -> #DIV/0! | T7: =K7/G7-1 -> #DIV/0! | U7: =L7/H7-1 -> #DIV/0! | V7: =M7/I7-1 -> #DIV/0! | W7: =N7/J7-1 -> #DIV/0! | X7: =O7/K7-1 -> #DIV/0! | Y7: Price Increase in 26' -9% Growth
C8: B&J Cups | D8: 428282.4 | E8: 1197580 | F8: 1060263 | M8: 951586 | N8: 0 | O8: 0 | S8: =J8/F8-1 -> -1 | T8: =K8/G8-1 -> #DIV/0! | U8: =L8/H8-1 -> #DIV/0! | V8: =M8/I8-1 -> #DIV/0! | W8: =N8/J8-1 -> #DIV/0! | X8: =O8/K8-1 -> #DIV/0! | Y8: Only 1% growth
C9: BJ Bars | E9: 190000 | F9: 1987500 | M9: 0 | N9: 0 | O9: 0 | S9: =J9/F9-1 -> -1 | T9: =K9/G9-1 -> #DIV/0! | U9: =L9/H9-1 -> #DIV/0! | V9: =M9/I9-1 -> #DIV/0! | W9: =N9/J9-1 -> #DIV/0! | X9: =O9/K9-1 -> #DIV/0! | Y9: Run All out till Sept, then must reduce
C10: BJ PTS | E10: 607165 | F10: 0 | J10: 306662 | K10: 115851 | L10: 0 | M10: 26084291 | N10: 25610872 | O10: 24125674 | S10: =J10/F10-1 -> #DIV/0! | T10: =K10/G10-1 -> #DIV/0! | U10: =L10/H10-1 -> #DIV/0! | V10: =M10/I10-1 -> #DIV/0! | W10: =N10/J10-1 -> 82.514984 | X10: =O10/K10-1 -> 207.24744
C11: Dough Bites | D11: 414132 | E11: 472047 | F11: 338000 | S11: =J11/F11-1 -> -1 | T11: =K11/G11-1 -> #DIV/0! | U11: =L11/H11-1 -> #DIV/0! | V11: =M11/I11-1 -> #DIV/0! | W11: =N11/J11-1 -> #DIV/0! | X11: =O11/K11-1 -> #DIV/0!
C12: EDF | M12: 4730331 | N12: 4886903 | O12: 4799210 | S12: =J12/F12-1 -> #DIV/0! | T12: =K12/G12-1 -> #DIV/0! | U12: =L12/H12-1 -> #DIV/0! | V12: =M12/I12-1 -> #DIV/0! | W12: =N12/J12-1 -> #DIV/0! | X12: =O12/K12-1 -> #DIV/0!
C13: EFW | J13: 277747 | K13: 0 | L13: 210808.32 | M13: 1279479 | N13: 429288 | O13: 0 | S13: =J13/F13-1 -> #DIV/0! | T13: =K13/G13-1 -> #DIV/0! | U13: =L13/H13-1 -> #DIV/0! | V13: =M13/I13-1 -> #DIV/0! | W13: =N13/J13-1 -> 0.54560805 | X13: =O13/K13-1 -> #DIV/0!
C14: ESS | D14: 1152694 | E14: 2139398 | F14: 2441304 | H14: 0 | I14: 0 | J14: 153328 | K14: 366132.4 | L14: 417273.6 | M14: 1566148 | N14: 0 | O14: 0 | S14: =J14/F14-1 -> -0.93719422 | T14: =K14/G14-1 -> #DIV/0! | U14: =L14/H14-1 -> #DIV/0! | V14: =M14/I14-1 -> #DIV/0! | W14: =N14/J14-1 -> -1 | X14: =O14/K14-1 -> -1
C15: Facepieces | G15: 3277504 | H15: 4737327 | I15: 3860663 | S15: =J15/F15-1 -> #DIV/0! | T15: =K15/G15-1 -> -1 | U15: =L15/H15-1 -> -1 | V15: =M15/I15-1 -> -1 | W15: =N15/J15-1 -> #DIV/0! | X15: =O15/K15-1 -> #DIV/0!
C16: KL Mini Cones | G16: 988955 | H16: 741961 | I16: 638158 | S16: =J16/F16-1 -> #DIV/0! | T16: =K16/G16-1 -> -1 | U16: =L16/H16-1 -> -1 | V16: =M16/I16-1 -> -1 | W16: =N16/J16-1 -> #DIV/0! | X16: =O16/K16-1 -> #DIV/0!
C17: MBG | M17: 3656088 | N17: 3863294 | O17: 2789300 | S17: =J17/F17-1 -> #DIV/0! | T17: =K17/G17-1 -> #DIV/0! | U17: =L17/H17-1 -> #DIV/0! | V17: =M17/I17-1 -> #DIV/0! | W17: =N17/J17-1 -> #DIV/0! | X17: =O17/K17-1 -> #DIV/0!
C18: MG Sticks | G18: 215076 | H18: 108582 | I18: 0 | J18: 75496 | K18: 8403 | L18: 0 | M18: 6269673 | N18: 6988063.5 | O18: 6048195 | S18: =J18/F18-1 -> #DIV/0! | T18: =K18/G18-1 -> -0.96093009 | U18: =L18/H18-1 -> -1 | V18: =M18/I18-1 -> #DIV/0! | W18: =N18/J18-1 -> 91.562036 | X18: =O18/K18-1 -> 718.76615
C19: Other | D19: 1646147 | E19: 761236 | F19: 873302.14 | G19: 92423 | H19: 218262 | I19: 329856 | M19: 168964 | N19: 358927 | O19: 472340 | S19: =J19/F19-1 -> -1 | T19: =K19/G19-1 -> -1 | U19: =L19/H19-1 -> -1 | V19: =M19/I19-1 -> -0.48776436 | W19: =N19/J19-1 -> #DIV/0! | X19: =O19/K19-1 -> #DIV/0!
C20: PG | G20: 1676859 | H20: 3133646.9 | I20: 1490517.9 | J20: 11427 | K20: 17358 | L20: 0 | M20: 2414254 | N20: 5053318.5 | O20: 5361705 | S20: =J20/F20-1 -> #DIV/0! | T20: =K20/G20-1 -> -0.9896485 | U20: =L20/H20-1 -> -1 | V20: =M20/I20-1 -> 0.6197417 | W20: =N20/J20-1 -> 441.22617 | X20: =O20/K20-1 -> 307.88956
C21: SP1 | D21: 229128 | E21: 8521 | F21: 0 | M21: 3347105.6 | N21: 3907336 | O21: 4073579 | S21: =J21/F21-1 -> #DIV/0! | T21: =K21/G21-1 -> #DIV/0! | U21: =L21/H21-1 -> #DIV/0! | V21: =M21/I21-1 -> #DIV/0! | W21: =N21/J21-1 -> #DIV/0! | X21: =O21/K21-1 -> #DIV/0!
C22: TALENTI | M22: 11399511 | N22: 10546374 | O22: 11003808 | S22: =J22/F22-1 -> #DIV/0! | T22: =K22/G22-1 -> #DIV/0! | U22: =L22/H22-1 -> #DIV/0! | V22: =M22/I22-1 -> #DIV/0! | W22: =N22/J22-1 -> #DIV/0! | X22: =O22/K22-1 -> #DIV/0!
C23: Yasso Poppables | D23: 335233 | E23: 489248 | F23: 417600 | S23: =J23/F23-1 -> -1 | T23: =K23/G23-1 -> #DIV/0! | U23: =L23/H23-1 -> #DIV/0! | V23: =M23/I23-1 -> #DIV/0! | W23: =N23/J23-1 -> #DIV/0! | X23: =O23/K23-1 -> #DIV/0!
C24: Yasso Sandwich | D24: 168614 | E24: 156824 | F24: 169253.5 | S24: =J24/F24-1 -> -1 | T24: =K24/G24-1 -> #DIV/0! | U24: =L24/H24-1 -> #DIV/0! | V24: =M24/I24-1 -> #DIV/0! | W24: =N24/J24-1 -> #DIV/0! | X24: =O24/K24-1 -> #DIV/0!
C25: Yasso Sticks | D25: 7019764 | E25: 7905382.8 | F25: 7006250 | M25: 441482 | N25: 1474098 | O25: 3855100 | S25: =J25/F25-1 -> -1 | T25: =K25/G25-1 -> #DIV/0! | U25: =L25/H25-1 -> #DIV/0! | V25: =M25/I25-1 -> #DIV/0! | W25: =N25/J25-1 -> #DIV/0! | X25: =O25/K25-1 -> #DIV/0!
C26: YS PTS | E26: 238415 | F26: 0 | M26: 0 | N26: 75000 | O26: 1680000 | S26: =J26/F26-1 -> #DIV/0! | T26: =K26/G26-1 -> #DIV/0! | U26: =L26/H26-1 -> #DIV/0! | V26: =M26/I26-1 -> #DIV/0! | W26: =N26/J26-1 -> #DIV/0! | X26: =O26/K26-1 -> #DIV/0!
C27: Yasso Club | D27: 1931563 | E27: 2821581 | F27: 2142284.2 | S27: =J27/F27-1 -> -1 | T27: =K27/G27-1 -> #DIV/0! | U27: =L27/H27-1 -> #DIV/0! | V27: =M27/I27-1 -> #DIV/0! | W27: =N27/J27-1 -> #DIV/0! | X27: =O27/K27-1 -> #DIV/0!
C28: Grand Total | D28: 13325557 | E28: 16987398 | F28: 16435757 | G28: 6250817 | H28: 8939778.8 | I28: 6319194.9 | J28: 824660 | K28: 507744.4 | L28: 628081.92 | M28: 88745585 | N28: 88851298 | O28: 90331291 | S28: =J28/F28-1 -> -0.94982525 | T28: =K28/G28-1 -> -0.91877151 | U28: =L28/H28-1 -> -0.92974301 | V28: =M28/I28-1 -> 13.043812 | W28: =N28/J28-1 -> 106.74295 | X28: =O28/K28-1 -> 176.90702
C32: Type | D32: (Multiple Items)
G33: Demand | J33: Demand | L33: Suppl | N33: Supp vs Dem
C34: Row Labels | D34: Sum of 2024 MRF12 | E34: Sum of 2025 MRF8 | F34: Sum of 2026 MRF8 | G34: 2024 | H34: 2025 | I34: 2026 | J34: 2025 | K34: 2026 | L34: 2025 | M34: 2026 | N34: 25 | O34: 26
B35: Cases | C35: 48oz | D35: 25940115 | E35: 25174238 | F35: 25596140 | G35: =VLOOKUP($C35,#REF!,2,0) -> #REF! | H35: =VLOOKUP($C35,#REF!,3,0) -> #REF! | I35: =VLOOKUP($C35,#REF!,4,0) -> #REF! | J35: =H35/G35-1 -> #REF! | K35: =I35/H35-1 -> #REF! | L35: =E35/D35-1 -> -0.029524811 | M35: =F35/E35-1 -> 0.016759276 | N35: =E35/H35-1 -> #REF! | O35: =F35/I35-1 -> #REF! | P35: Short in 25'
C36: BJ PTS | D36: 26390953 | E36: 26333888 | F36: 24125674 | G36: =VLOOKUP($C36,#REF!,2,0) -> #REF! | H36: =VLOOKUP($C36,#REF!,3,0) -> #REF! | I36: =VLOOKUP($C36,#REF!,4,0) -> #REF! | J36: =H36/G36-1 -> #REF! | K36: =I36/H36-1 -> #REF! | L36: =E36/D36-1 -> -0.002162288 | M36: =F36/E36-1 -> -0.083854456 | N36: =E36/H36-1 -> #REF! | O36: =F36/I36-1 -> #REF!
C37: TALENTI | D37: 11399511 | E37: 10546374 | F37: 11003808 | G37: =VLOOKUP($C37,#REF!,2,0) -> #REF! | H37: =VLOOKUP($C37,#REF!,3,0) -> #REF! | I37: =VLOOKUP($C37,#REF!,4,0) -> #REF! | J37: =H37/G37-1 -> #REF! | K37: =I37/H37-1 -> #REF! | L37: =E37/D37-1 -> -0.074839752 | M37: =F37/E37-1 -> 0.04337358 | N37: =E37/H37-1 -> #REF! | O37: =F37/I37-1 -> #REF! | P37: Course correction in 25'
C38: Yasso Sticks | D38: 7461246 | E38: 9379480.8 | F38: 10861350 | G38: =VLOOKUP($C38,#REF!,2,0) -> #REF! | H38: =VLOOKUP($C38,#REF!,3,0) -> #REF! | I38: =VLOOKUP($C38,#REF!,4,0) -> #REF! | J38: =H38/G38-1 -> #REF! | K38: =I38/H38-1 -> #REF! | L38: =E38/D38-1 -> 0.25709308 | M38: =F38/E38-1 -> 0.15799054 | N38: =E38/H38-1 -> #REF! | O38: =F38/I38-1 -> #REF!
C39: PG | D39: 4102540 | E39: 8204323.3 | F39: 6852222.9 | G39: =VLOOKUP($C39,#REF!,2,0) -> #REF! | H39: =VLOOKUP($C39,#REF!,3,0) -> #REF! | I39: =VLOOKUP($C39,#REF!,4,0) -> #REF! | J39: =H39/G39-1 -> #REF! | K39: =I39/H39-1 -> #REF! | L39: =E39/D39-1 -> 0.99981557 | M39: =F39/E39-1 -> -0.16480341 | N39: =E39/H39-1 -> #REF! | O39: =F39/I39-1 -> #REF!
C40: MG Sticks | D40: 6560245 | E40: 7105048.5 | F40: 6048195 | G40: =VLOOKUP($C40,#REF!,2,0) -> #REF! | H40: =VLOOKUP($C40,#REF!,3,0) -> #REF! | I40: =VLOOKUP($C40,#REF!,4,0) -> #REF! | J40: =H40/G40-1 -> #REF! | K40: =I40/H40-1 -> #REF! | L40: =E40/D40-1 -> 0.083046212 | M40: =F40/E40-1 -> -0.14874684 | N40: =E40/H40-1 -> #REF! | O40: =F40/I40-1 -> #REF!
C41: EDF | D41: 4730331 | E41: 4886903 | F41: 4799210 | G41: =VLOOKUP($C41,#REF!,2,0) -> #REF! | H41: =VLOOKUP($C41,#REF!,3,0) -> #REF! | I41: =VLOOKUP($C41,#REF!,4,0) -> #REF! | J41: =H41/G41-1 -> #REF! | K41: =I41/H41-1 -> #REF! | L41: =E41/D41-1 -> 0.033099586 | M41: =F41/E41-1 -> -0.017944494 | N41: =E41/H41-1 -> #REF! | O41: =F41/I41-1 -> #REF!
C42: SP1 | D42: 3576233.6 | E42: 3915857 | F42: 4073579 | G42: =VLOOKUP($C42,#REF!,2,0) -> #REF! | H42: =VLOOKUP($C42,#REF!,3,0) -> #REF! | I42: =VLOOKUP($C42,#REF!,4,0) -> #REF! | J42: =H42/G42-1 -> #REF! | K42: =I42/H42-1 -> #REF! | L42: =E42/D42-1 -> 0.094966792 | M42: =F42/E42-1 -> 0.040277782 | N42: =E42/H42-1 -> #REF! | O42: =F42/I42-1 -> #REF!
C43: Facepieces | D43: 3277504 | E43: 4737327 | F43: 3860663 | G43: =VLOOKUP($C43,#REF!,2,0) -> #REF! | H43: =VLOOKUP($C43,#REF!,3,0) -> #REF! | I43: =VLOOKUP($C43,#REF!,4,0) -> #REF! | J43: =H43/G43-1 -> #REF! | K43: =I43/H43-1 -> #REF! | L43: =E43/D43-1 -> 0.44540693 | M43: =F43/E43-1 -> -0.18505456 | N43: =E43/H43-1 -> #REF! | O43: =F43/I43-1 -> #REF!
C44: ESS | D44: 2872170 | E44: 2505530.4 | F44: 2858577.6 | G44: =VLOOKUP($C44,#REF!,2,0) -> #REF! | H44: =VLOOKUP($C44,#REF!,3,0) -> #REF! | I44: =VLOOKUP($C44,#REF!,4,0) -> #REF! | J44: =H44/G44-1 -> #REF! | K44: =I44/H44-1 -> #REF! | L44: =E44/D44-1 -> -0.12765247 | M44: =F44/E44-1 -> 0.14090717 | N44: =E44/H44-1 -> #REF! | O44: =F44/I44-1 -> #REF!
C45: MBG | D45: 3656088 | E45: 3863294 | F45: 2789300 | G45: =VLOOKUP($C45,#REF!,2,0) -> #REF! | H45: =VLOOKUP($C45,#REF!,3,0) -> #REF! | I45: =VLOOKUP($C45,#REF!,4,0) -> #REF! | J45: =H45/G45-1 -> #REF! | K45: =I45/H45-1 -> #REF! | L45: =E45/D45-1 -> 0.056674238 | M45: =F45/E45-1 -> -0.27799955 | N45: =E45/H45-1 -> #REF! | O45: =F45/I45-1 -> #REF!
C46: Other | D46: 2597792 | E46: 1837585 | F46: 2241498.1 | G46: =VLOOKUP($C46,#REF!,2,0) -> #REF! | H46: =VLOOKUP($C46,#REF!,3,0) -> #REF! | I46: =VLOOKUP($C46,#REF!,4,0) -> #REF! | J46: =H46/G46-1 -> #REF! | K46: =I46/H46-1 -> #REF! | L46: =E46/D46-1 -> -0.29263582 | M46: =F46/E46-1 -> 0.21980651 | N46: =E46/H46-1 -> #REF! | O46: =F46/I46-1 -> #REF!
C47: Yasso Club | D47: 1931563 | E47: 2821581 | F47: 2142284.2 | G47: =VLOOKUP($C47,#REF!,2,0) -> #REF! | H47: =VLOOKUP($C47,#REF!,3,0) -> #REF! | I47: =VLOOKUP($C47,#REF!,4,0) -> #REF! | J47: =H47/G47-1 -> #REF! | K47: =I47/H47-1 -> #REF! | L47: =E47/D47-1 -> 0.46077607 | M47: =F47/E47-1 -> -0.24075043 | N47: =E47/H47-1 -> #REF! | O47: =F47/I47-1 -> #REF!
C48: BJ Bars | D48: 0 | E48: 190000 | F48: 1987500 | G48: =VLOOKUP($C48,#REF!,2,0) -> #REF! | H48: =VLOOKUP($C48,#REF!,3,0) -> #REF! | I48: =VLOOKUP($C48,#REF!,4,0) -> #REF! | J48: =H48/G48-1 -> #REF! | K48: =I48/H48-1 -> #REF! | L48: =E48/D48-1 -> #DIV/0! | M48: =F48/E48-1 -> 9.4605263 | N48: =E48/H48-1 -> #REF! | O48: =F48/I48-1 -> #REF!
C49: YS PTS | D49: 0 | E49: 313415 | F49: 1680000 | G49: =VLOOKUP($C49,#REF!,2,0) -> #REF! | H49: =VLOOKUP($C49,#REF!,3,0) -> #REF! | I49: =VLOOKUP($C49,#REF!,4,0) -> #REF! | J49: =H49/G49-1 -> #REF! | K49: =I49/H49-1 -> #REF! | L49: =E49/D49-1 -> #DIV/0! | M49: =F49/E49-1 -> 4.360305 | N49: =E49/H49-1 -> #REF! | O49: =F49/I49-1 -> #REF!
... C56: Yasso Sandwich | D56: 168614 | E56: 156824 | F56: 169253.5 | G56: =VLOOKUP($C56,#REF!,2,0) -> #REF! | H56: =VLOOKUP($C56,#REF!,3,0) -> #REF! | I56: =VLOOKUP($C56,#REF!,4,0) -> #REF! | J56: =H56/G56-1 -> #REF! | K56: =I56/H56-1 -> #REF! | L56: =E56/D56-1 -> -0.069923019 | M56: =F56/E56-1 -> 0.079257639 | N56: =E56/H56-1 -> #REF! | O56: =F56/I56-1 -> #REF!
C57: Grand Total | D57: 1.0983688e+08 | E57: 1.1578538e+08 | F57: 1.1428032e+08 | G57: =SUM(G35:G56) -> #REF! | H57: =SUM(H35:H56) -> #REF! | I57: =SUM(I35:I56) -> #REF! | J57: =H57/G57-1 -> #REF! | K57: =I57/H57-1 -> #REF! | L57: =E57/D57-1 -> 0.0541576 | M57: =F57/E57-1 -> -0.012998655 | N57: =E57/H57-1 -> #REF! | O57: =F57/I57-1 -> #REF!
C60: Type | D60: (All)
G61: Demand | J61: Demand | L61: Suppl | N61: Supp vs Dem
C62: Row Labels | D62: Sum of 2024 MRF12 | E62: Sum of 2025 MRF8 | F62: Sum of 2026 MRF8 | G62: 2024 | H62: 2025 | I62: 2026 | J62: 2025 | K62: 2026 | L62: 2025 | M62: 2026 | N62: 25 | O62: 26
B63: Litons | C63: 48oz | D63: 220972.61 | E63: 216373.92 | F63: 218079.11 | G63: =VLOOKUP($C63,#REF!,5,0) -> #REF! | H63: =VLOOKUP($C63,#REF!,6,0) -> #REF! | I63: =VLOOKUP($C63,#REF!,7,0) -> #REF! | J63: =H63/G63-1 -> #REF! | K63: =I63/H63-1 -> #REF! | L63: =E63/D63-1 -> -0.020811151 | M63: =F63/E63-1 -> 0.0078807697 | N63: =E63/H63-1 -> #REF! | O63: =F63/I63-1 -> #REF! | P63: Short vs demand in 25'
C64: BJ PTS | D64: 99782.115 | E64: 99621.005 | F64: 91323.976 | G64: =VLOOKUP($C64,#REF!,5,0) -> #REF! | H64: =VLOOKUP($C64,#REF!,6,0) -> #REF! | I64: =VLOOKUP($C64,#REF!,7,0) -> #REF! | J64: =H64/G64-1 -> #REF! | K64: =I64/H64-1 -> #REF! | L64: =E64/D64-1 -> -0.0016146154 | M64: =F64/E64-1 -> -0.083285939 | N64: =E64/H64-1 -> #REF! | O64: =F64/I64-1 -> #REF!
C65: EDF | D65: 42644.849 | E65: 44175.709 | F65: 43382.998 | G65: =VLOOKUP($C65,#REF!,5,0) -> #REF! | H65: =VLOOKUP($C65,#REF!,6,0) -> #REF! | I65: =VLOOKUP($C65,#REF!,7,0) -> #REF! | J65: =H65/G65-1 -> #REF! | K65: =I65/H65-1 -> #REF! | L65: =E65/D65-1 -> 0.035897884 | M65: =F65/E65-1 -> -0.017944494 | N65: =E65/H65-1 -> #REF! | O65: =F65/I65-1 -> #REF!
C66: TALENTI | D66: 42779.712 | E66: 39342.717 | F66: 41137.308 | G66: =VLOOKUP($C66,#REF!,5,0) -> #REF! | H66: =VLOOKUP($C66,#REF!,6,0) -> #REF! | I66: =VLOOKUP($C66,#REF!,7,0) -> #REF! | J66: =H66/G66-1 -> #REF! | K66: =I66/H66-1 -> #REF! | L66: =E66/D66-1 -> -0.080341691 | M66: =F66/E66-1 -> 0.045614308 | N66: =E66/H66-1 -> #REF! | O66: =F66/I66-1 -> #REF! | P66: Course Correction in 25'
C67: PG | D67: 20656.302 | E67: 41838.211 | F67: 34943.132 | G67: =VLOOKUP($C67,#REF!,5,0) -> #REF! | H67: =VLOOKUP($C67,#REF!,6,0) -> #REF! | I67: =VLOOKUP($C67,#REF!,7,0) -> #REF! | J67: =H67/G67-1 -> #REF! | K67: =I67/H67-1 -> #REF! | L67: =E67/D67-1 -> 1.0254453 | M67: =F67/E67-1 -> -0.16480341 | N67: =E67/H67-1 -> #REF! | O67: =F67/I67-1 -> #REF!
C68: Yasso Sticks | D68: 24920.026 | E68: 29634.51 | F68: 33730.291 | G68: =VLOOKUP($C68,#REF!,5,0) -> #REF! | H68: =VLOOKUP($C68,#REF!,6,0) -> #REF! | I68: =VLOOKUP($C68,#REF!,7,0) -> #REF! | J68: =H68/G68-1 -> #REF! | K68: =I68/H68-1 -> #REF! | L68: =E68/D68-1 -> 0.18918454 | M68: =F68/E68-1 -> 0.13820986 | N68: =E68/H68-1 -> #REF! | O68: =F68/I68-1 -> #REF!
C69: MG Sticks | D69: 16214.983 | E69: 16475.198 | F69: 16334.091 | G69: =VLOOKUP($C69,#REF!,5,0) -> #REF! | H69: =VLOOKUP($C69,#REF!,6,0) -> #REF! | I69: =VLOOKUP($C69,#REF!,7,0) -> #REF! | J69: =H69/G69-1 -> #REF! | K69: =I69/H69-1 -> #REF! | L69: =E69/D69-1 -> 0.016047827 | M69: =F69/E69-1 -> -0.0085648477 | N69: =E69/H69-1 -> #REF! | O69: =F69/I69-1 -> #REF!
C70: SP1 | D70: 13962.233 | E70: 13166.549 | F70: 14505.104 | G70: =VLOOKUP($C70,#REF!,5,0) -> #REF! | H70: =VLOOKUP($C70,#REF!,6,0) -> #REF! | I70: =VLOOKUP($C70,#REF!,7,0) -> #REF! | J70: =H70/G70-1 -> #REF! | K70: =I70/H70-1 -> #REF! | L70: =E70/D70-1 -> -0.056988275 | M70: =F70/E70-1 -> 0.1016633 | N70: =E70/H70-1 -> #REF! | O70: =F70/I70-1 -> #REF!
C71: ESS | D71: 11712.022 | E71: 11309.779 | F71: 13780.963 | G71: =VLOOKUP($C71,#REF!,5,0) -> #REF! | H71: =VLOOKUP($C71,#REF!,6,0) -> #REF! | I71: =VLOOKUP($C71,#REF!,7,0) -> #REF! | J71: =H71/G71-1 -> #REF! | K71: =I71/H71-1 -> #REF! | L71: =E71/D71-1 -> -0.034344477 | M71: =F71/E71-1 -> 0.21849978 | N71: =E71/H71-1 -> #REF! | O71: =F71/I71-1 -> #REF! | P71: Recoup Supply
C72: Other | D72: 7677.9931 | E72: 7169.9071 | F72: 10571.862 | G72: =VLOOKUP($C72,#REF!,5,0) -> #REF! | H72: =VLOOKUP($C72,#REF!,6,0) -> #REF! | I72: =VLOOKUP($C72,#REF!,7,0) -> #REF! | J72: =H72/G72-1 -> #REF! | K72: =I72/H72-1 -> #REF! | L72: =E72/D72-1 -> -0.06617432 | M72: =F72/E72-1 -> 0.47447686 | N72: =E72/H72-1 -> #REF! | O72: =F72/I72-1 -> #REF! | P72: Course Correct Inventory in 26'
C73: BJ Bars | D73: 0 | E73: 912 | F73: 9540 | G73: =VLOOKUP($C73,#REF!,5,0) -> #REF! | H73: =VLOOKUP($C73,#REF!,6,0) -> #REF! | I73: =VLOOKUP($C73,#REF!,7,0) -> #REF! | J73: =H73/G73-1 -> #REF! | K73: =I73/H73-1 -> #REF! | L73: =E73/D73-1 -> #DIV/0! | M73: =F73/E73-1 -> 9.4605263 | N73: =E73/H73-1 -> #REF! | O73: =F73/I73-1 -> #REF!
C74: MBG | D74: 12757.566 | E74: 13526.836 | F74: 9353.5934 | G74: =VLOOKUP($C74,#REF!,5,0) -> #REF! | H74: =VLOOKUP($C74,#REF!,6,0) -> #REF! | I74: =VLOOKUP($C74,#REF!,7,0) -> #REF! | J74: =H74/G74-1 -> #REF! | K74: =I74/H74-1 -> #REF! | L74: =E74/D74-1 -> 0.060299104 | M74: =F74/E74-1 -> -0.30851578 | N74: =E74/H74-1 -> #REF! | O74: =F74/I74-1 -> #REF!
C75: Facepieces | D75: 11553.296 | E75: 10422.617 | F75: 8266.1758 | G75: =VLOOKUP($C75,#REF!,5,0) -> #REF! | H75: =VLOOKUP($C75,#REF!,6,0) -> #REF! | I75: =VLOOKUP($C75,#REF!,7,0) -> #REF! | J75: =H75/G75-1 -> #REF! | K75: =I75/H75-1 -> #REF! | L75: =E75/D75-1 -> -0.097866353 | M75: =F75/E75-1 -> -0.20690018 | N75: =E75/H75-1 -> #REF! | O75: =F75/I75-1 -> #REF!
C76: YS PTS | D76: 0 | E76: 1038.0305 | F76: 5564.16 | G76: =VLOOKUP($C76,#REF!,5,0) -> #REF! | H76: =VLOOKUP($C76,#REF!,6,0) -> #REF! | I76: =VLOOKUP($C76,#REF!,7,0) -> #REF! | J76: =H76/G76-1 -> #REF! | K76: =I76/H76-1 -> #REF! | L76: =E76/D76-1 -> #DIV/0! | M76: =F76/E76-1 -> 4.360305 | N76: =E76/H76-1 -> #REF! | O76: =F76/I76-1 -> #REF!
C77: 2.4 Gal | D77: 4511.154 | E77: 4393.3133 | F77: 4780.8133 | G77: =VLOOKUP($C77,#REF!,5,0) -> #REF! | H77: =VLOOKUP($C77,#REF!,6,0) -> #REF! | I77: =VLOOKUP($C77,#REF!,7,0) -> #REF! | J77: =H77/G77-1 -> #REF! | K77: =I77/H77-1 -> #REF! | L77: =E77/D77-1 -> -0.026122069 | M77: =F77/E77-1 -> 0.088202225 | N77: =E77/H77-1 -> #REF! | O77: =F77/I77-1 -> #REF!
C78: Yasso Club | D78: 2399.0012 | E78: 4273.9515 | F78: 3320.5404 | G78: =VLOOKUP($C78,#REF!,5,0) -> #REF! | H78: =VLOOKUP($C78,#REF!,6,0) -> #REF! | I78: =VLOOKUP($C78,#REF!,7,0) -> #REF! | J78: =H78/G78-1 -> #REF! | K78: =I78/H78-1 -> #REF! | L78: =E78/D78-1 -> 0.7815545 | M78: =F78/E78-1 -> -0.22307483 | N78: =E78/H78-1 -> #REF! | O78: =F78/I78-1 -> #REF!
C79: B&J Cups | D79: 2317.5917 | E79: 3013.4835 | F79: 2426.9512 | G79: =VLOOKUP($C79,#REF!,5,0) -> #REF! | H79: =VLOOKUP($C79,#REF!,6,0) -> #REF! | I79: =VLOOKUP($C79,#REF!,7,0) -> #REF! | J79: =H79/G79-1 -> #REF! | K79: =I79/H79-1 -> #REF! | L79: =E79/D79-1 -> 0.30026506 | M79: =F79/E79-1 -> -0.19463598 | N79: =E79/H79-1 -> #REF! | O79: =F79/I79-1 -> #REF!
C80: KL Mini Cones | D80: 4372.8286 | E80: 2435.0779 | F80: 2069.4707 | G80: =VLOOKUP($C80,#REF!,5,0) -> #REF! | H80: =VLOOKUP($C80,#REF!,6,0) -> #REF! | I80: =VLOOKUP($C80,#REF!,7,0) -> #REF! | J80: =H80/G80-1 -> #REF! | K80: =I80/H80-1 -> #REF! | L80: =E80/D80-1 -> -0.44313439 | M80: =F80/E80-1 -> -0.15014187 | N80: =E80/H80-1 -> #REF! | O80: =F80/I80-1 -> #REF!
C81: EFW | D81: 4399.681 | E81: 1368.0072 | F81: 1452.4959 | G81: =VLOOKUP($C81,#REF!,5,0) -> #REF! | H81: =VLOOKUP($C81,#REF!,6,0) -> #REF! | I81: =VLOOKUP($C81,#REF!,7,0) -> #REF! | J81: =H81/G81-1 -> #REF! | K81: =I81/H81-1 -> #REF! | L81: =E81/D81-1 -> -0.68906673 | M81: =F81/E81-1 -> 0.061760385 | N81: =E81/H81-1 -> #REF! | O81: =F81/I81-1 -> #REF!
C82: Yasso Poppables | D82: 677.17066 | E82: 988.28096 | F82: 843.552 | G82: =VLOOKUP($C82,#REF!,5,0) -> #REF! | H82: =VLOOKUP($C82,#REF!,6,0) -> #REF! | I82: =VLOOKUP($C82,#REF!,7,0) -> #REF! | J82: =H82/G82-1 -> #REF! | K82: =I82/H82-1 -> #REF! | L82: =E82/D82-1 -> 0.45942673 | M82: =F82/E82-1 -> -0.14644516 | N82: =E82/H82-1 -> #REF! | O82: =F82/I82-1 -> #REF! | P82: Club in 2024
C83: Dough Bites | D83: 724.06357 | E83: 827.82833 | F83: 595.05582 | G83: =VLOOKUP($C83,#REF!,5,0) -> #REF! | H83: =VLOOKUP($C83,#REF!,6,0) -> #REF! | I83: =VLOOKUP($C83,#REF!,7,0) -> #REF! | J83: =H83/G83-1 -> #REF! | K83: =I83/H83-1 -> #REF! | L83: =E83/D83-1 -> 0.14330891 | M83: =F83/E83-1 -> -0.28118451 | N83: =E83/H83-1 -> #REF! | O83: =F83/I83-1 -> #REF!
C84: Yasso Sandwich | D84: 122.75099 | E84: 365.81178 | F84: 416.64868 | G84: =VLOOKUP($C84,#REF!,5,0) -> #REF! | H84: =VLOOKUP($C84,#REF!,6,0) -> #REF! | I84: =VLOOKUP($C84,#REF!,7,0) -> #REF! | J84: =H84/G84-1 -> #REF! | K84: =I84/H84-1 -> #REF! | L84: =E84/D84-1 -> 1.9801126 | M84: =F84/E84-1 -> 0.1389701 | N84: =E84/H84-1 -> #REF! | O84: =F84/I84-1 -> #REF!
C85: Grand Total | D85: 545157.95 | E85: 562672.74 | F85: 566418.3 | G85: =VLOOKUP($C85,#REF!,5,0) -> #REF! | H85: =VLOOKUP($C85,#REF!,6,0) -> #REF! | I85: =VLOOKUP($C85,#REF!,7,0) -> #REF! | J85: =H85/G85-1 -> #REF! | K85: =I85/H85-1 -> #REF! | L85: =E85/D85-1 -> 0.032127918 | M85: =F85/E85-1 -> 0.0066567144 | N85: =E85/H85-1 -> #REF! | O85: =F85/I85-1 -> #REF!
C88: 48oz | D88: =VLOOKUP($C88,$C$63:$F$85,2,0) -> 220972.61 | E88: =VLOOKUP($C88,$C$63:$F$85,3,0) -> 216373.92 | F88: =VLOOKUP($C88,$C$63:$F$85,4,0) -> 218079.11
C89: BJ PTS | D89: =VLOOKUP($C89,$C$63:$F$85,2,0) -> 99782.115 | E89: =VLOOKUP($C89,$C$63:$F$85,3,0) -> 99621.005 | F89: =VLOOKUP($C89,$C$63:$F$85,4,0) -> 91323.976
C90: TALENTI | D90: =VLOOKUP($C90,$C$63:$F$85,2,0) -> 42779.712 | E90: =VLOOKUP($C90,$C$63:$F$85,3,0) -> 39342.717 | F90: =VLOOKUP($C90,$C$63:$F$85,4,0) -> 41137.308
C91: Yasso Sticks | D91: =VLOOKUP($C91,$C$63:$F$85,2,0) -> 24920.026 | E91: =VLOOKUP($C91,$C$63:$F$85,3,0) -> 29634.51 | F91: =VLOOKUP($C91,$C$63:$F$85,4,0) -> 33730.291
C92: PG | D92: =VLOOKUP($C92,$C$63:$F$85,2,0) -> 20656.302 | E92: =VLOOKUP($C92,$C$63:$F$85,3,0) -> 41838.211 | F92: =VLOOKUP($C92,$C$63:$F$85,4,0) -> 34943.132
C93: MG Sticks | D93: =VLOOKUP($C93,$C$63:$F$85,2,0) -> 16214.983 | E93: =VLOOKUP($C93,$C$63:$F$85,3,0) -> 16475.198 | F93: =VLOOKUP($C93,$C$63:$F$85,4,0) -> 16334.091
C94: EDF | D94: =VLOOKUP($C94,$C$63:$F$85,2,0) -> 42644.849 | E94: =VLOOKUP($C94,$C$63:$F$85,3,0) -> 44175.709 | F94: =VLOOKUP($C94,$C$63:$F$85,4,0) -> 43382.998
C95: SP1 | D95: =VLOOKUP($C95,$C$63:$F$85,2,0) -> 13962.233 | E95: =VLOOKUP($C95,$C$63:$F$85,3,0) -> 13166.549 | F95: =VLOOKUP($C95,$C$63:$F$85,4,0) -> 14505.104
C96: Facepieces | D96: =VLOOKUP($C96,$C$63:$F$85,2,0) -> 11553.296 | E96: =VLOOKUP($C96,$C$63:$F$85,3,0) -> 10422.617 | F96: =VLOOKUP($C96,$C$63:$F$85,4,0) -> 8266.1758
C97: ESS | D97: =VLOOKUP($C97,$C$63:$F$85,2,0) -> 11712.022 | E97: =VLOOKUP($C97,$C$63:$F$85,3,0) -> 11309.779 | F97: =VLOOKUP($C97,$C$63:$F$85,4,0) -> 13780.963
C98: MBG | D98: =VLOOKUP($C98,$C$63:$F$85,2,0) -> 12757.566 | E98: =VLOOKUP($C98,$C$63:$F$85,3,0) -> 13526.836 | F98: =VLOOKUP($C98,$C$63:$F$85,4,0) -> 9353.5934
C99: Other | D99: =VLOOKUP($C99,$C$63:$F$85,2,0) -> 7677.9931 | E99: =VLOOKUP($C99,$C$63:$F$85,3,0) -> 7169.9071 | F99: =VLOOKUP($C99,$C$63:$F$85,4,0) -> 10571.862
... C109: Yasso Sandwich | D109: =VLOOKUP($C109,$C$63:$F$85,2,0) -> 122.75099 | E109: =VLOOKUP($C109,$C$63:$F$85,3,0) -> 365.81178 | F109: =VLOOKUP($C109,$C$63:$F$85,4,0) -> 416.64868
C111: 48oz | D111: =D88/D35 -> 0.0085185673 | E111: =E88/E35 -> 0.0085950534 | F111: =F88/F35 -> 0.00852
C112: BJ PTS | D112: =D89/D36 -> 0.0037809213 | E112: =E89/E36 -> 0.0037829964 | F112: =F89/F36 -> 0.003785344
C113: TALENTI | D113: =D90/D37 -> 0.0037527674 | E113: =E90/E37 -> 0.0037304497 | F113: =F90/F37 -> 0.0037384611
C114: Yasso Sticks | D114: =D91/D38 -> 0.0033399282 | E114: =E91/E38 -> 0.0031595043 | F114: =F91/F38 -> 0.003105534
C115: PG | D115: =D92/D39 -> 0.0050350033 | E115: =E92/E39 -> 0.0050995322 | F115: =F92/F39 -> 0.0050995322 | G115: Scribbler
C116: MG Sticks | D116: =D93/D40 -> 0.0024717039 | E116: =E93/E40 -> 0.0023188017 | F116: =F93/F40 -> 0.0027006555 | G116: CS more than MG
C117: EDF | D117: =D94/D41 -> 0.0090151934 | E117: =E94/E41 -> 0.0090396123 | F117: =F94/F41 -> 0.0090396123
C118: SP1 | D118: =D95/D42 -> 0.0039041726 | E118: =E95/E42 -> 0.0033623673 | F118: =F95/F42 -> 0.0035607764
C119: Facepieces | D119: =D96/D43 -> 0.0035250288 | E119: =E96/E43 -> 0.0022001051 | F119: =F96/F43 -> 0.0021411286
C120: ESS | D120: =D97/D44 -> 0.0040777608 | E120: =E97/E44 -> 0.0045139261 | F120: =F97/F44 -> 0.0048209163
C121: MBG | D121: =D98/D45 -> 0.0034894034 | E121: =E98/E45 -> 0.0035013736 | F121: =F98/F45 -> 0.0033533838
C122: Other | D122: =D99/D46 -> 0.0029555842 | E122: =E99/E46 -> 0.0039018098 | F122: =F99/F46 -> 0.0047164269
C123: Yasso Club | D123: =D100/D47 -> 0.001242 | E123: =E100/E47 -> 0.0015147364 | F123: =F100/F47 -> 0.00155
C124: BJ Bars | D124: =D101/D48 -> #DIV/0! | E124: =E101/E48 -> 0.0048 | F124: =F101/F48 -> 0.0048
C125: YS PTS | D125: =D102/D49 -> #DIV/0! | E125: =E102/E49 -> 0.003312 | F125: =F102/F49 -> 0.003312
...

Sheet Recap2
B2: Tonnage Recap
F3: Vs Prior
C4: MRF1 | D4: MRF2 | E4: MRF3 | F4: Litons | G4: %
B5: SIK | C5: 203 | D5: 205 | E5: ='Litons Post Attain'!P167/1000 -> 203.97838 | F5: =E5-D5 -> -1.0216206 | G5: =E5/D5-1 -> -0.0049835152
B6: COV | C6: 161 | D6: 166 | E6: ='Litons Post Attain'!P168/1000 -> 164.69916 | F6: =E6-D6 -> -1.3008368 | G6: =E6/D6-1 -> -0.0078363664
B7: VT | C7: 89 | D7: 90 | E7: ='Litons Post Attain'!P169/1000 -> 91.781613 | F7: =E7-D7 -> 1.7816133 | G7: =E7/D7-1 -> 0.019795704
B8: UL Sites | C8: 454 | D8: 461 | E8: ='Litons Post Attain'!P170/1000 -> 460.45916 | F8: =E8-D8 -> -0.5408441 | G8: =E8/D8-1 -> -0.0011731976
B9: CM | C9: 48 | D9: 54 | E9: ='Litons Post Attain'!P184/1000 -> 54.737552 | F9: =E9-D9 -> 0.7375524 | G9: =E9/D9-1 -> 0.013658378
B10: Import | C10: 26.028 | D10: =SUM('Litons Post Attain'!Q185:Q186)/1000 -> 26.431099 | E10: =SUM('Litons Post Attain'!P185:P186)/1000 -> 28.49724 | F10: =E10-D10 -> 2.0661412 | G10: =E10/D10-1 -> 0.078170838
B11: Total UL | C11: =SUM(C8:C10) -> 528.028 | D11: =SUM(D8:D10) -> 541.4311 | E11: =SUM(E8:E10) -> 543.69395 | F11: =E11-D11 -> 2.2628495 | G11: =E11/D11-1 -> 0.0041793858
B14: Pallet Positions
C15: Peak | D15: EOY | E15: Notes
B16: 2025 | C16: 113 | D16: 98
B17: 2026 LV | C17: 135 | D17: 95 | E17: With CM, Intransit, & Club volume we would be at 126 internally, just above 124
B20: Inventory
B21: 2025 | C21: 68.3
C22: MRF1 | D22: MRF2 | E22: MRF3
B23: Demand | C23: 530 | D23: 528 | E23: 527
B24: Suppl | C24: =C11 -> 528.028 | D24: =D11 -> 541.4311 | E24: =E11 -> 543.69395
B25: SCC's | C25: 1459 | D25: 1532 | E25: 1530
B26: 2026 | C26: 65.1 | D26: 75.2 | E26: 75.1
B27: vs YAG | C27: =C26-C21 -> -3.2 | D27: =D26-C21 -> 6.9 | E27: =E26-C21 -> 6.8
B28: Notes | C28: Error in calculation in MRF1

Sheet Cases post Attain
D1: 110 | E1: 110 | F1: 120 | G1: =SUM(D1:F1) -> 340 | H1: =G1*4 -> 1360
H2: =G1*3.5 -> 1190
B3: PLANT | C3: STA ALBANS | R3: Vs YAG | T3: Commentary
A4: Tech Rollup | B4: PLANT | C4: Row Labels | D4: Jan | E4: Feb | F4: Mar | G4: Apr | H4: May | I4: Jun | J4: Jul | K4: Aug | L4: Sep | M4: Oct | N4: Nov | O4: Dec | P4: 2026 MRF3 | Q4: 2026 MRF2 | R4: Difference | S4: % change | T4: Commentary | U4: 2025 Final
A5: 2.4 Gal | B5: 5914 | C5: 2.4 Gal | D5: =SUMIFS('2026'!$L:$L,'2026'!$J:$J,$B5&$C5,'2026'!$O:$O,D$4) -> 40870 | E5: =SUMIFS('2026'!$L:$L,'2026'!$J:$J,$B5&$C5,'2026'!$O:$O,E$4) -> 84448 | F5: =SUMIFS('2026'!$L:$L,'2026'!$J:$J,$B5&$C5,'2026'!$O:$O,F$4) -> 63514 | G5: =SUMIFS('2026'!$L:$L,'2026'!$J:$J,$B5&$C5,'2026'!$O:$O,G$4) -> 63648 | H5: =SUMIFS('2026'!$L:$L,'2026'!$J:$J,$B5&$C5,'2026'!$O:$O,H$4) -> 95999 | I5: =SUMIFS('2026'!$L:$L,'2026'!$J:$J,$B5&$C5,'2026'!$O:$O,I$4) -> 27404 | J5: =SUMIFS('2026'!$L:$L,'2026'!$J:$J,$B5&$C5,'2026'!$O:$O,J$4) -> 50830 | K5: =SUMIFS('2026'!$L:$L,'2026'!$J:$J,$B5&$C5,'2026'!$O:$O,K$4) -> 53040 | ... O5: =SUMIFS('2026'!$L:$L,'2026'!$J:$J,$B5&$C5,'2026'!$O:$O,O$4) -> 0 | P5: =SUM(D5:O5) -> 566385 | Q5: 504816.4 | R5: =P5-Q5 -> 61568.6 | S5: =IF(ISERROR(R5/Q5),"",R5/Q5) -> 0.12196236 | T5: Deman | U5: 469585
A6: Other | B6: 5914 | C6: Quarts | D6: =SUMIFS('2026'!$L:$L,'2026'!$J:$J,$B6&$C6,'2026'!$O:$O,D$4) -> 0 | E6: =SUMIFS('2026'!$L:$L,'2026'!$J:$J,$B6&$C6,'2026'!$O:$O,E$4) -> 0 | F6: =SUMIFS('2026'!$L:$L,'2026'!$J:$J,$B6&$C6,'2026'!$O:$O,F$4) -> 0 | G6: =SUMIFS('2026'!$L:$L,'2026'!$J:$J,$B6&$C6,'2026'!$O:$O,G$4) -> 0 | H6: =SUMIFS('2026'!$L:$L,'2026'!$J:$J,$B6&$C6,'2026'!$O:$O,H$4) -> 0 | I6: =SUMIFS('2026'!$L:$L,'2026'!$J:$J,$B6&$C6,'2026'!$O:$O,I$4) -> 0 | J6: =SUMIFS('2026'!$L:$L,'2026'!$J:$J,$B6&$C6,'2026'!$O:$O,J$4) -> 0 | K6: =SUMIFS('2026'!$L:$L,'2026'!$J:$J,$B6&$C6,'2026'!$O:$O,K$4) -> 0 | ... O6: =SUMIFS('2026'!$L:$L,'2026'!$J:$J,$B6&$C6,'2026'!$O:$O,O$4) -> 0 | P6: =SUM(D6:O6) -> 0 | Q6: 0 | R6: =P6-Q6 -> 0 | S6: =IF(ISERROR(R6/Q6),"",R6/Q6) | T6: Demand & Being Discontinued | U6: 321236
A7: BJ PTS | B7: 5914 | C7: PTS Exports | D7: =SUMIFS('2026'!$L:$L,'2026'!$J:$J,$B7&$C7,'2026'!$O:$O,D$4) -> 56422 | E7: =SUMIFS('2026'!$L:$L,'2026'!$J:$J,$B7&$C7,'2026'!$O:$O,E$4) -> 0 | F7: =SUMIFS('2026'!$L:$L,'2026'!$J:$J,$B7&$C7,'2026'!$O:$O,F$4) -> 76571 | G7: =SUMIFS('2026'!$L:$L,'2026'!$J:$J,$B7&$C7,'2026'!$O:$O,G$4) -> 32832 | H7: =SUMIFS('2026'!$L:$L,'2026'!$J:$J,$B7&$C7,'2026'!$O:$O,H$4) -> 62784 | I7: =SUMIFS('2026'!$L:$L,'2026'!$J:$J,$B7&$C7,'2026'!$O:$O,I$4) -> 0 | J7: =SUMIFS('2026'!$L:$L,'2026'!$J:$J,$B7&$C7,'2026'!$O:$O,J$4) -> 0 | K7: =SUMIFS('2026'!$L:$L,'2026'!$J:$J,$B7&$C7,'2026'!$O:$O,K$4) -> 0 | ... O7: =SUMIFS('2026'!$L:$L,'2026'!$J:$J,$B7&$C7,'2026'!$O:$O,O$4) -> 0 | P7: =SUM(D7:O7) -> 228609 | Q7: 147967.6 | R7: =P7-Q7 -> 80641.4 | S7: =IF(ISERROR(R7/Q7),"",R7/Q7) -> 0.54499363 | U7: 446691
A8: B&J Cups | B8: 5914 | C8: Cup Exports | D8: =SUMIFS('2026'!$L:$L,'2026'!$J:$J,$B8&$C8,'2026'!$O:$O,D$4) -> 0 | E8: =SUMIFS('2026'!$L:$L,'2026'!$J:$J,$B8&$C8,'2026'!$O:$O,E$4) -> 0 | F8: =SUMIFS('2026'!$L:$L,'2026'!$J:$J,$B8&$C8,'2026'!$O:$O,F$4) -> 0 | G8: =SUMIFS('2026'!$L:$L,'2026'!$J:$J,$B8&$C8,'2026'!$O:$O,G$4) -> 0 | H8: =SUMIFS('2026'!$L:$L,'2026'!$J:$J,$B8&$C8,'2026'!$O:$O,H$4) -> 0 | I8: =SUMIFS('2026'!$L:$L,'2026'!$J:$J,$B8&$C8,'2026'!$O:$O,I$4) -> 0 | J8: =SUMIFS('2026'!$L:$L,'2026'!$J:$J,$B8&$C8,'2026'!$O:$O,J$4) -> 0 | K8: =SUMIFS('2026'!$L:$L,'2026'!$J:$J,$B8&$C8,'2026'!$O:$O,K$4) -> 0 | ... O8: =SUMIFS('2026'!$L:$L,'2026'!$J:$J,$B8&$C8,'2026'!$O:$O,O$4) -> 0 | P8: =SUM(D8:O8) -> 0 | Q8: 0 | S8: =IF(ISERROR(R8/Q8),"",R8/Q8) | U8: 0
A9: 2.4 Gal | B9: 5914 | C9: Bulk Exports | D9: =SUMIFS('2026'!$L:$L,'2026'!$J:$J,$B9&$C9,'2026'!$O:$O,D$4) -> 0 | E9: =SUMIFS('2026'!$L:$L,'2026'!$J:$J,$B9&$C9,'2026'!$O:$O,E$4) -> 0 | F9: =SUMIFS('2026'!$L:$L,'2026'!$J:$J,$B9&$C9,'2026'!$O:$O,F$4) -> 0 | G9: =SUMIFS('2026'!$L:$L,'2026'!$J:$J,$B9&$C9,'2026'!$O:$O,G$4) -> 0 | H9: =SUMIFS('2026'!$L:$L,'2026'!$J:$J,$B9&$C9,'2026'!$O:$O,H$4) -> 0 | I9: =SUMIFS('2026'!$L:$L,'2026'!$J:$J,$B9&$C9,'2026'!$O:$O,I$4) -> 0 | J9: =SUMIFS('2026'!$L:$L,'2026'!$J:$J,$B9&$C9,'2026'!$O:$O,J$4) -> 0 | K9: =SUMIFS('2026'!$L:$L,'2026'!$J:$J,$B9&$C9,'2026'!$O:$O,K$4) -> 0 | ... O9: =SUMIFS('2026'!$L:$L,'2026'!$J:$J,$B9&$C9,'2026'!$O:$O,O$4) -> 0 | P9: =SUM(D9:O9) -> 0 | Q9: 0 | S9: =IF(ISERROR(R9/Q9),"",R9/Q9) | U9: 0
A10: B&J Cups | B10: 5914 | C10: B&J Cups | D10: =SUMIFS('2026'!$L:$L,'2026'!$J:$J,$B10&$C10,'2026'!$O:$O,D$4) -> 0 | E10: =SUMIFS('2026'!$L:$L,'2026'!$J:$J,$B10&$C10,'2026'!$O:$O,E$4) -> 0 | F10: =SUMIFS('2026'!$L:$L,'2026'!$J:$J,$B10&$C10,'2026'!$O:$O,F$4) -> 0 | G10: =SUMIFS('2026'!$L:$L,'2026'!$J:$J,$B10&$C10,'2026'!$O:$O,G$4) -> 0 | H10: =SUMIFS('2026'!$L:$L,'2026'!$J:$J,$B10&$C10,'2026'!$O:$O,H$4) -> 0 | I10: =SUMIFS('2026'!$L:$L,'2026'!$J:$J,$B10&$C10,'2026'!$O:$O,I$4) -> 0 | J10: =SUMIFS('2026'!$L:$L,'2026'!$J:$J,$B10&$C10,'2026'!$O:$O,J$4) -> 0 | K10: =SUMIFS('2026'!$L:$L,'2026'!$J:$J,$B10&$C10,'2026'!$O:$O,K$4) -> 0 | ... O10: =SUMIFS('2026'!$L:$L,'2026'!$J:$J,$B10&$C10,'2026'!$O:$O,O$4) -> 0 | P10: =SUM(D10:O10) -> 0 | Q10: 0 | R10: =P10-Q10 -> 0 | S10: =IF(ISERROR(R10/Q10),"",R10/Q10) | U10: 0
A11: B&J Cups | B11: 5914 | C11: B&J Dog Treat | D11: =SUMIFS('2026'!$L:$L,'2026'!$J:$J,$B11&$C11,'2026'!$O:$O,D$4) -> 0 | E11: =SUMIFS('2026'!$L:$L,'2026'!$J:$J,$B11&$C11,'2026'!$O:$O,E$4) -> 0 | F11: =SUMIFS('2026'!$L:$L,'2026'!$J:$J,$B11&$C11,'2026'!$O:$O,F$4) -> 0 | G11: =SUMIFS('2026'!$L:$L,'2026'!$J:$J,$B11&$C11,'2026'!$O:$O,G$4) -> 0 | H11: =SUMIFS('2026'!$L:$L,'2026'!$J:$J,$B11&$C11,'2026'!$O:$O,H$4) -> 0 | I11: =SUMIFS('2026'!$L:$L,'2026'!$J:$J,$B11&$C11,'2026'!$O:$O,I$4) -> 0 | J11: =SUMIFS('2026'!$L:$L,'2026'!$J:$J,$B11&$C11,'2026'!$O:$O,J$4) -> 0 | K11: =SUMIFS('2026'!$L:$L,'2026'!$J:$J,$B11&$C11,'2026'!$O:$O,K$4) -> 0 | ... O11: =SUMIFS('2026'!$L:$L,'2026'!$J:$J,$B11&$C11,'2026'!$O:$O,O$4) -> 0 | P11: =SUM(D11:O11) -> 0 | Q11: 0 | R11: =P11-Q11 -> 0 | S11: =IF(ISERROR(R11/Q11),"",R11/Q11) | U11: 0
A12: SP1 | B12: 5914 | C12: PTS - BR | D12: =SUMIFS('2026'!$L:$L,'2026'!$J:$J,$B12&$C12,'2026'!$O:$O,D$4) -> 0 | E12: =SUMIFS('2026'!$L:$L,'2026'!$J:$J,$B12&$C12,'2026'!$O:$O,E$4) -> 0 | F12: =SUMIFS('2026'!$L:$L,'2026'!$J:$J,$B12&$C12,'2026'!$O:$O,F$4) -> 0 | G12: =SUMIFS('2026'!$L:$L,'2026'!$J:$J,$B12&$C12,'2026'!$O:$O,G$4) -> 0 | H12: =SUMIFS('2026'!$L:$L,'2026'!$J:$J,$B12&$C12,'2026'!$O:$O,H$4) -> 0 | I12: =SUMIFS('2026'!$L:$L,'2026'!$J:$J,$B12&$C12,'2026'!$O:$O,I$4) -> 0 | J12: =SUMIFS('2026'!$L:$L,'2026'!$J:$J,$B12&$C12,'2026'!$O:$O,J$4) -> 0 | K12: =SUMIFS('2026'!$L:$L,'2026'!$J:$J,$B12&$C12,'2026'!$O:$O,K$4) -> 0 | ... O12: =SUMIFS('2026'!$L:$L,'2026'!$J:$J,$B12&$C12,'2026'!$O:$O,O$4) -> 0 | P12: =SUM(D12:O12) -> 0 | Q12: 0 | S12: =IF(ISERROR(R12/Q12),"",R12/Q12) | U12: 0
A13: BJ PTS | B13: 5914 | C13: BJ PTS | D13: =SUMIFS('2026'!$L:$L,'2026'!$J:$J,$B13&$C13,'2026'!$O:$O,D$4) -> 1069362 | E13: =SUMIFS('2026'!$L:$L,'2026'!$J:$J,$B13&$C13,'2026'!$O:$O,E$4) -> 1516469 | F13: =SUMIFS('2026'!$L:$L,'2026'!$J:$J,$B13&$C13,'2026'!$O:$O,F$4) -> 1784134.4 | G13: =SUMIFS('2026'!$L:$L,'2026'!$J:$J,$B13&$C13,'2026'!$O:$O,G$4) -> 1248718 | H13: =SUMIFS('2026'!$L:$L,'2026'!$J:$J,$B13&$C13,'2026'!$O:$O,H$4) -> 1009508 | I13: =SUMIFS('2026'!$L:$L,'2026'!$J:$J,$B13&$C13,'2026'!$O:$O,I$4) -> 1203110.4 | J13: =SUMIFS('2026'!$L:$L,'2026'!$J:$J,$B13&$C13,'2026'!$O:$O,J$4) -> 1266432 | K13: =SUMIFS('2026'!$L:$L,'2026'!$J:$J,$B13&$C13,'2026'!$O:$O,K$4) -> 1393075.2 | ... O13: =SUMIFS('2026'!$L:$L,'2026'!$J:$J,$B13&$C13,'2026'!$O:$O,O$4) -> 1106265.6 | P13: =SUM(D13:O13) -> 15236204 | Q13: 15379174 | R13: =P13-Q13 -> -142969.6 | S13: =IF(ISERROR(R13/Q13),"",R13/Q13) -> -0.0092963121 | U13: 15309960
C14: Total St. Albans | D14: =SUM(D5:D13) -> 1166654 | E14: =SUM(E5:E13) -> 1600917 | F14: =SUM(F5:F13) -> 1924219.4 | G14: =SUM(G5:G13) -> 1345198 | H14: =SUM(H5:H13) -> 1168291 | I14: =SUM(I5:I13) -> 1230514.4 | J14: =SUM(J5:J13) -> 1317262 | K14: =SUM(K5:K13) -> 1446115.2 | ... O14: =SUM(O5:O13) -> 1106265.6 | P14: =SUM(D14:O14) -> 16031198 | Q14: 16031958 | R14: =SUM(R5:R13) -> -759.6 | S14: =IF(ISERROR(R14/Q14),"",R14/Q14) -> -4.7380364e-05 | U14: 16547472
D15: =SUM(D13,D7) -> 1125784 | E15: =SUM(E13,E7) -> 1516469 | F15: =SUM(F13,F7) -> 1860705.4 | G15: =SUM(G13,G7) -> 1281550 | H15: =SUM(H13,H7) -> 1072292 | I15: =SUM(I13,I7) -> 1203110.4 | J15: =SUM(J13,J7) -> 1266432 | K15: =SUM(K13,K7) -> 1393075.2 | ... O15: =SUM(O13,O7) -> 1106265.6
C16: WATERBURY | R16: Vs Last Cycle | T16: Commentary
C17: Row Labels | D17: Jan | E17: Feb | F17: Mar | G17: Apr | H17: May | I17: Jun | J17: Jul | K17: Aug | L17: Sep | M17: Oct | N17: Nov | O17: Dec | P17: =P$4 -> 2026 MRF3 | Q17: 2026 MRF2 | R17: =R$4 -> Difference | S17: =S$4 -> % change | U17: 2025 Final
A18: Other | B18: 5911 | C18: 1 Gal | D18: =SUMIFS('2026'!$L:$L,'2026'!$J:$J,$B18&$C18,'2026'!$O:$O,D$4) -> 0 | E18: =SUMIFS('2026'!$L:$L,'2026'!$J:$J,$B18&$C18,'2026'!$O:$O,E$4) -> 0 | F18: =SUMIFS('2026'!$L:$L,'2026'!$J:$J,$B18&$C18,'2026'!$O:$O,F$4) -> 0 | G18: =SUMIFS('2026'!$L:$L,'2026'!$J:$J,$B18&$C18,'2026'!$O:$O,G$4) -> 0 | H18: =SUMIFS('2026'!$L:$L,'2026'!$J:$J,$B18&$C18,'2026'!$O:$O,H$4) -> 0 | I18: =SUMIFS('2026'!$L:$L,'2026'!$J:$J,$B18&$C18,'2026'!$O:$O,I$4) -> 0 | J18: =SUMIFS('2026'!$L:$L,'2026'!$J:$J,$B18&$C18,'2026'!$O:$O,J$4) -> 0 | K18: =SUMIFS('2026'!$L:$L,'2026'!$J:$J,$B18&$C18,'2026'!$O:$O,K$4) -> 0 | ... O18: =SUMIFS('2026'!$L:$L,'2026'!$J:$J,$B18&$C18,'2026'!$O:$O,O$4) -> 0 | P18: =SUM(D18:O18) -> 0 | Q18: 0 | S18: =IF(ISERROR(R18/Q18),"",R18/Q18) | U18: 0
A19: Other | B19: 5911 | C19: QTS | D19: =SUMIFS('2026'!$L:$L,'2026'!$J:$J,$B19&$C19,'2026'!$O:$O,D$4) -> 0 | E19: =SUMIFS('2026'!$L:$L,'2026'!$J:$J,$B19&$C19,'2026'!$O:$O,E$4) -> 0 | F19: =SUMIFS('2026'!$L:$L,'2026'!$J:$J,$B19&$C19,'2026'!$O:$O,F$4) -> 0 | G19: =SUMIFS('2026'!$L:$L,'2026'!$J:$J,$B19&$C19,'2026'!$O:$O,G$4) -> 0 | H19: =SUMIFS('2026'!$L:$L,'2026'!$J:$J,$B19&$C19,'2026'!$O:$O,H$4) -> 0 | I19: =SUMIFS('2026'!$L:$L,'2026'!$J:$J,$B19&$C19,'2026'!$O:$O,I$4) -> 0 | J19: =SUMIFS('2026'!$L:$L,'2026'!$J:$J,$B19&$C19,'2026'!$O:$O,J$4) -> 0 | K19: =SUMIFS('2026'!$L:$L,'2026'!$J:$J,$B19&$C19,'2026'!$O:$O,K$4) -> 0 | ... O19: =SUMIFS('2026'!$L:$L,'2026'!$J:$J,$B19&$C19,'2026'!$O:$O,O$4) -> 0 | P19: =SUM(D19:O19) -> 0 | Q19: 0 | S19: =IF(ISERROR(R19/Q19),"",R19/Q19) | U19: 0
A20: BJ PTS | B20: 5911 | C20: PTS Exports | D20: =SUMIFS('2026'!$L:$L,'2026'!$J:$J,$B20&$C20,'2026'!$O:$O,D$4) -> 11510 | E20: =SUMIFS('2026'!$L:$L,'2026'!$J:$J,$B20&$C20,'2026'!$O:$O,E$4) -> 8824 | F20: =SUMIFS('2026'!$L:$L,'2026'!$J:$J,$B20&$C20,'2026'!$O:$O,F$4) -> 13545 | G20: =SUMIFS('2026'!$L:$L,'2026'!$J:$J,$B20&$C20,'2026'!$O:$O,G$4) -> 11520 | H20: =SUMIFS('2026'!$L:$L,'2026'!$J:$J,$B20&$C20,'2026'!$O:$O,H$4) -> 0 | I20: =SUMIFS('2026'!$L:$L,'2026'!$J:$J,$B20&$C20,'2026'!$O:$O,I$4) -> 0 | J20: =SUMIFS('2026'!$L:$L,'2026'!$J:$J,$B20&$C20,'2026'!$O:$O,J$4) -> 0 | K20: =SUMIFS('2026'!$L:$L,'2026'!$J:$J,$B20&$C20,'2026'!$O:$O,K$4) -> 0 | ... O20: =SUMIFS('2026'!$L:$L,'2026'!$J:$J,$B20&$C20,'2026'!$O:$O,O$4) -> 0 | P20: =SUM(D20:O20) -> 45399 | Q20: 46254 | R20: =P20-Q20 -> -855 | S20: =IF(ISERROR(R20/Q20),"",R20/Q20) -> -0.018484888 | U20: 271877
A21: BJ PTS | B21: 5911 | C21: BJ PTS | D21: =SUMIFS('2026'!$L:$L,'2026'!$J:$J,$B21&$C21,'2026'!$O:$O,D$4) -> 626144 | E21: =SUMIFS('2026'!$L:$L,'2026'!$J:$J,$B21&$C21,'2026'!$O:$O,E$4) -> 736400 | F21: =SUMIFS('2026'!$L:$L,'2026'!$J:$J,$B21&$C21,'2026'!$O:$O,F$4) -> 941614 | G21: =SUMIFS('2026'!$L:$L,'2026'!$J:$J,$B21&$C21,'2026'!$O:$O,G$4) -> 702620 | H21: =SUMIFS('2026'!$L:$L,'2026'!$J:$J,$B21&$C21,'2026'!$O:$O,H$4) -> 783750 | I21: =SUMIFS('2026'!$L:$L,'2026'!$J:$J,$B21&$C21,'2026'!$O:$O,I$4) -> 721920 | J21: =SUMIFS('2026'!$L:$L,'2026'!$J:$J,$B21&$C21,'2026'!$O:$O,J$4) -> 763611.43 | K21: =SUMIFS('2026'!$L:$L,'2026'!$J:$J,$B21&$C21,'2026'!$O:$O,K$4) -> 768000 | ... O21: =SUMIFS('2026'!$L:$L,'2026'!$J:$J,$B21&$C21,'2026'!$O:$O,O$4) -> 400000 | P21: =SUM(D21:O21) -> 7384059.4 | Q21: 7054006.6 | R21: =P21-Q21 -> 330052.86 | S21: =IF(ISERROR(R21/Q21),"",R21/Q21) -> 0.046789417 | U21: 8237828
C22: Total Waterbury | D22: =SUM(D18:D21) -> 637654 | E22: =SUM(E18:E21) -> 745224 | F22: =SUM(F18:F21) -> 955159 | G22: =SUM(G18:G21) -> 714140 | H22: =SUM(H18:H21) -> 783750 | I22: =SUM(I18:I21) -> 721920 | J22: =SUM(J18:J21) -> 763611.43 | K22: =SUM(K18:K21) -> 768000 | ... P22: =SUM(P18:P21) -> 7429458.4 | Q22: 7100260.6 | R22: =SUM(R18:R21) -> 329197.86 | S22: =IF(ISERROR(R22/Q22),"",R22/Q22) -> 0.046364194 | U22: 8509705
C24: SIKESTON | R24: Vs Last Cycle | T24: Commentary
C25: Row Labels | D25: Jan | E25: Feb | F25: Mar | G25: Apr | H25: May | I25: Jun | J25: Jul | K25: Aug | L25: Sep | M25: Oct | N25: Nov | O25: Dec | P25: =P$4 -> 2026 MRF3 | Q25: 2026 MRF2 | R25: =R$4 -> Difference | S25: =S$4 -> % change | U25: 2025 Final
A26: 48oz | B26: 2904 | C26: 48oz | D26: =SUMIFS('2026'!$L:$L,'2026'!$J:$J,$B26&$C26,'2026'!$O:$O,D$4) -> 907813 | E26: =SUMIFS('2026'!$L:$L,'2026'!$J:$J,$B26&$C26,'2026'!$O:$O,E$4) -> 1057884 | F26: =SUMIFS('2026'!$L:$L,'2026'!$J:$J,$B26&$C26,'2026'!$O:$O,F$4) -> 1317294.1 | G26: =SUMIFS('2026'!$L:$L,'2026'!$J:$J,$B26&$C26,'2026'!$O:$O,G$4) -> 1118647 | H26: =SUMIFS('2026'!$L:$L,'2026'!$J:$J,$B26&$C26,'2026'!$O:$O,H$4) -> 983240 | I26: =SUMIFS('2026'!$L:$L,'2026'!$J:$J,$B26&$C26,'2026'!$O:$O,I$4) -> 985241.42 | J26: =SUMIFS('2026'!$L:$L,'2026'!$J:$J,$B26&$C26,'2026'!$O:$O,J$4) -> 1021731.8 | K26: =SUMIFS('2026'!$L:$L,'2026'!$J:$J,$B26&$C26,'2026'!$O:$O,K$4) -> 1094712.7 | ... O26: =SUMIFS('2026'!$L:$L,'2026'!$J:$J,$B26&$C26,'2026'!$O:$O,O$4) -> 646771.84 | P26: =SUM(D26:O26) -> 11581679 | Q26: 11630678 | R26: =P26-Q26 -> -48999.723 | S26: =IF(ISERROR(R26/Q26),"",R26/Q26) -> -0.004212972 | T26: =P26/46 -> 251775.62 | U26: 12284789
A27: EDF | B27: 2904 | C27: EDF | D27: =SUMIFS('2026'!$L:$L,'2026'!$J:$J,$B27&$C27,'2026'!$O:$O,D$4) -> 44810 | E27: =SUMIFS('2026'!$L:$L,'2026'!$J:$J,$B27&$C27,'2026'!$O:$O,E$4) -> 55315 | F27: =SUMIFS('2026'!$L:$L,'2026'!$J:$J,$B27&$C27,'2026'!$O:$O,F$4) -> 85838.48 | G27: =SUMIFS('2026'!$L:$L,'2026'!$J:$J,$B27&$C27,'2026'!$O:$O,G$4) -> 72576 | H27: =SUMIFS('2026'!$L:$L,'2026'!$J:$J,$B27&$C27,'2026'!$O:$O,H$4) -> 62208 | I27: =SUMIFS('2026'!$L:$L,'2026'!$J:$J,$B27&$C27,'2026'!$O:$O,I$4) -> 0 | J27: =SUMIFS('2026'!$L:$L,'2026'!$J:$J,$B27&$C27,'2026'!$O:$O,J$4) -> 0 | K27: =SUMIFS('2026'!$L:$L,'2026'!$J:$J,$B27&$C27,'2026'!$O:$O,K$4) -> 0 | ... O27: =SUMIFS('2026'!$L:$L,'2026'!$J:$J,$B27&$C27,'2026'!$O:$O,O$4) -> 0 | P27: =SUM(D27:O27) -> 320747.48 | Q27: 358058.64 | R27: =P27-Q27 -> -37311.16 | S27: =IF(ISERROR(R27/Q27),"",R27/Q27) -> -0.10420405 | U27: 799237
A28: BJ Bars | B28: 2904 | C28: BJ Bars | D28: =SUMIFS('2026'!$L:$L,'2026'!$J:$J,$B28&$C28,'2026'!$O:$O,D$4) -> 0 | E28: =SUMIFS('2026'!$L:$L,'2026'!$J:$J,$B28&$C28,'2026'!$O:$O,E$4) -> 0 | F28: =SUMIFS('2026'!$L:$L,'2026'!$J:$J,$B28&$C28,'2026'!$O:$O,F$4) -> 0 | G28: =SUMIFS('2026'!$L:$L,'2026'!$J:$J,$B28&$C28,'2026'!$O:$O,G$4) -> 0 | H28: =SUMIFS('2026'!$L:$L,'2026'!$J:$J,$B28&$C28,'2026'!$O:$O,H$4) -> 0 | I28: =SUMIFS('2026'!$L:$L,'2026'!$J:$J,$B28&$C28,'2026'!$O:$O,I$4) -> 0 | J28: =SUMIFS('2026'!$L:$L,'2026'!$J:$J,$B28&$C28,'2026'!$O:$O,J$4) -> 0 | K28: =SUMIFS('2026'!$L:$L,'2026'!$J:$J,$B28&$C28,'2026'!$O:$O,K$4) -> 0 | ... O28: =SUMIFS('2026'!$L:$L,'2026'!$J:$J,$B28&$C28,'2026'!$O:$O,O$4) -> 0 | P28: =SUM(D28:O28) -> 0 | Q28: 0 | S28: =IF(ISERROR(R28/Q28),"",R28/Q28) | U28: 0
A29: Other | B29: 2904 | C29: Other | D29: =SUMIFS('2026'!$L:$L,'2026'!$J:$J,$B29&$C29,'2026'!$O:$O,D$4) -> 0 | E29: =SUMIFS('2026'!$L:$L,'2026'!$J:$J,$B29&$C29,'2026'!$O:$O,E$4) -> 85224 | F29: =SUMIFS('2026'!$L:$L,'2026'!$J:$J,$B29&$C29,'2026'!$O:$O,F$4) -> 15 | G29: =SUMIFS('2026'!$L:$L,'2026'!$J:$J,$B29&$C29,'2026'!$O:$O,G$4) -> 40320 | H29: =SUMIFS('2026'!$L:$L,'2026'!$J:$J,$B29&$C29,'2026'!$O:$O,H$4) -> 63360 | I29: =SUMIFS('2026'!$L:$L,'2026'!$J:$J,$B29&$C29,'2026'!$O:$O,I$4) -> 0 | J29: =SUMIFS('2026'!$L:$L,'2026'!$J:$J,$B29&$C29,'2026'!$O:$O,J$4) -> 16703.85 | K29: =SUMIFS('2026'!$L:$L,'2026'!$J:$J,$B29&$C29,'2026'!$O:$O,K$4) -> 22271.8 | ... O29: =SUMIFS('2026'!$L:$L,'2026'!$J:$J,$B29&$C29,'2026'!$O:$O,O$4) -> 22271.8 | P29: =SUM(D29:O29) -> 315543.55 | Q29: 281009.5 | R29: =P29-Q29 -> 34534.05 | S29: =IF(ISERROR(R29/Q29),"",R29/Q29) -> 0.12289282 | U29: 0
A30: MBG | B30: 2904 | C30: MBG | D30: =SUMIFS('2026'!$L:$L,'2026'!$J:$J,$B30&$C30,'2026'!$O:$O,D$4) -> 55878 | E30: =SUMIFS('2026'!$L:$L,'2026'!$J:$J,$B30&$C30,'2026'!$O:$O,E$4) -> 76823 | F30: =SUMIFS('2026'!$L:$L,'2026'!$J:$J,$B30&$C30,'2026'!$O:$O,F$4) -> 81797.88 | G30: =SUMIFS('2026'!$L:$L,'2026'!$J:$J,$B30&$C30,'2026'!$O:$O,G$4) -> 92832 | H30: =SUMIFS('2026'!$L:$L,'2026'!$J:$J,$B30&$C30,'2026'!$O:$O,H$4) -> 69120 | I30: =SUMIFS('2026'!$L:$L,'2026'!$J:$J,$B30&$C30,'2026'!$O:$O,I$4) -> 80750 | J30: =SUMIFS('2026'!$L:$L,'2026'!$J:$J,$B30&$C30,'2026'!$O:$O,J$4) -> 92862.5 | K30: =SUMIFS('2026'!$L:$L,'2026'!$J:$J,$B30&$C30,'2026'!$O:$O,K$4) -> 88825 | ... O30: =SUMIFS('2026'!$L:$L,'2026'!$J:$J,$B30&$C30,'2026'!$O:$O,O$4) -> 0 | P30: =SUM(D30:O30) -> 808463.38 | Q30: 806336.32 | R30: =P30-Q30 -> 2127.06 | S30: =IF(ISERROR(R30/Q30),"",R30/Q30) -> 0.0026379315 | U30: 745276
A31: MG Sticks | B31: 2904 | C31: MG Sticks | D31: =SUMIFS('2026'!$L:$L,'2026'!$J:$J,$B31&$C31,'2026'!$O:$O,D$4) -> 543661 | E31: =SUMIFS('2026'!$L:$L,'2026'!$J:$J,$B31&$C31,'2026'!$O:$O,E$4) -> 675319 | F31: =SUMIFS('2026'!$L:$L,'2026'!$J:$J,$B31&$C31,'2026'!$O:$O,F$4) -> 705455 | G31: =SUMIFS('2026'!$L:$L,'2026'!$J:$J,$B31&$C31,'2026'!$O:$O,G$4) -> 955824 | H31: =SUMIFS('2026'!$L:$L,'2026'!$J:$J,$B31&$C31,'2026'!$O:$O,H$4) -> 839424 | I31: =SUMIFS('2026'!$L:$L,'2026'!$J:$J,$B31&$C31,'2026'!$O:$O,I$4) -> 694925 | J31: =SUMIFS('2026'!$L:$L,'2026'!$J:$J,$B31&$C31,'2026'!$O:$O,J$4) -> 711075 | K31: =SUMIFS('2026'!$L:$L,'2026'!$J:$J,$B31&$C31,'2026'!$O:$O,K$4) -> 676875 | ... O31: =SUMIFS('2026'!$L:$L,'2026'!$J:$J,$B31&$C31,'2026'!$O:$O,O$4) -> 0 | P31: =SUM(D31:O31) -> 6511133 | Q31: 6678576 | R31: =P31-Q31 -> -167442.96 | S31: =IF(ISERROR(R31/Q31),"",R31/Q31) -> -0.025071656 | U31: 7080128
A32: MG Sticks | B32: 2904 | C32: TAL NV | D32: =SUMIFS('2026'!$L:$L,'2026'!$J:$J,$B32&$C32,'2026'!$O:$O,D$4) -> 0 | E32: =SUMIFS('2026'!$L:$L,'2026'!$J:$J,$B32&$C32,'2026'!$O:$O,E$4) -> 0 | F32: =SUMIFS('2026'!$L:$L,'2026'!$J:$J,$B32&$C32,'2026'!$O:$O,F$4) -> 0 | G32: =SUMIFS('2026'!$L:$L,'2026'!$J:$J,$B32&$C32,'2026'!$O:$O,G$4) -> 0 | H32: =SUMIFS('2026'!$L:$L,'2026'!$J:$J,$B32&$C32,'2026'!$O:$O,H$4) -> 0 | I32: =SUMIFS('2026'!$L:$L,'2026'!$J:$J,$B32&$C32,'2026'!$O:$O,I$4) -> 0 | J32: =SUMIFS('2026'!$L:$L,'2026'!$J:$J,$B32&$C32,'2026'!$O:$O,J$4) -> 0 | K32: =SUMIFS('2026'!$L:$L,'2026'!$J:$J,$B32&$C32,'2026'!$O:$O,K$4) -> 0 | ... O32: =SUMIFS('2026'!$L:$L,'2026'!$J:$J,$B32&$C32,'2026'!$O:$O,O$4) -> 0 | P32: =SUM(D32:O32) -> 0 | Q32: 0 | R32: =P32-Q32 -> 0 | S32: =IF(ISERROR(R32/Q32),"",R32/Q32) | U32: 120379
A33: Yasso Sticks | B33: 2904 | C33: Yasso Sticks | D33: =SUMIFS('2026'!$L:$L,'2026'!$J:$J,$B33&$C33,'2026'!$O:$O,D$4) -> 313143 | E33: =SUMIFS('2026'!$L:$L,'2026'!$J:$J,$B33&$C33,'2026'!$O:$O,E$4) -> 380320 | F33: =SUMIFS('2026'!$L:$L,'2026'!$J:$J,$B33&$C33,'2026'!$O:$O,F$4) -> 294111 | G33: =SUMIFS('2026'!$L:$L,'2026'!$J:$J,$B33&$C33,'2026'!$O:$O,G$4) -> 296208 | H33: =SUMIFS('2026'!$L:$L,'2026'!$J:$J,$B33&$C33,'2026'!$O:$O,H$4) -> 288000 | I33: =SUMIFS('2026'!$L:$L,'2026'!$J:$J,$B33&$C33,'2026'!$O:$O,I$4) -> 275310 | J33: =SUMIFS('2026'!$L:$L,'2026'!$J:$J,$B33&$C33,'2026'!$O:$O,J$4) -> 285142.5 | K33: =SUMIFS('2026'!$L:$L,'2026'!$J:$J,$B33&$C33,'2026'!$O:$O,K$4) -> 304807.5 | ... O33: =SUMIFS('2026'!$L:$L,'2026'!$J:$J,$B33&$C33,'2026'!$O:$O,O$4) -> 265477.5 | P33: =SUM(D33:O33) -> 3528449.5 | Q33: 3402261.5 | R33: =P33-Q33 -> 126188 | S33: =IF(ISERROR(R33/Q33),"",R33/Q33) -> 0.037089448 | U33: 1294124
A34: SP1 | B34: 2904 | C34: PTS | D34: =SUMIFS('2026'!$L:$L,'2026'!$J:$J,$B34&$C34,'2026'!$O:$O,D$4) -> 22671 | E34: =SUMIFS('2026'!$L:$L,'2026'!$J:$J,$B34&$C34,'2026'!$O:$O,E$4) -> 0 | F34: =SUMIFS('2026'!$L:$L,'2026'!$J:$J,$B34&$C34,'2026'!$O:$O,F$4) -> 69122.16 | G34: =SUMIFS('2026'!$L:$L,'2026'!$J:$J,$B34&$C34,'2026'!$O:$O,G$4) -> 0 | H34: =SUMIFS('2026'!$L:$L,'2026'!$J:$J,$B34&$C34,'2026'!$O:$O,H$4) -> 66528 | I34: =SUMIFS('2026'!$L:$L,'2026'!$J:$J,$B34&$C34,'2026'!$O:$O,I$4) -> 43690.388 | J34: =SUMIFS('2026'!$L:$L,'2026'!$J:$J,$B34&$C34,'2026'!$O:$O,J$4) -> 48544.875 | K34: =SUMIFS('2026'!$L:$L,'2026'!$J:$J,$B34&$C34,'2026'!$O:$O,K$4) -> 53399.363 | ... O34: =SUMIFS('2026'!$L:$L,'2026'!$J:$J,$B34&$C34,'2026'!$O:$O,O$4) -> 22500 | P34: =SUM(D34:O34) -> 506263.81 | Q34: 507623.88 | R34: =P34-Q34 -> -1360.0722 | S34: =IF(ISERROR(R34/Q34),"",R34/Q34) -> -0.0026792912 | U34: 366575
A35: BJ PTS | B35: 2904 | C35: BJ PTS | D35: =SUMIFS('2026'!$L:$L,'2026'!$J:$J,$B35&$C35,'2026'!$O:$O,D$4) -> 146152 | E35: =SUMIFS('2026'!$L:$L,'2026'!$J:$J,$B35&$C35,'2026'!$O:$O,E$4) -> 35832 | F35: =SUMIFS('2026'!$L:$L,'2026'!$J:$J,$B35&$C35,'2026'!$O:$O,F$4) -> 323036.25 | G35: =SUMIFS('2026'!$L:$L,'2026'!$J:$J,$B35&$C35,'2026'!$O:$O,G$4) -> 235125 | H35: =SUMIFS('2026'!$L:$L,'2026'!$J:$J,$B35&$C35,'2026'!$O:$O,H$4) -> 136800 | I35: =SUMIFS('2026'!$L:$L,'2026'!$J:$J,$B35&$C35,'2026'!$O:$O,I$4) -> 211212 | J35: =SUMIFS('2026'!$L:$L,'2026'!$J:$J,$B35&$C35,'2026'!$O:$O,J$4) -> 189960 | K35: =SUMIFS('2026'!$L:$L,'2026'!$J:$J,$B35&$C35,'2026'!$O:$O,K$4) -> 0 | ... O35: =SUMIFS('2026'!$L:$L,'2026'!$J:$J,$B35&$C35,'2026'!$O:$O,O$4) -> 0 | P35: =SUM(D35:O35) -> 1281833.2 | Q35: 1405397 | R35: =P35-Q35 -> -123563.75 | S35: =IF(ISERROR(R35/Q35),"",R35/Q35) -> -0.087920886 | U35: 1488407
A36: SP1 | B36: 2904 | C36: Sundaes | D36: =SUMIFS('2026'!$L:$L,'2026'!$J:$J,$B36&$C36,'2026'!$O:$O,D$4) -> 33616 | E36: =SUMIFS('2026'!$L:$L,'2026'!$J:$J,$B36&$C36,'2026'!$O:$O,E$4) -> 81737 | F36: =SUMIFS('2026'!$L:$L,'2026'!$J:$J,$B36&$C36,'2026'!$O:$O,F$4) -> 45972 | G36: =SUMIFS('2026'!$L:$L,'2026'!$J:$J,$B36&$C36,'2026'!$O:$O,G$4) -> 110880 | H36: =SUMIFS('2026'!$L:$L,'2026'!$J:$J,$B36&$C36,'2026'!$O:$O,H$4) -> 149688 | I36: =SUMIFS('2026'!$L:$L,'2026'!$J:$J,$B36&$C36,'2026'!$O:$O,I$4) -> 95017.104 | J36: =SUMIFS('2026'!$L:$L,'2026'!$J:$J,$B36&$C36,'2026'!$O:$O,J$4) -> 105574.56 | K36: =SUMIFS('2026'!$L:$L,'2026'!$J:$J,$B36&$C36,'2026'!$O:$O,K$4) -> 116132.02 | ... O36: =SUMIFS('2026'!$L:$L,'2026'!$J:$J,$B36&$C36,'2026'!$O:$O,O$4) -> 90000 | P36: =SUM(D36:O36) -> 1113929.6 | Q36: 1147570 | R36: =P36-Q36 -> -33640.371 | S36: =IF(ISERROR(R36/Q36),"",R36/Q36) -> -0.029314439 | U36: 961930
A37: YS PTS | B37: 2904 | C37: YS PTS | D37: =SUMIFS('2026'!$L:$L,'2026'!$J:$J,$B37&$C37,'2026'!$O:$O,D$4) -> -344 | E37: =SUMIFS('2026'!$L:$L,'2026'!$J:$J,$B37&$C37,'2026'!$O:$O,E$4) -> 121156 | F37: =SUMIFS('2026'!$L:$L,'2026'!$J:$J,$B37&$C37,'2026'!$O:$O,F$4) -> -15 | G37: =SUMIFS('2026'!$L:$L,'2026'!$J:$J,$B37&$C37,'2026'!$O:$O,G$4) -> 0 | H37: =SUMIFS('2026'!$L:$L,'2026'!$J:$J,$B37&$C37,'2026'!$O:$O,H$4) -> 0 | I37: =SUMIFS('2026'!$L:$L,'2026'!$J:$J,$B37&$C37,'2026'!$O:$O,I$4) -> 40500 | J37: =SUMIFS('2026'!$L:$L,'2026'!$J:$J,$B37&$C37,'2026'!$O:$O,J$4) -> 75000 | K37: =SUMIFS('2026'!$L:$L,'2026'!$J:$J,$B37&$C37,'2026'!$O:$O,K$4) -> 215000 | ... O37: =SUMIFS('2026'!$L:$L,'2026'!$J:$J,$B37&$C37,'2026'!$O:$O,O$4) -> 160000 | P37: =SUM(D37:O37) -> 1196297 | Q37: 733461.12 | R37: =P37-Q37 -> 462835.88 | S37: =IF(ISERROR(R37/Q37),"",R37/Q37) -> 0.63102988 | U37: 77109
A38: SP1 | B38: 2904 | C38: Topped | D38: =SUMIFS('2026'!$L:$L,'2026'!$J:$J,$B38&$C38,'2026'!$O:$O,D$4) -> 121965 | E38: =SUMIFS('2026'!$L:$L,'2026'!$J:$J,$B38&$C38,'2026'!$O:$O,E$4) -> 162834 | F38: =SUMIFS('2026'!$L:$L,'2026'!$J:$J,$B38&$C38,'2026'!$O:$O,F$4) -> 211985 | G38: =SUMIFS('2026'!$L:$L,'2026'!$J:$J,$B38&$C38,'2026'!$O:$O,G$4) -> 193248 | H38: =SUMIFS('2026'!$L:$L,'2026'!$J:$J,$B38&$C38,'2026'!$O:$O,H$4) -> 120384 | I38: =SUMIFS('2026'!$L:$L,'2026'!$J:$J,$B38&$C38,'2026'!$O:$O,I$4) -> 144960.99 | J38: =SUMIFS('2026'!$L:$L,'2026'!$J:$J,$B38&$C38,'2026'!$O:$O,J$4) -> 161067.76 | K38: =SUMIFS('2026'!$L:$L,'2026'!$J:$J,$B38&$C38,'2026'!$O:$O,K$4) -> 177174.54 | ... O38: =SUMIFS('2026'!$L:$L,'2026'!$J:$J,$B38&$C38,'2026'!$O:$O,O$4) -> 193500 | P38: =SUM(D38:O38) -> 1929094.7 | Q38: 2043949.4 | R38: =P38-Q38 -> -114854.76 | S38: =IF(ISERROR(R38/Q38),"",R38/Q38) -> -0.056192563 | U38: 2182170
A39: TALENTI | B39: 2904 | C39: TALENTI | D39: =SUMIFS('2026'!$L:$L,'2026'!$J:$J,$B39&$C39,'2026'!$O:$O,D$4) -> 787404 | E39: =SUMIFS('2026'!$L:$L,'2026'!$J:$J,$B39&$C39,'2026'!$O:$O,E$4) -> 936622 | F39: =SUMIFS('2026'!$L:$L,'2026'!$J:$J,$B39&$C39,'2026'!$O:$O,F$4) -> 1043191.2 | G39: =SUMIFS('2026'!$L:$L,'2026'!$J:$J,$B39&$C39,'2026'!$O:$O,G$4) -> 1240608 | H39: =SUMIFS('2026'!$L:$L,'2026'!$J:$J,$B39&$C39,'2026'!$O:$O,H$4) -> 912864 | I39: =SUMIFS('2026'!$L:$L,'2026'!$J:$J,$B39&$C39,'2026'!$O:$O,I$4) -> 1000719.4 | J39: =SUMIFS('2026'!$L:$L,'2026'!$J:$J,$B39&$C39,'2026'!$O:$O,J$4) -> 1000719.4 | K39: =SUMIFS('2026'!$L:$L,'2026'!$J:$J,$B39&$C39,'2026'!$O:$O,K$4) -> 1107939.3 | ... O39: =SUMIFS('2026'!$L:$L,'2026'!$J:$J,$B39&$C39,'2026'!$O:$O,O$4) -> 678950.95 | P39: =SUM(D39:O39) -> 11044130 | Q39: 11023727 | R39: =P39-Q39 -> 20402.886 | S39: =IF(ISERROR(R39/Q39),"",R39/Q39) -> 0.0018508156 | U39: 10467549
A40: PG | B40: 2904 | C40: PG | D40: =SUMIFS('2026'!$L:$L,'2026'!$J:$J,$B40&$C40,'2026'!$O:$O,D$4) -> 82580 | E40: =SUMIFS('2026'!$L:$L,'2026'!$J:$J,$B40&$C40,'2026'!$O:$O,E$4) -> 118064 | F40: =SUMIFS('2026'!$L:$L,'2026'!$J:$J,$B40&$C40,'2026'!$O:$O,F$4) -> 110940 | G40: =SUMIFS('2026'!$L:$L,'2026'!$J:$J,$B40&$C40,'2026'!$O:$O,G$4) -> 137088 | H40: =SUMIFS('2026'!$L:$L,'2026'!$J:$J,$B40&$C40,'2026'!$O:$O,H$4) -> 134784 | I40: =SUMIFS('2026'!$L:$L,'2026'!$J:$J,$B40&$C40,'2026'!$O:$O,I$4) -> 172900 | J40: =SUMIFS('2026'!$L:$L,'2026'!$J:$J,$B40&$C40,'2026'!$O:$O,J$4) -> 186675 | K40: =SUMIFS('2026'!$L:$L,'2026'!$J:$J,$B40&$C40,'2026'!$O:$O,K$4) -> 190950 | ... O40: =SUMIFS('2026'!$L:$L,'2026'!$J:$J,$B40&$C40,'2026'!$O:$O,O$4) -> 0 | P40: =SUM(D40:O40) -> 1566706 | Q40: 1666302.6 | R40: =P40-Q40 -> -99596.6 | S40: =IF(ISERROR(R40/Q40),"",R40/Q40) -> -0.059771016 | U40: 1801702
C41: Total Sikeston | D41: =SUM(D26:D40) -> 3059349 | E41: =SUM(E26:E40) -> 3787130 | F41: =SUM(F26:F40) -> 4288743.1 | G41: =SUM(G26:G40) -> 4493356 | H41: =SUM(H26:H40) -> 3826400 | I41: =SUM(I26:I40) -> 3745226.3 | J41: =SUM(J26:J40) -> 3895057.2 | K41: =SUM(K26:K40) -> 4048087.2 | ... P41: =SUM(P26:P40) -> 41704270 | Q41: 41684951 | R41: =SUM(R26:R40) -> 19318.483 | S41: =IF(ISERROR(R41/Q41),"",R41/Q41) -> 0.00046344022 | U41: 39669375
D42: =SUM(D34,D36,D38) -> 178252 | E42: =SUM(E34,E36,E38) -> 244571 | F42: =SUM(F34,F36,F38) -> 327079.16 | G42: =SUM(G34,G36,G38) -> 304128 | H42: =SUM(H34,H36,H38) -> 336600 | I42: =SUM(I34,I36,I38) -> 283668.48 | J42: =SUM(J34,J36,J38) -> 315187.2 | K42: =SUM(K34,K36,K38) -> 346705.92 | ... O42: =SUM(O34,O36,O38) -> 306000
C43: COVINGTON | R43: Vs Last Cycle | T43: Commentary
C44: Row Labels | D44: Jan | E44: Feb | F44: Mar | G44: Apr | H44: May | I44: Jun | J44: Jul | K44: Aug | L44: Sep | M44: Oct | N44: Nov | O44: Dec | P44: =P$4 -> 2026 MRF3 | Q44: 2026 MRF2 | R44: =R$4 -> Difference | S44: =S$4 -> % change | U44: 2025 Final
A45: 48oz | B45: 1352 | C45: 48oz | D45: =SUMIFS('2026'!$L:$L,'2026'!$J:$J,$B45&$C45,'2026'!$O:$O,D$4) -> 948937 | E45: =SUMIFS('2026'!$L:$L,'2026'!$J:$J,$B45&$C45,'2026'!$O:$O,E$4) -> 1155184 | F45: =SUMIFS('2026'!$L:$L,'2026'!$J:$J,$B45&$C45,'2026'!$O:$O,F$4) -> 1577496.3 | G45: =SUMIFS('2026'!$L:$L,'2026'!$J:$J,$B45&$C45,'2026'!$O:$O,G$4) -> 1188645 | H45: =SUMIFS('2026'!$L:$L,'2026'!$J:$J,$B45&$C45,'2026'!$O:$O,H$4) -> 977502.24 | I45: =SUMIFS('2026'!$L:$L,'2026'!$J:$J,$B45&$C45,'2026'!$O:$O,I$4) -> 1023799.3 | J45: =SUMIFS('2026'!$L:$L,'2026'!$J:$J,$B45&$C45,'2026'!$O:$O,J$4) -> 1061717.8 | K45: =SUMIFS('2026'!$L:$L,'2026'!$J:$J,$B45&$C45,'2026'!$O:$O,K$4) -> 1239290.7 | ... O45: =SUMIFS('2026'!$L:$L,'2026'!$J:$J,$B45&$C45,'2026'!$O:$O,O$4) -> 569198.69 | P45: =SUM(D45:O45) -> 11928540 | Q45: 11898960 | R45: =P45-Q45 -> 29579.754 | S45: =IF(ISERROR(R45/Q45),"",R45/Q45) -> 0.0024859109 | U45: 12445043
A46: Other | B46: 1352 | C46: 56oz | D46: =SUMIFS('2026'!$L:$L,'2026'!$J:$J,$B46&$C46,'2026'!$O:$O,D$4) -> 0 | E46: =SUMIFS('2026'!$L:$L,'2026'!$J:$J,$B46&$C46,'2026'!$O:$O,E$4) -> 0 | F46: =SUMIFS('2026'!$L:$L,'2026'!$J:$J,$B46&$C46,'2026'!$O:$O,F$4) -> 0 | G46: =SUMIFS('2026'!$L:$L,'2026'!$J:$J,$B46&$C46,'2026'!$O:$O,G$4) -> 0 | H46: =SUMIFS('2026'!$L:$L,'2026'!$J:$J,$B46&$C46,'2026'!$O:$O,H$4) -> 0 | I46: =SUMIFS('2026'!$L:$L,'2026'!$J:$J,$B46&$C46,'2026'!$O:$O,I$4) -> 0 | J46: =SUMIFS('2026'!$L:$L,'2026'!$J:$J,$B46&$C46,'2026'!$O:$O,J$4) -> 0 | K46: =SUMIFS('2026'!$L:$L,'2026'!$J:$J,$B46&$C46,'2026'!$O:$O,K$4) -> 0 | ... O46: =SUMIFS('2026'!$L:$L,'2026'!$J:$J,$B46&$C46,'2026'!$O:$O,O$4) -> 0 | P46: =SUM(D46:O46) -> 0 | Q46: 0 | R46: =P46-Q46 -> 0 | S46: =IF(ISERROR(R46/Q46),"",R46/Q46) | U46: 0
A47: Other | B47: 1352 | C47: 64oz | D47: =SUMIFS('2026'!$L:$L,'2026'!$J:$J,$B47&$C47,'2026'!$O:$O,D$4) -> 0 | E47: =SUMIFS('2026'!$L:$L,'2026'!$J:$J,$B47&$C47,'2026'!$O:$O,E$4) -> 0 | F47: =SUMIFS('2026'!$L:$L,'2026'!$J:$J,$B47&$C47,'2026'!$O:$O,F$4) -> 0 | G47: =SUMIFS('2026'!$L:$L,'2026'!$J:$J,$B47&$C47,'2026'!$O:$O,G$4) -> 0 | H47: =SUMIFS('2026'!$L:$L,'2026'!$J:$J,$B47&$C47,'2026'!$O:$O,H$4) -> 0 | I47: =SUMIFS('2026'!$L:$L,'2026'!$J:$J,$B47&$C47,'2026'!$O:$O,I$4) -> 0 | J47: =SUMIFS('2026'!$L:$L,'2026'!$J:$J,$B47&$C47,'2026'!$O:$O,J$4) -> 0 | K47: =SUMIFS('2026'!$L:$L,'2026'!$J:$J,$B47&$C47,'2026'!$O:$O,K$4) -> 0 | ... O47: =SUMIFS('2026'!$L:$L,'2026'!$J:$J,$B47&$C47,'2026'!$O:$O,O$4) -> 0 | P47: =SUM(D47:O47) -> 0 | Q47: 0 | R47: =P47-Q47 -> 0 | S47: =IF(ISERROR(R47/Q47),"",R47/Q47) | U47: 0
A48: EDF | B48: 1352 | C48: EDF | D48: =SUMIFS('2026'!$L:$L,'2026'!$J:$J,$B48&$C48,'2026'!$O:$O,D$4) -> 373150 | E48: =SUMIFS('2026'!$L:$L,'2026'!$J:$J,$B48&$C48,'2026'!$O:$O,E$4) -> 459113 | F48: =SUMIFS('2026'!$L:$L,'2026'!$J:$J,$B48&$C48,'2026'!$O:$O,F$4) -> 572625.44 | G48: =SUMIFS('2026'!$L:$L,'2026'!$J:$J,$B48&$C48,'2026'!$O:$O,G$4) -> 479059.2 | H48: =SUMIFS('2026'!$L:$L,'2026'!$J:$J,$B48&$C48,'2026'!$O:$O,H$4) -> 422976 | I48: =SUMIFS('2026'!$L:$L,'2026'!$J:$J,$B48&$C48,'2026'!$O:$O,I$4) -> 395580 | J48: =SUMIFS('2026'!$L:$L,'2026'!$J:$J,$B48&$C48,'2026'!$O:$O,J$4) -> 414105 | K48: =SUMIFS('2026'!$L:$L,'2026'!$J:$J,$B48&$C48,'2026'!$O:$O,K$4) -> 377311.5 | ... O48: =SUMIFS('2026'!$L:$L,'2026'!$J:$J,$B48&$C48,'2026'!$O:$O,O$4) -> 45000 | P48: =SUM(D48:O48) -> 4330717.6 | Q48: 4411870.4 | R48: =P48-Q48 -> -81152.747 | S48: =IF(ISERROR(R48/Q48),"",R48/Q48) -> -0.018394182 | U48: 4190845
A49: EFW | B49: 1352 | C49: EFW | D49: =SUMIFS('2026'!$L:$L,'2026'!$J:$J,$B49&$C49,'2026'!$O:$O,D$4) -> 0 | E49: =SUMIFS('2026'!$L:$L,'2026'!$J:$J,$B49&$C49,'2026'!$O:$O,E$4) -> 0 | F49: =SUMIFS('2026'!$L:$L,'2026'!$J:$J,$B49&$C49,'2026'!$O:$O,F$4) -> 0 | G49: =SUMIFS('2026'!$L:$L,'2026'!$J:$J,$B49&$C49,'2026'!$O:$O,G$4) -> 0 | H49: =SUMIFS('2026'!$L:$L,'2026'!$J:$J,$B49&$C49,'2026'!$O:$O,H$4) -> 0 | I49: =SUMIFS('2026'!$L:$L,'2026'!$J:$J,$B49&$C49,'2026'!$O:$O,I$4) -> 0 | J49: =SUMIFS('2026'!$L:$L,'2026'!$J:$J,$B49&$C49,'2026'!$O:$O,J$4) -> 0 | K49: =SUMIFS('2026'!$L:$L,'2026'!$J:$J,$B49&$C49,'2026'!$O:$O,K$4) -> 0 | ... O49: =SUMIFS('2026'!$L:$L,'2026'!$J:$J,$B49&$C49,'2026'!$O:$O,O$4) -> 0 | P49: =SUM(D49:O49) -> 0 | Q49: 0 | R49: =P49-Q49 -> 0 | S49: =IF(ISERROR(R49/Q49),"",R49/Q49) | U49: 419854
A50: MBG | B50: 1352 | C50: MBG | D50: =SUMIFS('2026'!$L:$L,'2026'!$J:$J,$B50&$C50,'2026'!$O:$O,D$4) -> 147490 | E50: =SUMIFS('2026'!$L:$L,'2026'!$J:$J,$B50&$C50,'2026'!$O:$O,E$4) -> 193235 | F50: =SUMIFS('2026'!$L:$L,'2026'!$J:$J,$B50&$C50,'2026'!$O:$O,F$4) -> 258555.2 | G50: =SUMIFS('2026'!$L:$L,'2026'!$J:$J,$B50&$C50,'2026'!$O:$O,G$4) -> 331776 | H50: =SUMIFS('2026'!$L:$L,'2026'!$J:$J,$B50&$C50,'2026'!$O:$O,H$4) -> 355008 | I50: =SUMIFS('2026'!$L:$L,'2026'!$J:$J,$B50&$C50,'2026'!$O:$O,I$4) -> 263150 | J50: =SUMIFS('2026'!$L:$L,'2026'!$J:$J,$B50&$C50,'2026'!$O:$O,J$4) -> 233795 | K50: =SUMIFS('2026'!$L:$L,'2026'!$J:$J,$B50&$C50,'2026'!$O:$O,K$4) -> 223630 | ... O50: =SUMIFS('2026'!$L:$L,'2026'!$J:$J,$B50&$C50,'2026'!$O:$O,O$4) -> 0 | P50: =SUM(D50:O50) -> 2322199.2 | Q50: 2270310.6 | R50: =P50-Q50 -> 51888.62 | S50: =IF(ISERROR(R50/Q50),"",R50/Q50) -> 0.022855296 | U50: 2792362
A51: PG | B51: 1352 | C51: PG | D51: =SUMIFS('2026'!$L:$L,'2026'!$J:$J,$B51&$C51,'2026'!$O:$O,D$4) -> 158880 | E51: =SUMIFS('2026'!$L:$L,'2026'!$J:$J,$B51&$C51,'2026'!$O:$O,E$4) -> 290587 | F51: =SUMIFS('2026'!$L:$L,'2026'!$J:$J,$B51&$C51,'2026'!$O:$O,F$4) -> 262928 | G51: =SUMIFS('2026'!$L:$L,'2026'!$J:$J,$B51&$C51,'2026'!$O:$O,G$4) -> 263347.2 | H51: =SUMIFS('2026'!$L:$L,'2026'!$J:$J,$B51&$C51,'2026'!$O:$O,H$4) -> 234432 | I51: =SUMIFS('2026'!$L:$L,'2026'!$J:$J,$B51&$C51,'2026'!$O:$O,I$4) -> 237500 | J51: =SUMIFS('2026'!$L:$L,'2026'!$J:$J,$B51&$C51,'2026'!$O:$O,J$4) -> 349600 | K51: =SUMIFS('2026'!$L:$L,'2026'!$J:$J,$B51&$C51,'2026'!$O:$O,K$4) -> 334400 | ... O51: =SUMIFS('2026'!$L:$L,'2026'!$J:$J,$B51&$C51,'2026'!$O:$O,O$4) -> 0 | P51: =SUM(D51:O51) -> 2970049.2 | Q51: 3082661.4 | R51: =P51-Q51 -> -112612.16 | S51: =IF(ISERROR(R51/Q51),"",R51/Q51) -> -0.036530824 | U51: 2907794
A52: TALENTI | B52: 1352 | C52: Talenti | D52: =SUMIFS('2026'!$L:$L,'2026'!$J:$J,$B52&$C52,'2026'!$O:$O,D$4) -> 0 | E52: =SUMIFS('2026'!$L:$L,'2026'!$J:$J,$B52&$C52,'2026'!$O:$O,E$4) -> 0 | F52: =SUMIFS('2026'!$L:$L,'2026'!$J:$J,$B52&$C52,'2026'!$O:$O,F$4) -> 0 | G52: =SUMIFS('2026'!$L:$L,'2026'!$J:$J,$B52&$C52,'2026'!$O:$O,G$4) -> 0 | H52: =SUMIFS('2026'!$L:$L,'2026'!$J:$J,$B52&$C52,'2026'!$O:$O,H$4) -> 0 | I52: =SUMIFS('2026'!$L:$L,'2026'!$J:$J,$B52&$C52,'2026'!$O:$O,I$4) -> 0 | J52: =SUMIFS('2026'!$L:$L,'2026'!$J:$J,$B52&$C52,'2026'!$O:$O,J$4) -> 0 | K52: =SUMIFS('2026'!$L:$L,'2026'!$J:$J,$B52&$C52,'2026'!$O:$O,K$4) -> 0 | ... O52: =SUMIFS('2026'!$L:$L,'2026'!$J:$J,$B52&$C52,'2026'!$O:$O,O$4) -> 0 | P52: =SUM(D52:O52) -> 0 | Q52: 0 | R52: =P52-Q52 -> 0 | S52: =IF(ISERROR(R52/Q52),"",R52/Q52) | U52: 0
C53: Total Covington | D53: =SUM(D45:D52) -> 1628457 | E53: =SUM(E45:E52) -> 2098119 | F53: =SUM(F45:F52) -> 2671605 | G53: =SUM(G45:G52) -> 2262827.4 | H53: =SUM(H45:H52) -> 1989918.2 | I53: =SUM(I45:I52) -> 1920029.3 | J53: =SUM(J45:J52) -> 2059217.8 | K53: =SUM(K45:K52) -> 2174632.2 | ... P53: =SUM(P45:P52) -> 21551506 | Q53: 21663802 | R53: =SUM(R45:R52) -> -112296.53 | S53: =IF(ISERROR(R53/Q53),"",R53/Q53) -> -0.0051836022 | U53: 22755898
C55: 3PM | R55: Vs Last Cycle | T55: Commentary
C56: Row Labels | D56: Jan | E56: Feb | F56: Mar | G56: Apr | H56: May | I56: Jun | J56: Jul | K56: Aug | L56: Sep | M56: Oct | N56: Nov | O56: Dec | P56: =P$4 -> 2026 MRF3 | Q56: 2026 MRF2 | R56: =R$4 -> Difference | S56: =S$4 -> % change | U56: 2025 Final
A57: B&J Cups | B57: 1712 | C57: B&J Cups | D57: =SUMIFS('2026'!$L:$L,'2026'!$J:$J,$B57&$C57,'2026'!$O:$O,D$4) -> 99137 | E57: =SUMIFS('2026'!$L:$L,'2026'!$J:$J,$B57&$C57,'2026'!$O:$O,E$4) -> 46867 | F57: =SUMIFS('2026'!$L:$L,'2026'!$J:$J,$B57&$C57,'2026'!$O:$O,F$4) -> 142438.8 | G57: =SUMIFS('2026'!$L:$L,'2026'!$J:$J,$B57&$C57,'2026'!$O:$O,G$4) -> 58052.16 | H57: =SUMIFS('2026'!$L:$L,'2026'!$J:$J,$B57&$C57,'2026'!$O:$O,H$4) -> 0 | I57: =SUMIFS('2026'!$L:$L,'2026'!$J:$J,$B57&$C57,'2026'!$O:$O,I$4) -> 20511.36 | J57: =SUMIFS('2026'!$L:$L,'2026'!$J:$J,$B57&$C57,'2026'!$O:$O,J$4) -> 49464 | K57: =SUMIFS('2026'!$L:$L,'2026'!$J:$J,$B57&$C57,'2026'!$O:$O,K$4) -> 102677.76 | ... O57: =SUMIFS('2026'!$L:$L,'2026'!$J:$J,$B57&$C57,'2026'!$O:$O,O$4) -> 29790.72 | P57: =SUM(D57:O57) -> 751330.8 | Q57: 706803.36 | R57: =P57-Q57 -> 44527.44 | S57: =IF(ISERROR(R57/Q57),"",R57/Q57) -> 0.062998342 | U57: 1393892
A58: ESS | B58: 1712 | C58: ESS | D58: =SUMIFS('2026'!$L:$L,'2026'!$J:$J,$B58&$C58,'2026'!$O:$O,D$4) -> 57951 | E58: =SUMIFS('2026'!$L:$L,'2026'!$J:$J,$B58&$C58,'2026'!$O:$O,E$4) -> 33203 | F58: =SUMIFS('2026'!$L:$L,'2026'!$J:$J,$B58&$C58,'2026'!$O:$O,F$4) -> 99584.52 | G58: =SUMIFS('2026'!$L:$L,'2026'!$J:$J,$B58&$C58,'2026'!$O:$O,G$4) -> 109608 | H58: =SUMIFS('2026'!$L:$L,'2026'!$J:$J,$B58&$C58,'2026'!$O:$O,H$4) -> 195417.6 | I58: =SUMIFS('2026'!$L:$L,'2026'!$J:$J,$B58&$C58,'2026'!$O:$O,I$4) -> 109900.8 | J58: =SUMIFS('2026'!$L:$L,'2026'!$J:$J,$B58&$C58,'2026'!$O:$O,J$4) -> 28876.8 | K58: =SUMIFS('2026'!$L:$L,'2026'!$J:$J,$B58&$C58,'2026'!$O:$O,K$4) -> 40857.6 | ... O58: =SUMIFS('2026'!$L:$L,'2026'!$J:$J,$B58&$C58,'2026'!$O:$O,O$4) -> 28876.8 | P58: =SUM(D58:O58) -> 884602.52 | Q58: 958332.56 | R58: =P58-Q58 -> -73730.04 | S58: =IF(ISERROR(R58/Q58),"",R58/Q58) -> -0.076935756 | T58: Shifted to Simcoe | U58: 1077035
A59: ESS | B59: 1712 | C59: KL Sandwich | D59: =SUMIFS('2026'!$L:$L,'2026'!$J:$J,$B59&$C59,'2026'!$O:$O,D$4) -> 0 | E59: =SUMIFS('2026'!$L:$L,'2026'!$J:$J,$B59&$C59,'2026'!$O:$O,E$4) -> 0 | F59: =SUMIFS('2026'!$L:$L,'2026'!$J:$J,$B59&$C59,'2026'!$O:$O,F$4) -> 0 | G59: =SUMIFS('2026'!$L:$L,'2026'!$J:$J,$B59&$C59,'2026'!$O:$O,G$4) -> 0 | H59: =SUMIFS('2026'!$L:$L,'2026'!$J:$J,$B59&$C59,'2026'!$O:$O,H$4) -> 0 | I59: =SUMIFS('2026'!$L:$L,'2026'!$J:$J,$B59&$C59,'2026'!$O:$O,I$4) -> 0 | J59: =SUMIFS('2026'!$L:$L,'2026'!$J:$J,$B59&$C59,'2026'!$O:$O,J$4) -> 0 | K59: =SUMIFS('2026'!$L:$L,'2026'!$J:$J,$B59&$C59,'2026'!$O:$O,K$4) -> 0 | ... O59: =SUMIFS('2026'!$L:$L,'2026'!$J:$J,$B59&$C59,'2026'!$O:$O,O$4) -> 0 | P59: =SUM(D59:O59) -> 0 | Q59: 0 | R59: =P59-Q59 -> 0 | S59: =IF(ISERROR(R59/Q59),"",R59/Q59) | U59: 0
C60: Total Schwann's | D60: =SUM(D57:D59) -> 157088 | E60: =SUM(E57:E59) -> 80070 | F60: =SUM(F57:F59) -> 242023.32 | G60: =SUM(G57:G59) -> 167660.16 | H60: =SUM(H57:H59) -> 195417.6 | I60: =SUM(I57:I59) -> 130412.16 | J60: =SUM(J57:J59) -> 78340.8 | K60: =SUM(K57:K59) -> 143535.36 | ... P60: =SUM(P57:P59) -> 1635933.3 | Q60: 1665135.9 | R60: =SUM(R57:R59) -> -29202.6 | S60: =IF(ISERROR(R60/Q60),"",R60/Q60) -> -0.017537667 | U60: 2470927
C62: Row Labels | D62: Jan | E62: Feb | F62: Mar | G62: Apr | H62: May | I62: Jun | J62: Jul | K62: Aug | L62: Sep | M62: Oct | N62: Nov | O62: Dec | P62: =P$4 -> 2026 MRF3 | Q62: 2026 MRF2 | R62: =R$4 -> Difference | S62: =S$4 -> % change | U62: 2025 Final
A63: Other | B63: 6765 | C63: BR Minicups | D63: =SUMIFS('2026'!$L:$L,'2026'!$J:$J,$B63&$C63,'2026'!$O:$O,D$4) -> 14446 | E63: =SUMIFS('2026'!$L:$L,'2026'!$J:$J,$B63&$C63,'2026'!$O:$O,E$4) -> 0 | F63: =SUMIFS('2026'!$L:$L,'2026'!$J:$J,$B63&$C63,'2026'!$O:$O,F$4) -> 8608.4 | G63: =SUMIFS('2026'!$L:$L,'2026'!$J:$J,$B63&$C63,'2026'!$O:$O,G$4) -> 0 | H63: =SUMIFS('2026'!$L:$L,'2026'!$J:$J,$B63&$C63,'2026'!$O:$O,H$4) -> 0 | I63: =SUMIFS('2026'!$L:$L,'2026'!$J:$J,$B63&$C63,'2026'!$O:$O,I$4) -> 8294.4 | J63: =SUMIFS('2026'!$L:$L,'2026'!$J:$J,$B63&$C63,'2026'!$O:$O,J$4) -> 8294.4 | K63: =SUMIFS('2026'!$L:$L,'2026'!$J:$J,$B63&$C63,'2026'!$O:$O,K$4) -> 8294.4 | ... O63: =SUMIFS('2026'!$L:$L,'2026'!$J:$J,$B63&$C63,'2026'!$O:$O,O$4) -> 16588.8 | P63: =SUM(D63:O63) -> 89409.6 | Q63: 604175.92 | R63: =P63-Q63 -> -514766.32 | S63: =IF(ISERROR(R63/Q63),"",R63/Q63) -> -0.85201396 | U63: 48994
A64: Other | B64: 6764 | C64: Other | D64: =SUMIFS('2026'!$L:$L,'2026'!$J:$J,$B64&$C64,'2026'!$O:$O,D$4) -> 78968 | E64: =SUMIFS('2026'!$L:$L,'2026'!$J:$J,$B64&$C64,'2026'!$O:$O,E$4) -> 76376 | F64: =SUMIFS('2026'!$L:$L,'2026'!$J:$J,$B64&$C64,'2026'!$O:$O,F$4) -> 49393 | G64: =SUMIFS('2026'!$L:$L,'2026'!$J:$J,$B64&$C64,'2026'!$O:$O,G$4) -> 57600 | H64: =SUMIFS('2026'!$L:$L,'2026'!$J:$J,$B64&$C64,'2026'!$O:$O,H$4) -> 57600 | I64: =SUMIFS('2026'!$L:$L,'2026'!$J:$J,$B64&$C64,'2026'!$O:$O,I$4) -> 76800 | J64: =SUMIFS('2026'!$L:$L,'2026'!$J:$J,$B64&$C64,'2026'!$O:$O,J$4) -> 38400 | K64: =SUMIFS('2026'!$L:$L,'2026'!$J:$J,$B64&$C64,'2026'!$O:$O,K$4) -> 38400 | ... O64: =SUMIFS('2026'!$L:$L,'2026'!$J:$J,$B64&$C64,'2026'!$O:$O,O$4) -> 0 | P64: =SUM(D64:O64) -> 531137 | Q64: 754766.52 | U64: 89496
A65: Other | B65: 6765 | C65: Other | D65: =SUMIFS('2026'!$L:$L,'2026'!$J:$J,$B65&$C65,'2026'!$O:$O,D$4) -> 0 | E65: =SUMIFS('2026'!$L:$L,'2026'!$J:$J,$B65&$C65,'2026'!$O:$O,E$4) -> 54383 | F65: =SUMIFS('2026'!$L:$L,'2026'!$J:$J,$B65&$C65,'2026'!$O:$O,F$4) -> 143910.24 | G65: =SUMIFS('2026'!$L:$L,'2026'!$J:$J,$B65&$C65,'2026'!$O:$O,G$4) -> 103680 | H65: =SUMIFS('2026'!$L:$L,'2026'!$J:$J,$B65&$C65,'2026'!$O:$O,H$4) -> 77760 | I65: =SUMIFS('2026'!$L:$L,'2026'!$J:$J,$B65&$C65,'2026'!$O:$O,I$4) -> 77760 | J65: =SUMIFS('2026'!$L:$L,'2026'!$J:$J,$B65&$C65,'2026'!$O:$O,J$4) -> 51840 | K65: =SUMIFS('2026'!$L:$L,'2026'!$J:$J,$B65&$C65,'2026'!$O:$O,K$4) -> 31104 | ... O65: =SUMIFS('2026'!$L:$L,'2026'!$J:$J,$B65&$C65,'2026'!$O:$O,O$4) -> 0 | P65: =SUM(D65:O65) -> 595157.24 | Q65: 707621.72 | R65: =P65-Q65 -> -112464.48 | S65: =IF(ISERROR(R65/Q65),"",R65/Q65) -> -0.15893305 | U65: 8520
A66: 48oz | B66: 6706 | C66: 48oz | D66: =SUMIFS('2026'!$L:$L,'2026'!$J:$J,$B66&$C66,'2026'!$O:$O,D$4) -> 0 | E66: =SUMIFS('2026'!$L:$L,'2026'!$J:$J,$B66&$C66,'2026'!$O:$O,E$4) -> 0 | F66: =SUMIFS('2026'!$L:$L,'2026'!$J:$J,$B66&$C66,'2026'!$O:$O,F$4) -> 0 | G66: =SUMIFS('2026'!$L:$L,'2026'!$J:$J,$B66&$C66,'2026'!$O:$O,G$4) -> 23500 | H66: =SUMIFS('2026'!$L:$L,'2026'!$J:$J,$B66&$C66,'2026'!$O:$O,H$4) -> 80000 | I66: =SUMIFS('2026'!$L:$L,'2026'!$J:$J,$B66&$C66,'2026'!$O:$O,I$4) -> 58500 | J66: =SUMIFS('2026'!$L:$L,'2026'!$J:$J,$B66&$C66,'2026'!$O:$O,J$4) -> 55000 | K66: =SUMIFS('2026'!$L:$L,'2026'!$J:$J,$B66&$C66,'2026'!$O:$O,K$4) -> 0 | ... O66: =SUMIFS('2026'!$L:$L,'2026'!$J:$J,$B66&$C66,'2026'!$O:$O,O$4) -> 0 | P66: =SUM(D66:O66) -> 217000 | Q66: 243500 | R66: =P66-Q66 -> -26500 | S66: =IF(ISERROR(R66/Q66),"",R66/Q66) -> -0.10882957 | U66: 459076
A67: Other | B67: 6706 | C67: FB Cones | D67: =SUMIFS('2026'!$L:$L,'2026'!$J:$J,$B67&$C67,'2026'!$O:$O,D$4) -> 0 | E67: =SUMIFS('2026'!$L:$L,'2026'!$J:$J,$B67&$C67,'2026'!$O:$O,E$4) -> 0 | F67: =SUMIFS('2026'!$L:$L,'2026'!$J:$J,$B67&$C67,'2026'!$O:$O,F$4) -> 0 | G67: =SUMIFS('2026'!$L:$L,'2026'!$J:$J,$B67&$C67,'2026'!$O:$O,G$4) -> 0 | H67: =SUMIFS('2026'!$L:$L,'2026'!$J:$J,$B67&$C67,'2026'!$O:$O,H$4) -> 0 | I67: =SUMIFS('2026'!$L:$L,'2026'!$J:$J,$B67&$C67,'2026'!$O:$O,I$4) -> 0 | J67: =SUMIFS('2026'!$L:$L,'2026'!$J:$J,$B67&$C67,'2026'!$O:$O,J$4) -> 0 | K67: =SUMIFS('2026'!$L:$L,'2026'!$J:$J,$B67&$C67,'2026'!$O:$O,K$4) -> 0 | ... O67: =SUMIFS('2026'!$L:$L,'2026'!$J:$J,$B67&$C67,'2026'!$O:$O,O$4) -> 0 | P67: =SUM(D67:O67) -> 0 | Q67: 0 | S67: =IF(ISERROR(R67/Q67),"",R67/Q67) | U67: 371937
A68: Other | B68: 6706 | C68: BR Minicups | D68: =SUMIFS('2026'!$L:$L,'2026'!$J:$J,$B68&$C68,'2026'!$O:$O,D$4) -> 27971 | E68: =SUMIFS('2026'!$L:$L,'2026'!$J:$J,$B68&$C68,'2026'!$O:$O,E$4) -> 0 | F68: =SUMIFS('2026'!$L:$L,'2026'!$J:$J,$B68&$C68,'2026'!$O:$O,F$4) -> 0 | G68: =SUMIFS('2026'!$L:$L,'2026'!$J:$J,$B68&$C68,'2026'!$O:$O,G$4) -> 3758.4 | H68: =SUMIFS('2026'!$L:$L,'2026'!$J:$J,$B68&$C68,'2026'!$O:$O,H$4) -> 0 | I68: =SUMIFS('2026'!$L:$L,'2026'!$J:$J,$B68&$C68,'2026'!$O:$O,I$4) -> 0 | J68: =SUMIFS('2026'!$L:$L,'2026'!$J:$J,$B68&$C68,'2026'!$O:$O,J$4) -> 0 | K68: =SUMIFS('2026'!$L:$L,'2026'!$J:$J,$B68&$C68,'2026'!$O:$O,K$4) -> 0 | ... O68: =SUMIFS('2026'!$L:$L,'2026'!$J:$J,$B68&$C68,'2026'!$O:$O,O$4) -> 0 | P68: =SUM(D68:O68) -> 31729.4 | Q68: 32154.68 | S68: =IF(ISERROR(R68/Q68),"",R68/Q68) -> 0 | U68: 154878
C69: Total Brothers 3PM | D69: =SUM(D63:D68) -> 121385 | E69: =SUM(E63:E68) -> 130759 | F69: =SUM(F63:F68) -> 201911.64 | G69: =SUM(G63:G68) -> 188538.4 | H69: =SUM(H63:H68) -> 215360 | I69: =SUM(I63:I68) -> 221354.4 | J69: =SUM(J63:J68) -> 153534.4 | K69: =SUM(K63:K68) -> 77798.4 | ... P69: =SUM(P63:P68) -> 1464433.2 | Q69: 2342218.8 | R69: =SUM(R63:R68) -> -653730.8 | S69: =IF(ISERROR(R69/Q69),"",R69/Q69) -> -0.27910748 | U69: 1132901
A71: Yasso Sticks | B71: 1715 | C71: Yasso Sticks | D71: =SUMIFS('2026'!$L:$L,'2026'!$J:$J,$B71&$C71,'2026'!$O:$O,D$4) -> 159308 | E71: =SUMIFS('2026'!$L:$L,'2026'!$J:$J,$B71&$C71,'2026'!$O:$O,E$4) -> 94351 | F71: =SUMIFS('2026'!$L:$L,'2026'!$J:$J,$B71&$C71,'2026'!$O:$O,F$4) -> 145653 | G71: =SUMIFS('2026'!$L:$L,'2026'!$J:$J,$B71&$C71,'2026'!$O:$O,G$4) -> 184880.64 | H71: =SUMIFS('2026'!$L:$L,'2026'!$J:$J,$B71&$C71,'2026'!$O:$O,H$4) -> 896880 | I71: =SUMIFS('2026'!$L:$L,'2026'!$J:$J,$B71&$C71,'2026'!$O:$O,I$4) -> 378000 | J71: =SUMIFS('2026'!$L:$L,'2026'!$J:$J,$B71&$C71,'2026'!$O:$O,J$4) -> 327600 | K71: =SUMIFS('2026'!$L:$L,'2026'!$J:$J,$B71&$C71,'2026'!$O:$O,K$4) -> 327600 | ... O71: =SUMIFS('2026'!$L:$L,'2026'!$J:$J,$B71&$C71,'2026'!$O:$O,O$4) -> 178000 | P71: =SUM(D71:O71) -> 3372672.6 | Q71: 2745970 | R71: =P71-Q71 -> 626702.64 | S71: =IF(ISERROR(R71/Q71),"",R71/Q71) -> 0.22822632 | U71: 2770754 | V71: 0.003312 | W71: =#REF!*V71 -> #REF!
A72: Yasso Sticks | B72: 1716 | C72: Yasso Sticks | D72: =SUMIFS('2026'!$L:$L,'2026'!$J:$J,$B72&$C72,'2026'!$O:$O,D$4) -> 77542 | E72: =SUMIFS('2026'!$L:$L,'2026'!$J:$J,$B72&$C72,'2026'!$O:$O,E$4) -> 100071 | F72: =SUMIFS('2026'!$L:$L,'2026'!$J:$J,$B72&$C72,'2026'!$O:$O,F$4) -> 38332 | G72: =SUMIFS('2026'!$L:$L,'2026'!$J:$J,$B72&$C72,'2026'!$O:$O,G$4) -> 66290.88 | H72: =SUMIFS('2026'!$L:$L,'2026'!$J:$J,$B72&$C72,'2026'!$O:$O,H$4) -> 358560 | I72: =SUMIFS('2026'!$L:$L,'2026'!$J:$J,$B72&$C72,'2026'!$O:$O,I$4) -> 53760 | J72: =SUMIFS('2026'!$L:$L,'2026'!$J:$J,$B72&$C72,'2026'!$O:$O,J$4) -> 107520 | K72: =SUMIFS('2026'!$L:$L,'2026'!$J:$J,$B72&$C72,'2026'!$O:$O,K$4) -> 26880 | ... O72: =SUMIFS('2026'!$L:$L,'2026'!$J:$J,$B72&$C72,'2026'!$O:$O,O$4) -> 52000 | P72: =SUM(D72:O72) -> 1178067.9 | Q72: 1854575.4 | R72: =P72-Q72 -> -676507.56 | S72: =IF(ISERROR(R72/Q72),"",R72/Q72) -> -0.36477759 | U72: 3357307 | V72: 0.003312 | W72: =#REF!*V72 -> #REF!
A73: Yasso Sticks | B73: 1717 | C73: Yasso Sticks | D73: =SUMIFS('2026'!$L:$L,'2026'!$J:$J,$B73&$C73,'2026'!$O:$O,D$4) -> 240492 | E73: =SUMIFS('2026'!$L:$L,'2026'!$J:$J,$B73&$C73,'2026'!$O:$O,E$4) -> 184952 | F73: =SUMIFS('2026'!$L:$L,'2026'!$J:$J,$B73&$C73,'2026'!$O:$O,F$4) -> 102469 | G73: =SUMIFS('2026'!$L:$L,'2026'!$J:$J,$B73&$C73,'2026'!$O:$O,G$4) -> 0 | H73: =SUMIFS('2026'!$L:$L,'2026'!$J:$J,$B73&$C73,'2026'!$O:$O,H$4) -> 0 | I73: =SUMIFS('2026'!$L:$L,'2026'!$J:$J,$B73&$C73,'2026'!$O:$O,I$4) -> 99840 | J73: =SUMIFS('2026'!$L:$L,'2026'!$J:$J,$B73&$C73,'2026'!$O:$O,J$4) -> 99840 | K73: =SUMIFS('2026'!$L:$L,'2026'!$J:$J,$B73&$C73,'2026'!$O:$O,K$4) -> 24960 | ... O73: =SUMIFS('2026'!$L:$L,'2026'!$J:$J,$B73&$C73,'2026'!$O:$O,O$4) -> 101920 | P73: =SUM(D73:O73) -> 1306455 | Q73: 1392656.2 | R73: =P73-Q73 -> -86201.17 | S73: =IF(ISERROR(R73/Q73),"",R73/Q73) -> -0.06189695 | U73: 1973678 | V73: 0.003312 | W73: =#REF!*V73 -> #REF!
A74: Yasso Club | B74: 1712 | C74: Yasso Club | D74: =SUMIFS('2026'!$L:$L,'2026'!$J:$J,$B74&$C74,'2026'!$O:$O,D$4) -> 119771 | E74: =SUMIFS('2026'!$L:$L,'2026'!$J:$J,$B74&$C74,'2026'!$O:$O,E$4) -> 292455 | F74: =SUMIFS('2026'!$L:$L,'2026'!$J:$J,$B74&$C74,'2026'!$O:$O,F$4) -> 358694 | G74: =SUMIFS('2026'!$L:$L,'2026'!$J:$J,$B74&$C74,'2026'!$O:$O,G$4) -> 110592 | H74: =SUMIFS('2026'!$L:$L,'2026'!$J:$J,$B74&$C74,'2026'!$O:$O,H$4) -> 181742.4 | I74: =SUMIFS('2026'!$L:$L,'2026'!$J:$J,$B74&$C74,'2026'!$O:$O,I$4) -> 221184 | J74: =SUMIFS('2026'!$L:$L,'2026'!$J:$J,$B74&$C74,'2026'!$O:$O,J$4) -> 110592 | K74: =SUMIFS('2026'!$L:$L,'2026'!$J:$J,$B74&$C74,'2026'!$O:$O,K$4) -> 442368 | ... O74: =SUMIFS('2026'!$L:$L,'2026'!$J:$J,$B74&$C74,'2026'!$O:$O,O$4) -> 331776 | P74: =SUM(D74:O74) -> 3177558.4 | Q74: 3130293.2 | R74: =P74-Q74 -> 47265.2 | S74: =IF(ISERROR(R74/Q74),"",R74/Q74) -> 0.015099288 | U74: 3325936 | V74: 0.001242 | W74: =#REF!*V74 -> #REF!
A75: Yasso Poppables | B75: 1713 | C75: Yasso Poppables | D75: =SUMIFS('2026'!$L:$L,'2026'!$J:$J,$B75&$C75,'2026'!$O:$O,D$4) -> 99 | E75: =SUMIFS('2026'!$L:$L,'2026'!$J:$J,$B75&$C75,'2026'!$O:$O,E$4) -> 20779 | F75: =SUMIFS('2026'!$L:$L,'2026'!$J:$J,$B75&$C75,'2026'!$O:$O,F$4) -> 0 | G75: =SUMIFS('2026'!$L:$L,'2026'!$J:$J,$B75&$C75,'2026'!$O:$O,G$4) -> 3456 | H75: =SUMIFS('2026'!$L:$L,'2026'!$J:$J,$B75&$C75,'2026'!$O:$O,H$4) -> 0 | I75: =SUMIFS('2026'!$L:$L,'2026'!$J:$J,$B75&$C75,'2026'!$O:$O,I$4) -> 21120 | J75: =SUMIFS('2026'!$L:$L,'2026'!$J:$J,$B75&$C75,'2026'!$O:$O,J$4) -> 10560 | K75: =SUMIFS('2026'!$L:$L,'2026'!$J:$J,$B75&$C75,'2026'!$O:$O,K$4) -> 8448 | ... O75: =SUMIFS('2026'!$L:$L,'2026'!$J:$J,$B75&$C75,'2026'!$O:$O,O$4) -> 0 | P75: =SUM(D75:O75) -> 85582 | Q75: 90691.12 | R75: =P75-Q75 -> -5109.12 | S75: =IF(ISERROR(R75/Q75),"",R75/Q75) -> -0.056335394 | U75: 339395 | V75: 0.00202 | W75: =#REF!*V75 -> #REF!
A76: Yasso Sandwich | B76: 1714 | C76: Yasso Sandwich | D76: =SUMIFS('2026'!$L:$L,'2026'!$J:$J,$B76&$C76,'2026'!$O:$O,D$4) -> 0 | E76: =SUMIFS('2026'!$L:$L,'2026'!$J:$J,$B76&$C76,'2026'!$O:$O,E$4) -> 0 | F76: =SUMIFS('2026'!$L:$L,'2026'!$J:$J,$B76&$C76,'2026'!$O:$O,F$4) -> 0 | G76: =SUMIFS('2026'!$L:$L,'2026'!$J:$J,$B76&$C76,'2026'!$O:$O,G$4) -> 0 | H76: =SUMIFS('2026'!$L:$L,'2026'!$J:$J,$B76&$C76,'2026'!$O:$O,H$4) -> 0 | I76: =SUMIFS('2026'!$L:$L,'2026'!$J:$J,$B76&$C76,'2026'!$O:$O,I$4) -> 0 | J76: =SUMIFS('2026'!$L:$L,'2026'!$J:$J,$B76&$C76,'2026'!$O:$O,J$4) -> 0 | K76: =SUMIFS('2026'!$L:$L,'2026'!$J:$J,$B76&$C76,'2026'!$O:$O,K$4) -> 0 | ... O76: =SUMIFS('2026'!$L:$L,'2026'!$J:$J,$B76&$C76,'2026'!$O:$O,O$4) -> 0 | P76: =SUM(D76:O76) -> 0 | Q76: 0 | R76: =P76-Q76 -> 0 | U76: 5670 | V76: 0.000728 | W76: =#REF!*V76 -> #REF!
C77: Total Yasso | D77: =SUM(D71:D76) -> 597212 | E77: =SUM(E71:E76) -> 692608 | F77: =SUM(F71:F76) -> 645148 | G77: =SUM(G71:G76) -> 365219.52 | H77: =SUM(H71:H76) -> 1437182.4 | I77: =SUM(I71:I76) -> 773904 | J77: =SUM(J71:J76) -> 656112 | K77: =SUM(K71:K76) -> 830256 | ... P77: =SUM(P71:P76) -> 9120335.9 | Q77: 9214185.9 | R77: =SUM(R71) -> 626702.64 | S77: =IF(ISERROR(R77/Q77),"",R77/Q77) -> 0.068014977 | U77: 11772740
D79: Jan | E79: Feb | F79: Mar | G79: Apr | H79: May | I79: Jun | J79: Jul | K79: Aug | L79: Sep | M79: Oct | N79: Nov | O79: Dec | P79: =P$4 -> 2026 MRF3 | Q79: 2026 MRF2 | R79: =R$4 -> Difference | S79: =S$4 -> % change | U79: 2025 Final
A80: Dough Bites | B80: Rhino | C80: Dough Bites | D80: =SUMIFS('2026'!$L:$L,'2026'!$J:$J,$B80&$C80,'2026'!$O:$O,D$4) -> 69103 | E80: =SUMIFS('2026'!$L:$L,'2026'!$J:$J,$B80&$C80,'2026'!$O:$O,E$4) -> 49152 | F80: =SUMIFS('2026'!$L:$L,'2026'!$J:$J,$B80&$C80,'2026'!$O:$O,F$4) -> 40557 | G80: =SUMIFS('2026'!$L:$L,'2026'!$J:$J,$B80&$C80,'2026'!$O:$O,G$4) -> 51840 | H80: =SUMIFS('2026'!$L:$L,'2026'!$J:$J,$B80&$C80,'2026'!$O:$O,H$4) -> 43680 | I80: =SUMIFS('2026'!$L:$L,'2026'!$J:$J,$B80&$C80,'2026'!$O:$O,I$4) -> 34800 | J80: =SUMIFS('2026'!$L:$L,'2026'!$J:$J,$B80&$C80,'2026'!$O:$O,J$4) -> 37920 | K80: =SUMIFS('2026'!$L:$L,'2026'!$J:$J,$B80&$C80,'2026'!$O:$O,K$4) -> 30720 | ... O80: =SUMIFS('2026'!$L:$L,'2026'!$J:$J,$B80&$C80,'2026'!$O:$O,O$4) -> 18720 | P80: =SUM(D80:O80) -> 440332 | Q80: 417455 | R80: =P80-Q80 -> 22877 | S80: =IF(ISERROR(R80/Q80),"",R80/Q80) -> 0.054801116 | U80: 453288
A81: ESS | B81: 6757 | C81: ESS | D81: =SUMIFS('2026'!$L:$L,'2026'!$J:$J,$B81&$C81,'2026'!$O:$O,D$4) -> 31944 | E81: =SUMIFS('2026'!$L:$L,'2026'!$J:$J,$B81&$C81,'2026'!$O:$O,E$4) -> 50274 | F81: =SUMIFS('2026'!$L:$L,'2026'!$J:$J,$B81&$C81,'2026'!$O:$O,F$4) -> 49821.72 | G81: =SUMIFS('2026'!$L:$L,'2026'!$J:$J,$B81&$C81,'2026'!$O:$O,G$4) -> 46513.92 | H81: =SUMIFS('2026'!$L:$L,'2026'!$J:$J,$B81&$C81,'2026'!$O:$O,H$4) -> 46513.92 | I81: =SUMIFS('2026'!$L:$L,'2026'!$J:$J,$B81&$C81,'2026'!$O:$O,I$4) -> 55816.32 | J81: =SUMIFS('2026'!$L:$L,'2026'!$J:$J,$B81&$C81,'2026'!$O:$O,J$4) -> 46513.92 | K81: =SUMIFS('2026'!$L:$L,'2026'!$J:$J,$B81&$C81,'2026'!$O:$O,K$4) -> 58142.4 | ... O81: =SUMIFS('2026'!$L:$L,'2026'!$J:$J,$B81&$C81,'2026'!$O:$O,O$4) -> 7065.6 | P81: =SUM(D81:O81) -> 462376.68 | Q81: 453782.96 | R81: =P81-Q81 -> 8593.72 | S81: =IF(ISERROR(R81/Q81),"",R81/Q81) -> 0.018937952 | T81: Ramp up rate/assumptions updated | U81: 363652
A82: Yasso Sandwich | B82: 6757 | C82: Yasso Sandwich | D82: =SUMIFS('2026'!$L:$L,'2026'!$J:$J,$B82&$C82,'2026'!$O:$O,D$4) -> 0 | E82: =SUMIFS('2026'!$L:$L,'2026'!$J:$J,$B82&$C82,'2026'!$O:$O,E$4) -> 33793 | F82: =SUMIFS('2026'!$L:$L,'2026'!$J:$J,$B82&$C82,'2026'!$O:$O,F$4) -> 34332 | G82: =SUMIFS('2026'!$L:$L,'2026'!$J:$J,$B82&$C82,'2026'!$O:$O,G$4) -> 0 | H82: =SUMIFS('2026'!$L:$L,'2026'!$J:$J,$B82&$C82,'2026'!$O:$O,H$4) -> 11808 | I82: =SUMIFS('2026'!$L:$L,'2026'!$J:$J,$B82&$C82,'2026'!$O:$O,I$4) -> 0 | J82: =SUMIFS('2026'!$L:$L,'2026'!$J:$J,$B82&$C82,'2026'!$O:$O,J$4) -> 0 | K82: =SUMIFS('2026'!$L:$L,'2026'!$J:$J,$B82&$C82,'2026'!$O:$O,K$4) -> 0 | ... O82: =SUMIFS('2026'!$L:$L,'2026'!$J:$J,$B82&$C82,'2026'!$O:$O,O$4) -> 0 | P82: =SUM(D82:O82) -> 86998.6 | Q82: 78796.84 | R82: =P82-Q82 -> 8201.76 | S82: =IF(ISERROR(R82/Q82),"",R82/Q82) -> 0.10408742 | U82: 177456
A83: Other | B83: 6757 | C83: BR Minicups | D83: =SUMIFS('2026'!$L:$L,'2026'!$J:$J,$B83&$C83,'2026'!$O:$O,D$4) -> 0 | E83: =SUMIFS('2026'!$L:$L,'2026'!$J:$J,$B83&$C83,'2026'!$O:$O,E$4) -> 0 | F83: =SUMIFS('2026'!$L:$L,'2026'!$J:$J,$B83&$C83,'2026'!$O:$O,F$4) -> 0 | G83: =SUMIFS('2026'!$L:$L,'2026'!$J:$J,$B83&$C83,'2026'!$O:$O,G$4) -> 0 | H83: =SUMIFS('2026'!$L:$L,'2026'!$J:$J,$B83&$C83,'2026'!$O:$O,H$4) -> 0 | I83: =SUMIFS('2026'!$L:$L,'2026'!$J:$J,$B83&$C83,'2026'!$O:$O,I$4) -> 0 | J83: =SUMIFS('2026'!$L:$L,'2026'!$J:$J,$B83&$C83,'2026'!$O:$O,J$4) -> 0 | K83: =SUMIFS('2026'!$L:$L,'2026'!$J:$J,$B83&$C83,'2026'!$O:$O,K$4) -> 0 | ... O83: =SUMIFS('2026'!$L:$L,'2026'!$J:$J,$B83&$C83,'2026'!$O:$O,O$4) -> 0 | P83: =SUM(D83:O83) -> 0 | Q83: 0 | U83: 0
A84: Other | B84: 1717 | C84: Other | D84: =SUMIFS('2026'!$L:$L,'2026'!$J:$J,$B84&$C84,'2026'!$O:$O,D$4) -> 69085 | E84: =SUMIFS('2026'!$L:$L,'2026'!$J:$J,$B84&$C84,'2026'!$O:$O,E$4) -> 38044 | F84: =SUMIFS('2026'!$L:$L,'2026'!$J:$J,$B84&$C84,'2026'!$O:$O,F$4) -> 93150.84 | G84: =SUMIFS('2026'!$L:$L,'2026'!$J:$J,$B84&$C84,'2026'!$O:$O,G$4) -> 69340.8 | H84: =SUMIFS('2026'!$L:$L,'2026'!$J:$J,$B84&$C84,'2026'!$O:$O,H$4) -> 54537.6 | I84: =SUMIFS('2026'!$L:$L,'2026'!$J:$J,$B84&$C84,'2026'!$O:$O,I$4) -> 51337.92 | J84: =SUMIFS('2026'!$L:$L,'2026'!$J:$J,$B84&$C84,'2026'!$O:$O,J$4) -> 64800 | K84: =SUMIFS('2026'!$L:$L,'2026'!$J:$J,$B84&$C84,'2026'!$O:$O,K$4) -> 43200 | ... O84: =SUMIFS('2026'!$L:$L,'2026'!$J:$J,$B84&$C84,'2026'!$O:$O,O$4) -> 28800 | P84: =SUM(D84:O84) -> 641896.16 | Q84: 637784.36 | U84: 0
A85: YS PTS | B85: 1716 | C85: YS PTS | D85: =SUMIFS('2026'!$L:$L,'2026'!$J:$J,$B85&$C85,'2026'!$O:$O,D$4) -> 209681 | E85: =SUMIFS('2026'!$L:$L,'2026'!$J:$J,$B85&$C85,'2026'!$O:$O,E$4) -> 207121 | F85: =SUMIFS('2026'!$L:$L,'2026'!$J:$J,$B85&$C85,'2026'!$O:$O,F$4) -> 312901 | G85: =SUMIFS('2026'!$L:$L,'2026'!$J:$J,$B85&$C85,'2026'!$O:$O,G$4) -> 226200 | H85: =SUMIFS('2026'!$L:$L,'2026'!$J:$J,$B85&$C85,'2026'!$O:$O,H$4) -> 125760 | I85: =SUMIFS('2026'!$L:$L,'2026'!$J:$J,$B85&$C85,'2026'!$O:$O,I$4) -> 77760 | J85: =SUMIFS('2026'!$L:$L,'2026'!$J:$J,$B85&$C85,'2026'!$O:$O,J$4) -> 155520 | K85: =SUMIFS('2026'!$L:$L,'2026'!$J:$J,$B85&$C85,'2026'!$O:$O,K$4) -> 77760 | ... O85: =SUMIFS('2026'!$L:$L,'2026'!$J:$J,$B85&$C85,'2026'!$O:$O,O$4) -> 50880 | P85: =SUM(D85:O85) -> 1778623 | Q85: 1679869.2 | R85: =P85-Q85 -> 98753.84 | S85: =IF(ISERROR(R85/Q85),"",R85/Q85) -> 0.058786626 | U85: 180934
A86: SP1 | B86: 1716 | C86: PTS | D86: =SUMIFS('2026'!$L:$L,'2026'!$J:$J,$B86&$C86,'2026'!$O:$O,D$4) -> 0 | E86: =SUMIFS('2026'!$L:$L,'2026'!$J:$J,$B86&$C86,'2026'!$O:$O,E$4) -> 0 | F86: =SUMIFS('2026'!$L:$L,'2026'!$J:$J,$B86&$C86,'2026'!$O:$O,F$4) -> 0 | G86: =SUMIFS('2026'!$L:$L,'2026'!$J:$J,$B86&$C86,'2026'!$O:$O,G$4) -> 0 | H86: =SUMIFS('2026'!$L:$L,'2026'!$J:$J,$B86&$C86,'2026'!$O:$O,H$4) -> 0 | I86: =SUMIFS('2026'!$L:$L,'2026'!$J:$J,$B86&$C86,'2026'!$O:$O,I$4) -> 0 | J86: =SUMIFS('2026'!$L:$L,'2026'!$J:$J,$B86&$C86,'2026'!$O:$O,J$4) -> 0 | K86: =SUMIFS('2026'!$L:$L,'2026'!$J:$J,$B86&$C86,'2026'!$O:$O,K$4) -> 0 | ... O86: =SUMIFS('2026'!$L:$L,'2026'!$J:$J,$B86&$C86,'2026'!$O:$O,O$4) -> 90000 | P86: =SUM(D86:O86) -> 90000 | Q86: 0 | R86: =P86-Q86 -> 90000 | S86: =IF(ISERROR(R86/Q86),"",R86/Q86) | U86: 0
A87: BJ Pts | B87: 1716 | C87: BJ PTS | D87: =SUMIFS('2026'!$L:$L,'2026'!$J:$J,$B87&$C87,'2026'!$O:$O,D$4) -> 0 | E87: =SUMIFS('2026'!$L:$L,'2026'!$J:$J,$B87&$C87,'2026'!$O:$O,E$4) -> 0 | F87: =SUMIFS('2026'!$L:$L,'2026'!$J:$J,$B87&$C87,'2026'!$O:$O,F$4) -> 0 | G87: =SUMIFS('2026'!$L:$L,'2026'!$J:$J,$B87&$C87,'2026'!$O:$O,G$4) -> 0 | H87: =SUMIFS('2026'!$L:$L,'2026'!$J:$J,$B87&$C87,'2026'!$O:$O,H$4) -> 0 | I87: =SUMIFS('2026'!$L:$L,'2026'!$J:$J,$B87&$C87,'2026'!$O:$O,I$4) -> 0 | J87: =SUMIFS('2026'!$L:$L,'2026'!$J:$J,$B87&$C87,'2026'!$O:$O,J$4) -> 0 | K87: =SUMIFS('2026'!$L:$L,'2026'!$J:$J,$B87&$C87,'2026'!$O:$O,K$4) -> 0 | ... O87: =SUMIFS('2026'!$L:$L,'2026'!$J:$J,$B87&$C87,'2026'!$O:$O,O$4) -> 0 | P87: =SUM(D87:O87) -> 0 | Q87: 0 | R87: =P87-Q87 -> 0 | S87: =IF(ISERROR(R87/Q87),"",R87/Q87) | T87: PB Cup & Attainment | U87: 542888
A88: BJ Bars | B88: 1716 | C88: BJ Bars | D88: =SUMIFS('2026'!$L:$L,'2026'!$J:$J,$B88&$C88,'2026'!$O:$O,D$4) -> 90072 | E88: =SUMIFS('2026'!$L:$L,'2026'!$J:$J,$B88&$C88,'2026'!$O:$O,E$4) -> 112410 | F88: =SUMIFS('2026'!$L:$L,'2026'!$J:$J,$B88&$C88,'2026'!$O:$O,F$4) -> 285317.4 | G88: =SUMIFS('2026'!$L:$L,'2026'!$J:$J,$B88&$C88,'2026'!$O:$O,G$4) -> 132960.96 | H88: =SUMIFS('2026'!$L:$L,'2026'!$J:$J,$B88&$C88,'2026'!$O:$O,H$4) -> 281869.44 | I88: =SUMIFS('2026'!$L:$L,'2026'!$J:$J,$B88&$C88,'2026'!$O:$O,I$4) -> 134400 | J88: =SUMIFS('2026'!$L:$L,'2026'!$J:$J,$B88&$C88,'2026'!$O:$O,J$4) -> 107520 | K88: =SUMIFS('2026'!$L:$L,'2026'!$J:$J,$B88&$C88,'2026'!$O:$O,K$4) -> 215040 | ... O88: =SUMIFS('2026'!$L:$L,'2026'!$J:$J,$B88&$C88,'2026'!$O:$O,O$4) -> 80640 | P88: =SUM(D88:O88) -> 1950949.8 | Q88: 1817336 | R88: =P88-Q88 -> 133613.84 | S88: =IF(ISERROR(R88/Q88),"",R88/Q88) -> 0.073521816 | U88: 231638
A89: ESS | B89: Turkey Hill | C89: ESS | D89: =SUMIFS('2026'!$L:$L,'2026'!$J:$J,$B89&$C89,'2026'!$O:$O,D$4) -> 0 | E89: =SUMIFS('2026'!$L:$L,'2026'!$J:$J,$B89&$C89,'2026'!$O:$O,E$4) -> 0 | F89: =SUMIFS('2026'!$L:$L,'2026'!$J:$J,$B89&$C89,'2026'!$O:$O,F$4) -> 0 | G89: =SUMIFS('2026'!$L:$L,'2026'!$J:$J,$B89&$C89,'2026'!$O:$O,G$4) -> 37037.037 | H89: =SUMIFS('2026'!$L:$L,'2026'!$J:$J,$B89&$C89,'2026'!$O:$O,H$4) -> 70000 | I89: =SUMIFS('2026'!$L:$L,'2026'!$J:$J,$B89&$C89,'2026'!$O:$O,I$4) -> 62037.037 | J89: =SUMIFS('2026'!$L:$L,'2026'!$J:$J,$B89&$C89,'2026'!$O:$O,J$4) -> 62034.537 | K89: =SUMIFS('2026'!$L:$L,'2026'!$J:$J,$B89&$C89,'2026'!$O:$O,K$4) -> 62034.537 | ... O89: =SUMIFS('2026'!$L:$L,'2026'!$J:$J,$B89&$C89,'2026'!$O:$O,O$4) -> 45370.37 | P89: =SUM(D89:O89) -> 495457.96 | Q89: 495457.96 | R89: =P89-Q89 -> 0 | S89: =IF(ISERROR(R89/Q89),"",R89/Q89) -> 0 | U89: 0
A90: Other | B90: Glacier Point | C90: Other | D90: =SUMIFS('2026'!$L:$L,'2026'!$J:$J,$B90&$C90,'2026'!$O:$O,D$4) -> 0 | E90: =SUMIFS('2026'!$L:$L,'2026'!$J:$J,$B90&$C90,'2026'!$O:$O,E$4) -> 0 | F90: =SUMIFS('2026'!$L:$L,'2026'!$J:$J,$B90&$C90,'2026'!$O:$O,F$4) -> 0 | G90: =SUMIFS('2026'!$L:$L,'2026'!$J:$J,$B90&$C90,'2026'!$O:$O,G$4) -> 0 | H90: =SUMIFS('2026'!$L:$L,'2026'!$J:$J,$B90&$C90,'2026'!$O:$O,H$4) -> 0 | I90: =SUMIFS('2026'!$L:$L,'2026'!$J:$J,$B90&$C90,'2026'!$O:$O,I$4) -> 0 | J90: =SUMIFS('2026'!$L:$L,'2026'!$J:$J,$B90&$C90,'2026'!$O:$O,J$4) -> 0 | K90: =SUMIFS('2026'!$L:$L,'2026'!$J:$J,$B90&$C90,'2026'!$O:$O,K$4) -> 0 | ... O90: =SUMIFS('2026'!$L:$L,'2026'!$J:$J,$B90&$C90,'2026'!$O:$O,O$4) -> 0 | P90: =SUM(D90:O90) -> 0 | Q90: 0 | R90: =P90-Q90 -> 0 | S90: =IF(ISERROR(R90/Q90),"",R90/Q90) | U90: 73993
C92: Imports/Others | P92: =P$4 -> 2026 MRF3 | Q92: 2026 MRF2 | R92: =R$4 -> Difference | S92: =S$4 -> % change | T92: Commentary | U92: 2025 Final
C93: Row Labels | D93: Jan | E93: Feb | F93: Mar | G93: Apr | H93: May | I93: Jun | J93: Jul | K93: Aug | L93: Sep | M93: Oct | N93: Nov | O93: Dec | P93: L Projection | Q93: L Projection | R93: Difference | S93: % change | U93: L Projection
A94: Other | B94: St Iria | C94: King Cone (PT) | D94: =SUMIFS('2026'!$L:$L,'2026'!$J:$J,$B94&$C94,'2026'!$O:$O,D$4) -> 0 | E94: =SUMIFS('2026'!$L:$L,'2026'!$J:$J,$B94&$C94,'2026'!$O:$O,E$4) -> 0 | F94: =SUMIFS('2026'!$L:$L,'2026'!$J:$J,$B94&$C94,'2026'!$O:$O,F$4) -> 0 | G94: =SUMIFS('2026'!$L:$L,'2026'!$J:$J,$B94&$C94,'2026'!$O:$O,G$4) -> 0 | H94: =SUMIFS('2026'!$L:$L,'2026'!$J:$J,$B94&$C94,'2026'!$O:$O,H$4) -> 0 | I94: =SUMIFS('2026'!$L:$L,'2026'!$J:$J,$B94&$C94,'2026'!$O:$O,I$4) -> 0 | J94: =SUMIFS('2026'!$L:$L,'2026'!$J:$J,$B94&$C94,'2026'!$O:$O,J$4) -> 0 | K94: =SUMIFS('2026'!$L:$L,'2026'!$J:$J,$B94&$C94,'2026'!$O:$O,K$4) -> 0 | ... O94: =SUMIFS('2026'!$L:$L,'2026'!$J:$J,$B94&$C94,'2026'!$O:$O,O$4) -> 0 | P94: =SUM(D94:O94) -> 0 | Q94: 0 | S94: =IF(ISERROR(R94/Q94),"",R94/Q94) | U94: 0
A95: MG Sticks | B95: St Iria | C95: MG Sticks | D95: =SUMIFS('2026'!$L:$L,'2026'!$J:$J,$B95&$C95,'2026'!$O:$O,D$4) -> 0 | E95: =SUMIFS('2026'!$L:$L,'2026'!$J:$J,$B95&$C95,'2026'!$O:$O,E$4) -> 0 | F95: =SUMIFS('2026'!$L:$L,'2026'!$J:$J,$B95&$C95,'2026'!$O:$O,F$4) -> 0 | G95: =SUMIFS('2026'!$L:$L,'2026'!$J:$J,$B95&$C95,'2026'!$O:$O,G$4) -> 0 | H95: =SUMIFS('2026'!$L:$L,'2026'!$J:$J,$B95&$C95,'2026'!$O:$O,H$4) -> 0 | I95: =SUMIFS('2026'!$L:$L,'2026'!$J:$J,$B95&$C95,'2026'!$O:$O,I$4) -> 0 | J95: =SUMIFS('2026'!$L:$L,'2026'!$J:$J,$B95&$C95,'2026'!$O:$O,J$4) -> 0 | K95: =SUMIFS('2026'!$L:$L,'2026'!$J:$J,$B95&$C95,'2026'!$O:$O,K$4) -> 0 | ... O95: =SUMIFS('2026'!$L:$L,'2026'!$J:$J,$B95&$C95,'2026'!$O:$O,O$4) -> 0 | P95: =SUM(D95:O95) -> 0 | Q95: 0 | S95: =IF(ISERROR(R95/Q95),"",R95/Q95) | U95: 0
A96: PG | B96: Tultitlan | C96: PG | D96: =SUMIFS('2026'!$L:$L,'2026'!$J:$J,$B96&$C96,'2026'!$O:$O,D$4) -> 0 | E96: =SUMIFS('2026'!$L:$L,'2026'!$J:$J,$B96&$C96,'2026'!$O:$O,E$4) -> 0 | F96: =SUMIFS('2026'!$L:$L,'2026'!$J:$J,$B96&$C96,'2026'!$O:$O,F$4) -> 0 | G96: =SUMIFS('2026'!$L:$L,'2026'!$J:$J,$B96&$C96,'2026'!$O:$O,G$4) -> 0 | H96: =SUMIFS('2026'!$L:$L,'2026'!$J:$J,$B96&$C96,'2026'!$O:$O,H$4) -> 0 | I96: =SUMIFS('2026'!$L:$L,'2026'!$J:$J,$B96&$C96,'2026'!$O:$O,I$4) -> 0 | J96: =SUMIFS('2026'!$L:$L,'2026'!$J:$J,$B96&$C96,'2026'!$O:$O,J$4) -> 0 | K96: =SUMIFS('2026'!$L:$L,'2026'!$J:$J,$B96&$C96,'2026'!$O:$O,K$4) -> 0 | ... O96: =SUMIFS('2026'!$L:$L,'2026'!$J:$J,$B96&$C96,'2026'!$O:$O,O$4) -> 0 | P96: =SUM(D96:O96) -> 0 | Q96: 0 | S96: =IF(ISERROR(R96/Q96),"",R96/Q96) | U96: 0
A97: Other | B97: Tultitlan | C97: Other | D97: =SUMIFS('2026'!$L:$L,'2026'!$J:$J,$B97&$C97,'2026'!$O:$O,D$4) -> 9538 | E97: =SUMIFS('2026'!$L:$L,'2026'!$J:$J,$B97&$C97,'2026'!$O:$O,E$4) -> 28742 | F97: =SUMIFS('2026'!$L:$L,'2026'!$J:$J,$B97&$C97,'2026'!$O:$O,F$4) -> 37631.96 | G97: =SUMIFS('2026'!$L:$L,'2026'!$J:$J,$B97&$C97,'2026'!$O:$O,G$4) -> 38928 | H97: =SUMIFS('2026'!$L:$L,'2026'!$J:$J,$B97&$C97,'2026'!$O:$O,H$4) -> 17340.48 | I97: =SUMIFS('2026'!$L:$L,'2026'!$J:$J,$B97&$C97,'2026'!$O:$O,I$4) -> 22196.16 | J97: =SUMIFS('2026'!$L:$L,'2026'!$J:$J,$B97&$C97,'2026'!$O:$O,J$4) -> 10984.32 | K97: =SUMIFS('2026'!$L:$L,'2026'!$J:$J,$B97&$C97,'2026'!$O:$O,K$4) -> 26083.2 | ... O97: =SUMIFS('2026'!$L:$L,'2026'!$J:$J,$B97&$C97,'2026'!$O:$O,O$4) -> 0 | P97: =SUM(D97:O97) -> 209977.88 | Q97: 240368.4 | S97: =IF(ISERROR(R97/Q97),"",R97/Q97) -> 0 | U97: 272855
A98: ESS | B98: Tultitlan | C98: KL Sandwiches | D98: =SUMIFS('2026'!$L:$L,'2026'!$J:$J,$B98&$C98,'2026'!$O:$O,D$4) -> 0 | E98: =SUMIFS('2026'!$L:$L,'2026'!$J:$J,$B98&$C98,'2026'!$O:$O,E$4) -> 0 | F98: =SUMIFS('2026'!$L:$L,'2026'!$J:$J,$B98&$C98,'2026'!$O:$O,F$4) -> 0 | G98: =SUMIFS('2026'!$L:$L,'2026'!$J:$J,$B98&$C98,'2026'!$O:$O,G$4) -> 0 | H98: =SUMIFS('2026'!$L:$L,'2026'!$J:$J,$B98&$C98,'2026'!$O:$O,H$4) -> 0 | I98: =SUMIFS('2026'!$L:$L,'2026'!$J:$J,$B98&$C98,'2026'!$O:$O,I$4) -> 0 | J98: =SUMIFS('2026'!$L:$L,'2026'!$J:$J,$B98&$C98,'2026'!$O:$O,J$4) -> 0 | K98: =SUMIFS('2026'!$L:$L,'2026'!$J:$J,$B98&$C98,'2026'!$O:$O,K$4) -> 0 | ... O98: =SUMIFS('2026'!$L:$L,'2026'!$J:$J,$B98&$C98,'2026'!$O:$O,O$4) -> 0 | P98: =SUM(D98:O98) -> 0 | Q98: 0 | R98: =P98-Q98 -> 0 | S98: =IF(ISERROR(R98/Q98),"",R98/Q98) | U98: 0
A99: KL Mini Cones | B99: Tultitlan | C99: KL Mini Cones | D99: =SUMIFS('2026'!$L:$L,'2026'!$J:$J,$B99&$C99,'2026'!$O:$O,D$4) -> 3888 | E99: =SUMIFS('2026'!$L:$L,'2026'!$J:$J,$B99&$C99,'2026'!$O:$O,E$4) -> 8625 | F99: =SUMIFS('2026'!$L:$L,'2026'!$J:$J,$B99&$C99,'2026'!$O:$O,F$4) -> 6158.08 | G99: =SUMIFS('2026'!$L:$L,'2026'!$J:$J,$B99&$C99,'2026'!$O:$O,G$4) -> 0 | H99: =SUMIFS('2026'!$L:$L,'2026'!$J:$J,$B99&$C99,'2026'!$O:$O,H$4) -> 7387.2 | I99: =SUMIFS('2026'!$L:$L,'2026'!$J:$J,$B99&$C99,'2026'!$O:$O,I$4) -> 0 | J99: =SUMIFS('2026'!$L:$L,'2026'!$J:$J,$B99&$C99,'2026'!$O:$O,J$4) -> 0 | K99: =SUMIFS('2026'!$L:$L,'2026'!$J:$J,$B99&$C99,'2026'!$O:$O,K$4) -> 0 | ... O99: =SUMIFS('2026'!$L:$L,'2026'!$J:$J,$B99&$C99,'2026'!$O:$O,O$4) -> 0 | P99: =SUM(D99:O99) -> 26058.28 | Q99: 34365.48 | U99: 106327
A100: MG Sticks | B100: Tultitlan | C100: MG Sticks | D100: =SUMIFS('2026'!$L:$L,'2026'!$J:$J,$B100&$C100,'2026'!$O:$O,D$4) -> 0 | E100: =SUMIFS('2026'!$L:$L,'2026'!$J:$J,$B100&$C100,'2026'!$O:$O,E$4) -> 0 | F100: =SUMIFS('2026'!$L:$L,'2026'!$J:$J,$B100&$C100,'2026'!$O:$O,F$4) -> 0 | G100: =SUMIFS('2026'!$L:$L,'2026'!$J:$J,$B100&$C100,'2026'!$O:$O,G$4) -> 0 | H100: =SUMIFS('2026'!$L:$L,'2026'!$J:$J,$B100&$C100,'2026'!$O:$O,H$4) -> 0 | I100: =SUMIFS('2026'!$L:$L,'2026'!$J:$J,$B100&$C100,'2026'!$O:$O,I$4) -> 0 | J100: =SUMIFS('2026'!$L:$L,'2026'!$J:$J,$B100&$C100,'2026'!$O:$O,J$4) -> 0 | K100: =SUMIFS('2026'!$L:$L,'2026'!$J:$J,$B100&$C100,'2026'!$O:$O,K$4) -> 0 | ... O100: =SUMIFS('2026'!$L:$L,'2026'!$J:$J,$B100&$C100,'2026'!$O:$O,O$4) -> 0 | P100: =SUM(D100:O100) -> 0 | Q100: 0 | R100: =P100-Q100 -> 0 | S100: =IF(ISERROR(R100/Q100),"",R100/Q100) | U100: 1986
A101: 48oz | B101: 3910 | C101: 48oz | D101: =SUMIFS('2026'!$L:$L,'2026'!$J:$J,$B101&$C101,'2026'!$O:$O,D$4) -> 0 | E101: =SUMIFS('2026'!$L:$L,'2026'!$J:$J,$B101&$C101,'2026'!$O:$O,E$4) -> 0 | F101: =SUMIFS('2026'!$L:$L,'2026'!$J:$J,$B101&$C101,'2026'!$O:$O,F$4) -> 0 | G101: =SUMIFS('2026'!$L:$L,'2026'!$J:$J,$B101&$C101,'2026'!$O:$O,G$4) -> 22560 | H101: =SUMIFS('2026'!$L:$L,'2026'!$J:$J,$B101&$C101,'2026'!$O:$O,H$4) -> 78960 | I101: =SUMIFS('2026'!$L:$L,'2026'!$J:$J,$B101&$C101,'2026'!$O:$O,I$4) -> 214320 | J101: =SUMIFS('2026'!$L:$L,'2026'!$J:$J,$B101&$C101,'2026'!$O:$O,J$4) -> 180480 | K101: =SUMIFS('2026'!$L:$L,'2026'!$J:$J,$B101&$C101,'2026'!$O:$O,K$4) -> 0 | ... O101: =SUMIFS('2026'!$L:$L,'2026'!$J:$J,$B101&$C101,'2026'!$O:$O,O$4) -> 0 | P101: =SUM(D101:O101) -> 496320 | Q101: 450000 | R101: =P101-Q101 -> 46320 | S101: =IF(ISERROR(R101/Q101),"",R101/Q101) -> 0.10293333 | U101: 0
A102: ESS | B102: 3910 | C102: ESS | D102: =SUMIFS('2026'!$L:$L,'2026'!$J:$J,$B102&$C102,'2026'!$O:$O,D$4) -> 54639 | E102: =SUMIFS('2026'!$L:$L,'2026'!$J:$J,$B102&$C102,'2026'!$O:$O,E$4) -> 15444 | F102: =SUMIFS('2026'!$L:$L,'2026'!$J:$J,$B102&$C102,'2026'!$O:$O,F$4) -> 0 | G102: =SUMIFS('2026'!$L:$L,'2026'!$J:$J,$B102&$C102,'2026'!$O:$O,G$4) -> 16024.32 | H102: =SUMIFS('2026'!$L:$L,'2026'!$J:$J,$B102&$C102,'2026'!$O:$O,H$4) -> 0 | I102: =SUMIFS('2026'!$L:$L,'2026'!$J:$J,$B102&$C102,'2026'!$O:$O,I$4) -> 36979.2 | J102: =SUMIFS('2026'!$L:$L,'2026'!$J:$J,$B102&$C102,'2026'!$O:$O,J$4) -> 0 | K102: =SUMIFS('2026'!$L:$L,'2026'!$J:$J,$B102&$C102,'2026'!$O:$O,K$4) -> 18489.6 | ... O102: =SUMIFS('2026'!$L:$L,'2026'!$J:$J,$B102&$C102,'2026'!$O:$O,O$4) -> 0 | P102: =SUM(D102:O102) -> 197044.92 | Q102: 120083 | R102: =P102-Q102 -> 76961.92 | S102: =IF(ISERROR(R102/Q102),"",R102/Q102) -> 0.64090604 | T102: Includes Van SW, C&C IH & OOH | U102: 338227
A103: MG Sticks | B103: 3910 | C103: MG Sticks | D103: =SUMIFS('2026'!$L:$L,'2026'!$J:$J,$B103&$C103,'2026'!$O:$O,D$4) -> 0 | E103: =SUMIFS('2026'!$L:$L,'2026'!$J:$J,$B103&$C103,'2026'!$O:$O,E$4) -> 0 | F103: =SUMIFS('2026'!$L:$L,'2026'!$J:$J,$B103&$C103,'2026'!$O:$O,F$4) -> 0 | G103: =SUMIFS('2026'!$L:$L,'2026'!$J:$J,$B103&$C103,'2026'!$O:$O,G$4) -> 0 | H103: =SUMIFS('2026'!$L:$L,'2026'!$J:$J,$B103&$C103,'2026'!$O:$O,H$4) -> 0 | I103: =SUMIFS('2026'!$L:$L,'2026'!$J:$J,$B103&$C103,'2026'!$O:$O,I$4) -> 0 | J103: =SUMIFS('2026'!$L:$L,'2026'!$J:$J,$B103&$C103,'2026'!$O:$O,J$4) -> 0 | K103: =SUMIFS('2026'!$L:$L,'2026'!$J:$J,$B103&$C103,'2026'!$O:$O,K$4) -> 0 | ... O103: =SUMIFS('2026'!$L:$L,'2026'!$J:$J,$B103&$C103,'2026'!$O:$O,O$4) -> 0 | P103: =SUM(D103:O103) -> 0 | Q103: 0 | R103: =P103-Q103 -> 0 | S103: =IF(ISERROR(R103/Q103),"",R103/Q103) | U103: 0
A104: PG | B104: 3910 | C104: PG | D104: =SUMIFS('2026'!$L:$L,'2026'!$J:$J,$B104&$C104,'2026'!$O:$O,D$4) -> 0 | E104: =SUMIFS('2026'!$L:$L,'2026'!$J:$J,$B104&$C104,'2026'!$O:$O,E$4) -> 0 | F104: =SUMIFS('2026'!$L:$L,'2026'!$J:$J,$B104&$C104,'2026'!$O:$O,F$4) -> 0 | G104: =SUMIFS('2026'!$L:$L,'2026'!$J:$J,$B104&$C104,'2026'!$O:$O,G$4) -> 0 | H104: =SUMIFS('2026'!$L:$L,'2026'!$J:$J,$B104&$C104,'2026'!$O:$O,H$4) -> 0 | I104: =SUMIFS('2026'!$L:$L,'2026'!$J:$J,$B104&$C104,'2026'!$O:$O,I$4) -> 0 | J104: =SUMIFS('2026'!$L:$L,'2026'!$J:$J,$B104&$C104,'2026'!$O:$O,J$4) -> 0 | K104: =SUMIFS('2026'!$L:$L,'2026'!$J:$J,$B104&$C104,'2026'!$O:$O,K$4) -> 0 | ... O104: =SUMIFS('2026'!$L:$L,'2026'!$J:$J,$B104&$C104,'2026'!$O:$O,O$4) -> 0 | P104: =SUM(D104:O104) -> 0 | Q104: 0 | R104: =P104-Q104 -> 0 | S104: =IF(ISERROR(R104/Q104),"",R104/Q104) | U104: 0
A105: EFW | B105: 3910 | C105: EFW | D105: =SUMIFS('2026'!$L:$L,'2026'!$J:$J,$B105&$C105,'2026'!$O:$O,D$4) -> 0 | E105: =SUMIFS('2026'!$L:$L,'2026'!$J:$J,$B105&$C105,'2026'!$O:$O,E$4) -> 9618 | F105: =SUMIFS('2026'!$L:$L,'2026'!$J:$J,$B105&$C105,'2026'!$O:$O,F$4) -> 240 | G105: =SUMIFS('2026'!$L:$L,'2026'!$J:$J,$B105&$C105,'2026'!$O:$O,G$4) -> 18662.4 | H105: =SUMIFS('2026'!$L:$L,'2026'!$J:$J,$B105&$C105,'2026'!$O:$O,H$4) -> 41472 | I105: =SUMIFS('2026'!$L:$L,'2026'!$J:$J,$B105&$C105,'2026'!$O:$O,I$4) -> 121472 | J105: =SUMIFS('2026'!$L:$L,'2026'!$J:$J,$B105&$C105,'2026'!$O:$O,J$4) -> 142208 | K105: =SUMIFS('2026'!$L:$L,'2026'!$J:$J,$B105&$C105,'2026'!$O:$O,K$4) -> 122208 | ... O105: =SUMIFS('2026'!$L:$L,'2026'!$J:$J,$B105&$C105,'2026'!$O:$O,O$4) -> 20000 | P105: =SUM(D105:O105) -> 680296.4 | Q105: 480000 | R105: =P105-Q105 -> 200296.4 | S105: =IF(ISERROR(R105/Q105),"",R105/Q105) -> 0.41728417 | T105: KL Origina | U105: 0
A106: MG Sticks | B106: Veszprem | C106: MG Sticks | D106: =SUMIFS('2026'!$L:$L,'2026'!$J:$J,$B106&$C106,'2026'!$O:$O,D$4) -> 0 | E106: =SUMIFS('2026'!$L:$L,'2026'!$J:$J,$B106&$C106,'2026'!$O:$O,E$4) -> 0 | F106: =SUMIFS('2026'!$L:$L,'2026'!$J:$J,$B106&$C106,'2026'!$O:$O,F$4) -> 0 | G106: =SUMIFS('2026'!$L:$L,'2026'!$J:$J,$B106&$C106,'2026'!$O:$O,G$4) -> 0 | H106: =SUMIFS('2026'!$L:$L,'2026'!$J:$J,$B106&$C106,'2026'!$O:$O,H$4) -> 146880 | I106: =SUMIFS('2026'!$L:$L,'2026'!$J:$J,$B106&$C106,'2026'!$O:$O,I$4) -> 0 | J106: =SUMIFS('2026'!$L:$L,'2026'!$J:$J,$B106&$C106,'2026'!$O:$O,J$4) -> 0 | K106: =SUMIFS('2026'!$L:$L,'2026'!$J:$J,$B106&$C106,'2026'!$O:$O,K$4) -> 0 | ... O106: =SUMIFS('2026'!$L:$L,'2026'!$J:$J,$B106&$C106,'2026'!$O:$O,O$4) -> 0 | P106: =SUM(D106:O106) -> 146880 | Q106: 146880 | R106: =P106-Q106 -> 0 | S106: =IF(ISERROR(R106/Q106),"",R106/Q106) -> 0 | U106: 113399
...

Sheet Litons Post Attain
C3: STA ALBANS
A4: Tech Rollup | B4: Plant | C4: Row Labels | D4: Jan | E4: Feb | F4: Mar | G4: Apr | H4: May | I4: Jun | J4: Jul | K4: Aug | L4: Sep | M4: Oct | N4: Nov | O4: Dec | P4: 2026 MRF3 | Q4: 2026 MRF2 | R4: Difference | S4: % change | T4: Commentary | U4: 2025 Final | V4: 2025 MRF8 | W4: 2025 MRF7 | X4: 2024 MRF12 | Y4: Vs YAG MRF8 | Z4: VS YA | AA4: Type | AB4: 2026 MRF7
A5: 2.4 Gal | B5: 5914 | C5: 2.4 Gal | D5: =SUMIFS('2026'!$M:$M,'2026'!$J:$J,$B5&$C5,'2026'!$O:$O,D$4) -> 371.29852 | E5: =SUMIFS('2026'!$M:$M,'2026'!$J:$J,$B5&$C5,'2026'!$O:$O,E$4) -> 767.1967 | F5: =SUMIFS('2026'!$M:$M,'2026'!$J:$J,$B5&$C5,'2026'!$O:$O,F$4) -> 577.01471 | G5: =SUMIFS('2026'!$M:$M,'2026'!$J:$J,$B5&$C5,'2026'!$O:$O,G$4) -> 578.23283 | H5: =SUMIFS('2026'!$M:$M,'2026'!$J:$J,$B5&$C5,'2026'!$O:$O,H$4) -> 874.45591 | I5: =SUMIFS('2026'!$M:$M,'2026'!$J:$J,$B5&$C5,'2026'!$O:$O,I$4) -> 248.96257 | J5: =SUMIFS('2026'!$M:$M,'2026'!$J:$J,$B5&$C5,'2026'!$O:$O,J$4) -> 461.78331 | K5: =SUMIFS('2026'!$M:$M,'2026'!$J:$J,$B5&$C5,'2026'!$O:$O,K$4) -> 481.861 | ... O5: =SUMIFS('2026'!$M:$M,'2026'!$J:$J,$B5&$C5,'2026'!$O:$O,O$4) -> 0 | P5: =SUM(D5:O5) -> 5147.8471 | Q5: 4586.1812 | R5: =P5-Q5 -> 561.66588 | S5: =IF(ISERROR(R5/Q5),"",R5/Q5) -> 0.12246919 | U5: 4266.1069 | V5: 4393.3133 | W5: 4725.0633 | X5: 4511.154 | Y5: =P5/V5-1 -> 0.17174595 | Z5: =P5-V5 -> 754.53378 | AA5: UL | AB5: 4780.8133
A6: Other | B6: 5914 | C6: Quarts | D6: =SUMIFS('2026'!$M:$M,'2026'!$J:$J,$B6&$C6,'2026'!$O:$O,D$4) -> 0 | E6: =SUMIFS('2026'!$M:$M,'2026'!$J:$J,$B6&$C6,'2026'!$O:$O,E$4) -> 0 | F6: =SUMIFS('2026'!$M:$M,'2026'!$J:$J,$B6&$C6,'2026'!$O:$O,F$4) -> 0 | G6: =SUMIFS('2026'!$M:$M,'2026'!$J:$J,$B6&$C6,'2026'!$O:$O,G$4) -> 0 | H6: =SUMIFS('2026'!$M:$M,'2026'!$J:$J,$B6&$C6,'2026'!$O:$O,H$4) -> 0 | I6: =SUMIFS('2026'!$M:$M,'2026'!$J:$J,$B6&$C6,'2026'!$O:$O,I$4) -> 0 | J6: =SUMIFS('2026'!$M:$M,'2026'!$J:$J,$B6&$C6,'2026'!$O:$O,J$4) -> 0 | K6: =SUMIFS('2026'!$M:$M,'2026'!$J:$J,$B6&$C6,'2026'!$O:$O,K$4) -> 0 | ... O6: =SUMIFS('2026'!$M:$M,'2026'!$J:$J,$B6&$C6,'2026'!$O:$O,O$4) -> 0 | P6: =SUM(D6:O6) -> 0 | Q6: 0 | R6: =P6-Q6 -> 0 | S6: =IF(ISERROR(R6/Q6),"",R6/Q6) | U6: 1595.9004 | V6: 1783.1493 | W6: 2310.8503 | X6: 839.41315 | Y6: =P6/V6-1 -> -1 | Z6: =P6-V6 -> -1783.1493 | AA6: UL | AB6: 2346.5851
A7: BJ PTS | B7: 5914 | C7: PTS Exports | D7: =SUMIFS('2026'!$M:$M,'2026'!$J:$J,$B7&$C7,'2026'!$O:$O,D$4) -> 209.90622 | E7: =SUMIFS('2026'!$M:$M,'2026'!$J:$J,$B7&$C7,'2026'!$O:$O,E$4) -> 0 | F7: =SUMIFS('2026'!$M:$M,'2026'!$J:$J,$B7&$C7,'2026'!$O:$O,F$4) -> 281.91622 | G7: =SUMIFS('2026'!$M:$M,'2026'!$J:$J,$B7&$C7,'2026'!$O:$O,G$4) -> 120.29645 | H7: =SUMIFS('2026'!$M:$M,'2026'!$J:$J,$B7&$C7,'2026'!$O:$O,H$4) -> 234.0798 | I7: =SUMIFS('2026'!$M:$M,'2026'!$J:$J,$B7&$C7,'2026'!$O:$O,I$4) -> 0 | J7: =SUMIFS('2026'!$M:$M,'2026'!$J:$J,$B7&$C7,'2026'!$O:$O,J$4) -> 0 | K7: =SUMIFS('2026'!$M:$M,'2026'!$J:$J,$B7&$C7,'2026'!$O:$O,K$4) -> 0 | ... O7: =SUMIFS('2026'!$M:$M,'2026'!$J:$J,$B7&$C7,'2026'!$O:$O,O$4) -> 0 | P7: =SUM(D7:O7) -> 846.19869 | Q7: 546.61954 | R7: =P7-Q7 -> 299.57915 | S7: =IF(ISERROR(R7/Q7),"",R7/Q7) -> 0.5480579 | U7: 1649.0903 | V7: 1861.0493 | W7: 1431.4722 | X7: 1311.5092 | Y7: =P7/V7-1 -> -0.54531097 | Z7: =P7-V7 -> -1014.8506 | AA7: UL | AB7: 0
A8: B&J Cups | B8: 5914 | C8: Cup Exports | D8: =SUMIFS('2026'!$M:$M,'2026'!$J:$J,$B8&$C8,'2026'!$O:$O,D$4) -> 0 | E8: =SUMIFS('2026'!$M:$M,'2026'!$J:$J,$B8&$C8,'2026'!$O:$O,E$4) -> 0 | F8: =SUMIFS('2026'!$M:$M,'2026'!$J:$J,$B8&$C8,'2026'!$O:$O,F$4) -> 0 | G8: =SUMIFS('2026'!$M:$M,'2026'!$J:$J,$B8&$C8,'2026'!$O:$O,G$4) -> 0 | H8: =SUMIFS('2026'!$M:$M,'2026'!$J:$J,$B8&$C8,'2026'!$O:$O,H$4) -> 0 | I8: =SUMIFS('2026'!$M:$M,'2026'!$J:$J,$B8&$C8,'2026'!$O:$O,I$4) -> 0 | J8: =SUMIFS('2026'!$M:$M,'2026'!$J:$J,$B8&$C8,'2026'!$O:$O,J$4) -> 0 | K8: =SUMIFS('2026'!$M:$M,'2026'!$J:$J,$B8&$C8,'2026'!$O:$O,K$4) -> 0 | ... O8: =SUMIFS('2026'!$M:$M,'2026'!$J:$J,$B8&$C8,'2026'!$O:$O,O$4) -> 0 | P8: =SUM(D8:O8) -> 0 | Q8: 0 | R8: =P8-Q8 -> 0 | S8: =IF(ISERROR(R8/Q8),"",R8/Q8) | U8: 0 | V8: 0 | W8: 0 | X8: 66.42864 | Y8: =P8/V8-1 -> #DIV/0! | Z8: =P8-V8 -> 0 | AA8: UL | AB8: 0
A9: 2.4 Gal | B9: 5914 | C9: Bulk Exports | D9: =SUMIFS('2026'!$M:$M,'2026'!$J:$J,$B9&$C9,'2026'!$O:$O,D$4) -> 0 | E9: =SUMIFS('2026'!$M:$M,'2026'!$J:$J,$B9&$C9,'2026'!$O:$O,E$4) -> 0 | F9: =SUMIFS('2026'!$M:$M,'2026'!$J:$J,$B9&$C9,'2026'!$O:$O,F$4) -> 0 | G9: =SUMIFS('2026'!$M:$M,'2026'!$J:$J,$B9&$C9,'2026'!$O:$O,G$4) -> 0 | H9: =SUMIFS('2026'!$M:$M,'2026'!$J:$J,$B9&$C9,'2026'!$O:$O,H$4) -> 0 | I9: =SUMIFS('2026'!$M:$M,'2026'!$J:$J,$B9&$C9,'2026'!$O:$O,I$4) -> 0 | J9: =SUMIFS('2026'!$M:$M,'2026'!$J:$J,$B9&$C9,'2026'!$O:$O,J$4) -> 0 | K9: =SUMIFS('2026'!$M:$M,'2026'!$J:$J,$B9&$C9,'2026'!$O:$O,K$4) -> 0 | ... O9: =SUMIFS('2026'!$M:$M,'2026'!$J:$J,$B9&$C9,'2026'!$O:$O,O$4) -> 0 | P9: =SUM(D9:O9) -> 0 | Q9: 0 | R9: =P9-Q9 -> 0 | S9: =IF(ISERROR(R9/Q9),"",R9/Q9) | U9: 0 | V9: 0 | W9: 0 | X9: 0 | Y9: =P9/V9-1 -> #DIV/0! | Z9: =P9-V9 -> 0 | AA9: UL | AB9: 0
A10: B&J Cups | B10: 5914 | C10: B&J Cups | D10: =SUMIFS('2026'!$M:$M,'2026'!$J:$J,$B10&$C10,'2026'!$O:$O,D$4) -> 0 | E10: =SUMIFS('2026'!$M:$M,'2026'!$J:$J,$B10&$C10,'2026'!$O:$O,E$4) -> 0 | F10: =SUMIFS('2026'!$M:$M,'2026'!$J:$J,$B10&$C10,'2026'!$O:$O,F$4) -> 0 | G10: =SUMIFS('2026'!$M:$M,'2026'!$J:$J,$B10&$C10,'2026'!$O:$O,G$4) -> 0 | H10: =SUMIFS('2026'!$M:$M,'2026'!$J:$J,$B10&$C10,'2026'!$O:$O,H$4) -> 0 | I10: =SUMIFS('2026'!$M:$M,'2026'!$J:$J,$B10&$C10,'2026'!$O:$O,I$4) -> 0 | J10: =SUMIFS('2026'!$M:$M,'2026'!$J:$J,$B10&$C10,'2026'!$O:$O,J$4) -> 0 | K10: =SUMIFS('2026'!$M:$M,'2026'!$J:$J,$B10&$C10,'2026'!$O:$O,K$4) -> 0 | ... O10: =SUMIFS('2026'!$M:$M,'2026'!$J:$J,$B10&$C10,'2026'!$O:$O,O$4) -> 0 | P10: =SUM(D10:O10) -> 0 | Q10: 0 | R10: =P10-Q10 -> 0 | S10: =IF(ISERROR(R10/Q10),"",R10/Q10) | U10: 0 | V10: 0 | W10: 0 | X10: 1215.7807 | Y10: =P10/V10-1 -> #DIV/0! | Z10: =P10-V10 -> 0 | AA10: UL | AB10: 0
A11: B&J Cups | B11: 5914 | C11: B&J Dog Treat | D11: =SUMIFS('2026'!$M:$M,'2026'!$J:$J,$B11&$C11,'2026'!$O:$O,D$4) -> 0 | E11: =SUMIFS('2026'!$M:$M,'2026'!$J:$J,$B11&$C11,'2026'!$O:$O,E$4) -> 0 | F11: =SUMIFS('2026'!$M:$M,'2026'!$J:$J,$B11&$C11,'2026'!$O:$O,F$4) -> 0 | G11: =SUMIFS('2026'!$M:$M,'2026'!$J:$J,$B11&$C11,'2026'!$O:$O,G$4) -> 0 | H11: =SUMIFS('2026'!$M:$M,'2026'!$J:$J,$B11&$C11,'2026'!$O:$O,H$4) -> 0 | I11: =SUMIFS('2026'!$M:$M,'2026'!$J:$J,$B11&$C11,'2026'!$O:$O,I$4) -> 0 | J11: =SUMIFS('2026'!$M:$M,'2026'!$J:$J,$B11&$C11,'2026'!$O:$O,J$4) -> 0 | K11: =SUMIFS('2026'!$M:$M,'2026'!$J:$J,$B11&$C11,'2026'!$O:$O,K$4) -> 0 | ... O11: =SUMIFS('2026'!$M:$M,'2026'!$J:$J,$B11&$C11,'2026'!$O:$O,O$4) -> 0 | P11: =SUM(D11:O11) -> 0 | Q11: 0 | R11: =P11-Q11 -> 0 | S11: =IF(ISERROR(R11/Q11),"",R11/Q11) | U11: 0 | V11: 0 | W11: 0 | X11: 90.575711 | Y11: =P11/V11-1 -> #DIV/0! | Z11: =P11-V11 -> 0 | AA11: UL | AB11: 0
A12: SP1 | B12: 5914 | C12: PTS - BR | D12: =SUMIFS('2026'!$M:$M,'2026'!$J:$J,$B12&$C12,'2026'!$O:$O,D$4) -> 0 | E12: =SUMIFS('2026'!$M:$M,'2026'!$J:$J,$B12&$C12,'2026'!$O:$O,E$4) -> 0 | F12: =SUMIFS('2026'!$M:$M,'2026'!$J:$J,$B12&$C12,'2026'!$O:$O,F$4) -> 0 | G12: =SUMIFS('2026'!$M:$M,'2026'!$J:$J,$B12&$C12,'2026'!$O:$O,G$4) -> 0 | H12: =SUMIFS('2026'!$M:$M,'2026'!$J:$J,$B12&$C12,'2026'!$O:$O,H$4) -> 0 | I12: =SUMIFS('2026'!$M:$M,'2026'!$J:$J,$B12&$C12,'2026'!$O:$O,I$4) -> 0 | J12: =SUMIFS('2026'!$M:$M,'2026'!$J:$J,$B12&$C12,'2026'!$O:$O,J$4) -> 0 | K12: =SUMIFS('2026'!$M:$M,'2026'!$J:$J,$B12&$C12,'2026'!$O:$O,K$4) -> 0 | ... O12: =SUMIFS('2026'!$M:$M,'2026'!$J:$J,$B12&$C12,'2026'!$O:$O,O$4) -> 0 | P12: =SUM(D12:O12) -> 0 | Q12: 0 | R12: =P12-Q12 -> 0 | S12: =IF(ISERROR(R12/Q12),"",R12/Q12) | U12: 0 | V12: 0 | W12: 0 | X12: 0 | Y12: =P12/V12-1 -> #DIV/0! | Z12: =P12-V12 -> 0 | AA12: UL | AB12: 0
A13: BJ PTS | B13: 5914 | C13: BJ PTS | D13: =SUMIFS('2026'!$M:$M,'2026'!$J:$J,$B13&$C13,'2026'!$O:$O,D$4) -> 4047.3508 | E13: =SUMIFS('2026'!$M:$M,'2026'!$J:$J,$B13&$C13,'2026'!$O:$O,E$4) -> 5739.5715 | F13: =SUMIFS('2026'!$M:$M,'2026'!$J:$J,$B13&$C13,'2026'!$O:$O,F$4) -> 6752.8084 | G13: =SUMIFS('2026'!$M:$M,'2026'!$J:$J,$B13&$C13,'2026'!$O:$O,G$4) -> 4725.9196 | H13: =SUMIFS('2026'!$M:$M,'2026'!$J:$J,$B13&$C13,'2026'!$O:$O,H$4) -> 3820.7458 | I13: =SUMIFS('2026'!$M:$M,'2026'!$J:$J,$B13&$C13,'2026'!$O:$O,I$4) -> 4554.1867 | J13: =SUMIFS('2026'!$M:$M,'2026'!$J:$J,$B13&$C13,'2026'!$O:$O,J$4) -> 4793.8808 | K13: =SUMIFS('2026'!$M:$M,'2026'!$J:$J,$B13&$C13,'2026'!$O:$O,K$4) -> 5273.2688 | ... O13: =SUMIFS('2026'!$M:$M,'2026'!$J:$J,$B13&$C13,'2026'!$O:$O,O$4) -> 4187.5959 | P13: =SUM(D13:O13) -> 57670.686 | Q13: 58212.488 | R13: =P13-Q13 -> -541.80203 | S13: =IF(ISERROR(R13/Q13),"",R13/Q13) -> -0.0093073162 | U13: 57943.937 | V13: 56361.537 | W13: 56669.026 | X13: 64060.535 | Y13: =P13/V13-1 -> 0.023227697 | Z13: =P13-V13 -> 1309.1487 | AA13: UL | AB13: 56967.889
C14: Total St. Albans | D14: =SUM(D5:D13) -> 4628.5556 | E14: =SUM(E5:E13) -> 6506.7682 | F14: =SUM(F5:F13) -> 7611.7393 | G14: =SUM(G5:G13) -> 5424.4489 | H14: =SUM(H5:H13) -> 4929.2815 | I14: =SUM(I5:I13) -> 4803.1493 | J14: =SUM(J5:J13) -> 5255.6641 | K14: =SUM(K5:K13) -> 5755.1299 | ... P14: =SUM(P5:P13) -> 63664.731 | Q14: 63345.288 | R14: =SUM(R5:R13) -> 319.44301 | S14: =IF(ISERROR(R14/Q14),"",R14/Q14) -> 0.0050428851 | T14: 3 lines 24.7% | U14: 65455.035 | V14: 64399.049 | W14: 65136.412 | X14: 72095.396 | Y14: =P14/V14-1 -> -0.011402613 | Z14: =P14-V14 -> -734.31746 | AB14: 64095.288
C16: WATERBURY | R16: Vs PV | T16: Commentary
C17: Row Labels | D17: Jan | E17: Feb | F17: Mar | G17: Apr | H17: May | I17: Jun | J17: Jul | K17: Aug | L17: Sep | M17: Oct | N17: Nov | O17: Dec | P17: =P$4 -> 2026 MRF3 | Q17: 2026 MRF2 | R17: =R$4 -> Difference | S17: =S$4 -> % change | U17: 2025 Final | V17: 2025 MRF8 | W17: 2025 MRF7 | X17: 2024 MRF12 | AB17: 2026 MRF7
A18: Other | B18: 5911 | C18: 1 Gal | D18: =SUMIFS('2026'!$M:$M,'2026'!$J:$J,$B18&$C18,'2026'!$O:$O,D$4) -> 0 | E18: =SUMIFS('2026'!$M:$M,'2026'!$J:$J,$B18&$C18,'2026'!$O:$O,E$4) -> 0 | F18: =SUMIFS('2026'!$M:$M,'2026'!$J:$J,$B18&$C18,'2026'!$O:$O,F$4) -> 0 | G18: =SUMIFS('2026'!$M:$M,'2026'!$J:$J,$B18&$C18,'2026'!$O:$O,G$4) -> 0 | H18: =SUMIFS('2026'!$M:$M,'2026'!$J:$J,$B18&$C18,'2026'!$O:$O,H$4) -> 0 | I18: =SUMIFS('2026'!$M:$M,'2026'!$J:$J,$B18&$C18,'2026'!$O:$O,I$4) -> 0 | J18: =SUMIFS('2026'!$M:$M,'2026'!$J:$J,$B18&$C18,'2026'!$O:$O,J$4) -> 0 | K18: =SUMIFS('2026'!$M:$M,'2026'!$J:$J,$B18&$C18,'2026'!$O:$O,K$4) -> 0 | ... O18: =SUMIFS('2026'!$M:$M,'2026'!$J:$J,$B18&$C18,'2026'!$O:$O,O$4) -> 0 | P18: =SUM(D18:O18) -> 0 | Q18: 0 | R18: =P18-Q18 -> 0 | S18: =IF(ISERROR(R18/Q18),"",R18/Q18) | U18: 0 | V18: 0 | W18: 0 | X18: 0 | Y18: =P18/V18-1 -> #DIV/0! | Z18: =P18-V18 -> 0 | AA18: UL | AB18: 0
A19: Other | B19: 5911 | C19: QTS | D19: =SUMIFS('2026'!$M:$M,'2026'!$J:$J,$B19&$C19,'2026'!$O:$O,D$4) -> 0 | E19: =SUMIFS('2026'!$M:$M,'2026'!$J:$J,$B19&$C19,'2026'!$O:$O,E$4) -> 0 | F19: =SUMIFS('2026'!$M:$M,'2026'!$J:$J,$B19&$C19,'2026'!$O:$O,F$4) -> 0 | G19: =SUMIFS('2026'!$M:$M,'2026'!$J:$J,$B19&$C19,'2026'!$O:$O,G$4) -> 0 | H19: =SUMIFS('2026'!$M:$M,'2026'!$J:$J,$B19&$C19,'2026'!$O:$O,H$4) -> 0 | I19: =SUMIFS('2026'!$M:$M,'2026'!$J:$J,$B19&$C19,'2026'!$O:$O,I$4) -> 0 | J19: =SUMIFS('2026'!$M:$M,'2026'!$J:$J,$B19&$C19,'2026'!$O:$O,J$4) -> 0 | K19: =SUMIFS('2026'!$M:$M,'2026'!$J:$J,$B19&$C19,'2026'!$O:$O,K$4) -> 0 | ... O19: =SUMIFS('2026'!$M:$M,'2026'!$J:$J,$B19&$C19,'2026'!$O:$O,O$4) -> 0 | P19: =SUM(D19:O19) -> 0 | Q19: 0 | R19: =P19-Q19 -> 0 | S19: =IF(ISERROR(R19/Q19),"",R19/Q19) | U19: 0 | V19: 0 | W19: 0 | X19: 0 | Y19: =P19/V19-1 -> #DIV/0! | Z19: =P19-V19 -> 0 | AA19: UL | AB19: 0
A20: BJ PTS | B20: 5911 | C20: PTS Exports | D20: =SUMIFS('2026'!$M:$M,'2026'!$J:$J,$B20&$C20,'2026'!$O:$O,D$4) -> 40.48396 | E20: =SUMIFS('2026'!$M:$M,'2026'!$J:$J,$B20&$C20,'2026'!$O:$O,E$4) -> 33.390016 | F20: =SUMIFS('2026'!$M:$M,'2026'!$J:$J,$B20&$C20,'2026'!$O:$O,F$4) -> 51.25428 | G20: =SUMIFS('2026'!$M:$M,'2026'!$J:$J,$B20&$C20,'2026'!$O:$O,G$4) -> 40.59648 | H20: =SUMIFS('2026'!$M:$M,'2026'!$J:$J,$B20&$C20,'2026'!$O:$O,H$4) -> 0 | I20: =SUMIFS('2026'!$M:$M,'2026'!$J:$J,$B20&$C20,'2026'!$O:$O,I$4) -> 0 | J20: =SUMIFS('2026'!$M:$M,'2026'!$J:$J,$B20&$C20,'2026'!$O:$O,J$4) -> 0 | K20: =SUMIFS('2026'!$M:$M,'2026'!$J:$J,$B20&$C20,'2026'!$O:$O,K$4) -> 0 | ... O20: =SUMIFS('2026'!$M:$M,'2026'!$J:$J,$B20&$C20,'2026'!$O:$O,O$4) -> 0 | P20: =SUM(D20:O20) -> 165.72474 | Q20: 171.95526 | R20: =P20-Q20 -> -6.23052 | U20: 1016.0536 | V20: 1978.4506 | W20: 1709.5618 | X20: 1079.6825 | Y20: =P20/V20-1 -> -0.91623509 | Z20: =P20-V20 -> -1812.7258 | AA20: UL | AB20: 0
A21: BJ PTS | B21: 5911 | C21: BJ PTS | D21: =SUMIFS('2026'!$M:$M,'2026'!$J:$J,$B21&$C21,'2026'!$O:$O,D$4) -> 2370.1704 | E21: =SUMIFS('2026'!$M:$M,'2026'!$J:$J,$B21&$C21,'2026'!$O:$O,E$4) -> 2787.5273 | F21: =SUMIFS('2026'!$M:$M,'2026'!$J:$J,$B21&$C21,'2026'!$O:$O,F$4) -> 3564.3061 | G21: =SUMIFS('2026'!$M:$M,'2026'!$J:$J,$B21&$C21,'2026'!$O:$O,G$4) -> 2659.6373 | H21: =SUMIFS('2026'!$M:$M,'2026'!$J:$J,$B21&$C21,'2026'!$O:$O,H$4) -> 2966.7634 | I21: =SUMIFS('2026'!$M:$M,'2026'!$J:$J,$B21&$C21,'2026'!$O:$O,I$4) -> 2732.7155 | J21: =SUMIFS('2026'!$M:$M,'2026'!$J:$J,$B21&$C21,'2026'!$O:$O,J$4) -> 2890.5319 | K21: =SUMIFS('2026'!$M:$M,'2026'!$J:$J,$B21&$C21,'2026'!$O:$O,K$4) -> 2907.1442 | ... O21: =SUMIFS('2026'!$M:$M,'2026'!$J:$J,$B21&$C21,'2026'!$O:$O,O$4) -> 1514.1376 | P21: =SUM(D21:O21) -> 27951.157 | Q21: 26701.794 | R21: =P21-Q21 -> 1249.3636 | S21: =IF(ISERROR(R21/Q21),"",R21/Q21) -> 0.046789501 | T21: Still assuming 10 weeks down | U21: 31182.785 | V21: 31464.71 | W21: 30988.984 | X21: 31610.79 | Y21: =P21/V21-1 -> -0.11166647 | Z21: =P21-V21 -> -3513.5532 | AA21: UL | AB21: 30472.322
C22: Total Waterbury | D22: =SUM(D18:D21) -> 2410.6544 | E22: =SUM(E18:E21) -> 2820.9173 | F22: =SUM(F18:F21) -> 3615.5604 | G22: =SUM(G18:G21) -> 2700.2338 | H22: =SUM(H18:H21) -> 2966.7634 | I22: =SUM(I18:I21) -> 2732.7155 | J22: =SUM(J18:J21) -> 2890.5319 | K22: =SUM(K18:K21) -> 2907.1442 | ... P22: =SUM(P18:P21) -> 28116.882 | Q22: 26873.749 | R22: =SUM(R18:R21) -> 1243.1331 | S22: =IF(ISERROR(R22/Q22),"",R22/Q22) -> 0.046258268 | U22: 32198.839 | V22: 33443.161 | W22: 32698.545 | X22: 32690.473 | Y22: =P22/V22-1 -> -0.15926363 | Z22: =P22-V22 -> -5326.279 | AB22: 30472.322
P23: =P22+P14 -> 91781.613 | Q23: 90219.037 | R23: =P23-Q23 -> 1562.5761 | S23: =IF(ISERROR(R23/Q23),"",R23/Q23) -> 0.017319805 | U23: 97653.874 | V23: 97842.21 | W23: =W22+W14 -> 97834.957 | X23: =X22+X14 -> 104785.87 | Y23: =P23/V23-1 -> -0.061942555 | Z23: =P23-V23 -> -6060.5965 | AB23: 94567.61
C24: SIKESTON NORTH | R24: Vs PV | T24: Commentary
C25: Row Labels | D25: Jan | E25: Feb | F25: Mar | G25: Apr | H25: May | I25: Jun | J25: Jul | K25: Aug | L25: Sep | M25: Oct | N25: Nov | O25: Dec | P25: =P$4 -> 2026 MRF3 | Q25: 2026 MRF2 | R25: =R$4 -> Difference | S25: =S$4 -> % change | U25: 2025 Final | V25: 2025 MRF8 | W25: 2025 MRF7 | X25: 2024 MRF12 | Y25: VS YAG | AB25: 2026 MRF7
A26: 48oz | B26: 2904 | C26: 48oz | D26: =SUMIFS('2026'!$M:$M,'2026'!$J:$J,$B26&$C26,'2026'!$O:$O,D$4) -> 7733.7313 | E26: =SUMIFS('2026'!$M:$M,'2026'!$J:$J,$B26&$C26,'2026'!$O:$O,E$4) -> 9012.3946 | F26: =SUMIFS('2026'!$M:$M,'2026'!$J:$J,$B26&$C26,'2026'!$O:$O,F$4) -> 11222.138 | G26: =SUMIFS('2026'!$M:$M,'2026'!$J:$J,$B26&$C26,'2026'!$O:$O,G$4) -> 9529.7162 | H26: =SUMIFS('2026'!$M:$M,'2026'!$J:$J,$B26&$C26,'2026'!$O:$O,H$4) -> 8375.7147 | I26: =SUMIFS('2026'!$M:$M,'2026'!$J:$J,$B26&$C26,'2026'!$O:$O,I$4) -> 8394.2569 | J26: =SUMIFS('2026'!$M:$M,'2026'!$J:$J,$B26&$C26,'2026'!$O:$O,J$4) -> 8705.1553 | K26: =SUMIFS('2026'!$M:$M,'2026'!$J:$J,$B26&$C26,'2026'!$O:$O,K$4) -> 9326.9521 | ... O26: =SUMIFS('2026'!$M:$M,'2026'!$J:$J,$B26&$C26,'2026'!$O:$O,O$4) -> 5510.4961 | P26: =SUM(D26:O26) -> 98670.435 | Q26: 99088.629 | R26: =P26-Q26 -> -418.19399 | S26: =IF(ISERROR(R26/Q26),"",R26/Q26) -> -0.0042204034 | U26: 104658.28 | V26: 110052.08 | W26: 106954.05 | X26: 113929.04 | Y26: =P26/V26-1 -> -0.10342053 | Z26: =P26-V26 -> -11381.645 | AA26: UL | AB26: 107373.26
A27: EDF | B27: 2904 | C27: EDF | D27: =SUMIFS('2026'!$M:$M,'2026'!$J:$J,$B27&$C27,'2026'!$O:$O,D$4) -> 381.7812 | E27: =SUMIFS('2026'!$M:$M,'2026'!$J:$J,$B27&$C27,'2026'!$O:$O,E$4) -> 471.2838 | F27: =SUMIFS('2026'!$M:$M,'2026'!$J:$J,$B27&$C27,'2026'!$O:$O,F$4) -> 731.34385 | G27: =SUMIFS('2026'!$M:$M,'2026'!$J:$J,$B27&$C27,'2026'!$O:$O,G$4) -> 618.34752 | H27: =SUMIFS('2026'!$M:$M,'2026'!$J:$J,$B27&$C27,'2026'!$O:$O,H$4) -> 530.01216 | I27: =SUMIFS('2026'!$M:$M,'2026'!$J:$J,$B27&$C27,'2026'!$O:$O,I$4) -> 0 | J27: =SUMIFS('2026'!$M:$M,'2026'!$J:$J,$B27&$C27,'2026'!$O:$O,J$4) -> 0 | K27: =SUMIFS('2026'!$M:$M,'2026'!$J:$J,$B27&$C27,'2026'!$O:$O,K$4) -> 0 | ... O27: =SUMIFS('2026'!$M:$M,'2026'!$J:$J,$B27&$C27,'2026'!$O:$O,O$4) -> 0 | P27: =SUM(D27:O27) -> 2732.7685 | Q27: 3050.6596 | R27: =P27-Q27 -> -317.89108 | S27: =IF(ISERROR(R27/Q27),"",R27/Q27) -> -0.10420405 | U27: 7044.5691 | V27: 7455.3214 | W27: 8270.5362 | X27: 7219.6764 | Y27: =P27/V27-1 -> -0.63344725 | Z27: =P27-V27 -> -4722.5528 | AA27: UL | AB27: 4648.6692
A28: BJ Bars | B28: 2904 | C28: BJ Bars | D28: =SUMIFS('2026'!$M:$M,'2026'!$J:$J,$B28&$C28,'2026'!$O:$O,D$4) -> 0 | E28: =SUMIFS('2026'!$M:$M,'2026'!$J:$J,$B28&$C28,'2026'!$O:$O,E$4) -> 0 | F28: =SUMIFS('2026'!$M:$M,'2026'!$J:$J,$B28&$C28,'2026'!$O:$O,F$4) -> 0 | G28: =SUMIFS('2026'!$M:$M,'2026'!$J:$J,$B28&$C28,'2026'!$O:$O,G$4) -> 0 | H28: =SUMIFS('2026'!$M:$M,'2026'!$J:$J,$B28&$C28,'2026'!$O:$O,H$4) -> 0 | I28: =SUMIFS('2026'!$M:$M,'2026'!$J:$J,$B28&$C28,'2026'!$O:$O,I$4) -> 0 | J28: =SUMIFS('2026'!$M:$M,'2026'!$J:$J,$B28&$C28,'2026'!$O:$O,J$4) -> 0 | K28: =SUMIFS('2026'!$M:$M,'2026'!$J:$J,$B28&$C28,'2026'!$O:$O,K$4) -> 0 | ... O28: =SUMIFS('2026'!$M:$M,'2026'!$J:$J,$B28&$C28,'2026'!$O:$O,O$4) -> 0 | P28: =SUM(D28:O28) -> 0 | Q28: 0 | S28: =IF(ISERROR(R28/Q28),"",R28/Q28) | T28: Bars / Bites Volume NOT INCLUDED | U28: 0 | V28: 0 | W28: 0 | X28: 0 | Y28: =P28/V28-1 -> #DIV/0! | Z28: =P28-V28 -> 0 | AA28: UL | AB28: 0
A29: Other | B29: 2904 | C29: Other | D29: =SUMIFS('2026'!$M:$M,'2026'!$J:$J,$B29&$C29,'2026'!$O:$O,D$4) -> 0 | E29: =SUMIFS('2026'!$M:$M,'2026'!$J:$J,$B29&$C29,'2026'!$O:$O,E$4) -> 322.48762 | F29: =SUMIFS('2026'!$M:$M,'2026'!$J:$J,$B29&$C29,'2026'!$O:$O,F$4) -> 0.05676 | G29: =SUMIFS('2026'!$M:$M,'2026'!$J:$J,$B29&$C29,'2026'!$O:$O,G$4) -> 152.57088 | H29: =SUMIFS('2026'!$M:$M,'2026'!$J:$J,$B29&$C29,'2026'!$O:$O,H$4) -> 239.75424 | I29: =SUMIFS('2026'!$M:$M,'2026'!$J:$J,$B29&$C29,'2026'!$O:$O,I$4) -> 0 | J29: =SUMIFS('2026'!$M:$M,'2026'!$J:$J,$B29&$C29,'2026'!$O:$O,J$4) -> 63.207368 | K29: =SUMIFS('2026'!$M:$M,'2026'!$J:$J,$B29&$C29,'2026'!$O:$O,K$4) -> 84.276491 | ... O29: =SUMIFS('2026'!$M:$M,'2026'!$J:$J,$B29&$C29,'2026'!$O:$O,O$4) -> 84.276491 | P29: =SUM(D29:O29) -> 1194.0168 | Q29: 1063.3399 | R29: =P29-Q29 -> 130.67685 | S29: =IF(ISERROR(R29/Q29),"",R29/Q29) -> 0.12289282 | T29: New BR Pts | U29: 0 | V29: 0 | W29: 0 | X29: 6672.1279 | Y29: =P29/V29-1 -> #DIV/0! | Z29: =P29-V29 -> 1194.0168 | AA29: UL | AB29: 0
A30: MBG | B30: 2904 | C30: MBG | D30: =SUMIFS('2026'!$M:$M,'2026'!$J:$J,$B30&$C30,'2026'!$O:$O,D$4) -> 237.81677 | E30: =SUMIFS('2026'!$M:$M,'2026'!$J:$J,$B30&$C30,'2026'!$O:$O,E$4) -> 314.05683 | F30: =SUMIFS('2026'!$M:$M,'2026'!$J:$J,$B30&$C30,'2026'!$O:$O,F$4) -> 336.87834 | G30: =SUMIFS('2026'!$M:$M,'2026'!$J:$J,$B30&$C30,'2026'!$O:$O,G$4) -> 369.85037 | H30: =SUMIFS('2026'!$M:$M,'2026'!$J:$J,$B30&$C30,'2026'!$O:$O,H$4) -> 294.17472 | I30: =SUMIFS('2026'!$M:$M,'2026'!$J:$J,$B30&$C30,'2026'!$O:$O,I$4) -> 315.248 | J30: =SUMIFS('2026'!$M:$M,'2026'!$J:$J,$B30&$C30,'2026'!$O:$O,J$4) -> 362.5352 | K30: =SUMIFS('2026'!$M:$M,'2026'!$J:$J,$B30&$C30,'2026'!$O:$O,K$4) -> 346.7728 | ... O30: =SUMIFS('2026'!$M:$M,'2026'!$J:$J,$B30&$C30,'2026'!$O:$O,O$4) -> 0 | P30: =SUM(D30:O30) -> 3239.3538 | Q30: 3207.1575 | R30: =P30-Q30 -> 32.196352 | S30: =IF(ISERROR(R30/Q30),"",R30/Q30) -> 0.010038906 | U30: 2988.0056 | V30: 3249.8886 | W30: 3455.3093 | X30: 4006.9252 | Y30: =P30/V30-1 -> -0.0032415827 | Z30: =P30-V30 -> -10.534783 | AA30: UL | AB30: 3716.7739
A31: MG Sticks | B31: 2904 | C31: MG Sticks | D31: =SUMIFS('2026'!$M:$M,'2026'!$J:$J,$B31&$C31,'2026'!$O:$O,D$4) -> 1424.1782 | E31: =SUMIFS('2026'!$M:$M,'2026'!$J:$J,$B31&$C31,'2026'!$O:$O,E$4) -> 1540.2365 | F31: =SUMIFS('2026'!$M:$M,'2026'!$J:$J,$B31&$C31,'2026'!$O:$O,F$4) -> 1432.0751 | G31: =SUMIFS('2026'!$M:$M,'2026'!$J:$J,$B31&$C31,'2026'!$O:$O,G$4) -> 1926.7069 | H31: =SUMIFS('2026'!$M:$M,'2026'!$J:$J,$B31&$C31,'2026'!$O:$O,H$4) -> 1878.5211 | I31: =SUMIFS('2026'!$M:$M,'2026'!$J:$J,$B31&$C31,'2026'!$O:$O,I$4) -> 1855.4032 | J31: =SUMIFS('2026'!$M:$M,'2026'!$J:$J,$B31&$C31,'2026'!$O:$O,J$4) -> 1904.2256 | K31: =SUMIFS('2026'!$M:$M,'2026'!$J:$J,$B31&$C31,'2026'!$O:$O,K$4) -> 1870.2004 | ... O31: =SUMIFS('2026'!$M:$M,'2026'!$J:$J,$B31&$C31,'2026'!$O:$O,O$4) -> 0 | P31: =SUM(D31:O31) -> 15929.027 | Q31: 16972.213 | R31: =P31-Q31 -> -1043.1862 | S31: =IF(ISERROR(R31/Q31),"",R31/Q31) -> -0.061464359 | T31: Demand and Inventory | U31: 18530.169 | V31: 16217.468 | W31: 16493.612 | X31: 14708.683 | Y31: =P31/V31-1 -> -0.017785823 | Z31: =P31-V31 -> -288.441 | AA31: UL | AB31: 15353.304
A32: MG Sticks | B32: 2904 | C32: TAL NV | D32: =SUMIFS('2026'!$M:$M,'2026'!$J:$J,$B32&$C32,'2026'!$O:$O,D$4) -> 0 | E32: =SUMIFS('2026'!$M:$M,'2026'!$J:$J,$B32&$C32,'2026'!$O:$O,E$4) -> 0 | F32: =SUMIFS('2026'!$M:$M,'2026'!$J:$J,$B32&$C32,'2026'!$O:$O,F$4) -> 0 | G32: =SUMIFS('2026'!$M:$M,'2026'!$J:$J,$B32&$C32,'2026'!$O:$O,G$4) -> 0 | H32: =SUMIFS('2026'!$M:$M,'2026'!$J:$J,$B32&$C32,'2026'!$O:$O,H$4) -> 0 | I32: =SUMIFS('2026'!$M:$M,'2026'!$J:$J,$B32&$C32,'2026'!$O:$O,I$4) -> 0 | J32: =SUMIFS('2026'!$M:$M,'2026'!$J:$J,$B32&$C32,'2026'!$O:$O,J$4) -> 0 | K32: =SUMIFS('2026'!$M:$M,'2026'!$J:$J,$B32&$C32,'2026'!$O:$O,K$4) -> 0 | ... O32: =SUMIFS('2026'!$M:$M,'2026'!$J:$J,$B32&$C32,'2026'!$O:$O,O$4) -> 0 | P32: =SUM(D32:O32) -> 0 | Q32: 0 | R32: =P32-Q32 -> 0 | S32: =IF(ISERROR(R32/Q32),"",R32/Q32) | U32: 238.35042 | V32: 238.35042 | W32: 238.35042 | X32: 996.92604 | Y32: =P32/V32-1 -> -1 | Z32: =P32-V32 -> -238.35042 | AA32: UL | AB32: 0
A33: Yasso Sticks | B33: 2904 | C33: Yasso Sticks | D33: =SUMIFS('2026'!$M:$M,'2026'!$J:$J,$B33&$C33,'2026'!$O:$O,D$4) -> 1017.5065 | E33: =SUMIFS('2026'!$M:$M,'2026'!$J:$J,$B33&$C33,'2026'!$O:$O,E$4) -> 1159.8553 | F33: =SUMIFS('2026'!$M:$M,'2026'!$J:$J,$B33&$C33,'2026'!$O:$O,F$4) -> 952.21338 | G33: =SUMIFS('2026'!$M:$M,'2026'!$J:$J,$B33&$C33,'2026'!$O:$O,G$4) -> 981.0409 | H33: =SUMIFS('2026'!$M:$M,'2026'!$J:$J,$B33&$C33,'2026'!$O:$O,H$4) -> 779.328 | I33: =SUMIFS('2026'!$M:$M,'2026'!$J:$J,$B33&$C33,'2026'!$O:$O,I$4) -> 911.82672 | J33: =SUMIFS('2026'!$M:$M,'2026'!$J:$J,$B33&$C33,'2026'!$O:$O,J$4) -> 944.39196 | K33: =SUMIFS('2026'!$M:$M,'2026'!$J:$J,$B33&$C33,'2026'!$O:$O,K$4) -> 1009.5224 | ... O33: =SUMIFS('2026'!$M:$M,'2026'!$J:$J,$B33&$C33,'2026'!$O:$O,O$4) -> 879.26148 | P33: =SUM(D33:O33) -> 11370.427 | Q33: 10997.899 | R33: =P33-Q33 -> 372.52829 | S33: =IF(ISERROR(R33/Q33),"",R33/Q33) -> 0.033872679 | U33: 4251.705 | V33: 4882.2126 | W33: 5596.489 | X33: 1670.5679 | Y33: =P33/V33-1 -> 1.3289496 | Z33: =P33-V33 -> 6488.2143 | AA33: UL | AB33: 12768.091
A34: SP1 | B34: 2904 | C34: PTS | D34: =SUMIFS('2026'!$M:$M,'2026'!$J:$J,$B34&$C34,'2026'!$O:$O,D$4) -> 85.787064 | E34: =SUMIFS('2026'!$M:$M,'2026'!$J:$J,$B34&$C34,'2026'!$O:$O,E$4) -> 0 | F34: =SUMIFS('2026'!$M:$M,'2026'!$J:$J,$B34&$C34,'2026'!$O:$O,F$4) -> 261.55825 | G34: =SUMIFS('2026'!$M:$M,'2026'!$J:$J,$B34&$C34,'2026'!$O:$O,G$4) -> 0 | H34: =SUMIFS('2026'!$M:$M,'2026'!$J:$J,$B34&$C34,'2026'!$O:$O,H$4) -> 251.74195 | I34: =SUMIFS('2026'!$M:$M,'2026'!$J:$J,$B34&$C34,'2026'!$O:$O,I$4) -> 165.32443 | J34: =SUMIFS('2026'!$M:$M,'2026'!$J:$J,$B34&$C34,'2026'!$O:$O,J$4) -> 183.69381 | K34: =SUMIFS('2026'!$M:$M,'2026'!$J:$J,$B34&$C34,'2026'!$O:$O,K$4) -> 202.06319 | ... O34: =SUMIFS('2026'!$M:$M,'2026'!$J:$J,$B34&$C34,'2026'!$O:$O,O$4) -> 85.14 | P34: =SUM(D34:O34) -> 1915.7022 | Q34: 1920.8488 | R34: =P34-Q34 -> -5.1465131 | S34: =IF(ISERROR(R34/Q34),"",R34/Q34) -> -0.0026792912 | U34: 1387.1198 | V34: 1332.1837 | W34: 1062.7629 | X34: 3799.6375 | Y34: =P34/V34-1 -> 0.43801659 | Z34: =P34-V34 -> 583.51855 | AA34: UL | AB34: 1802.6183
A35: BJ PTS | B35: 2904 | C35: BJ PTS | D35: =SUMIFS('2026'!$M:$M,'2026'!$J:$J,$B35&$C35,'2026'!$O:$O,D$4) -> 553.18106 | E35: =SUMIFS('2026'!$M:$M,'2026'!$J:$J,$B35&$C35,'2026'!$O:$O,E$4) -> 135.58853 | F35: =SUMIFS('2026'!$M:$M,'2026'!$J:$J,$B35&$C35,'2026'!$O:$O,F$4) -> 1222.6022 | G35: =SUMIFS('2026'!$M:$M,'2026'!$J:$J,$B35&$C35,'2026'!$O:$O,G$4) -> 889.91984 | H35: =SUMIFS('2026'!$M:$M,'2026'!$J:$J,$B35&$C35,'2026'!$O:$O,H$4) -> 517.75845 | I35: =SUMIFS('2026'!$M:$M,'2026'!$J:$J,$B35&$C35,'2026'!$O:$O,I$4) -> 799.51008 | J35: =SUMIFS('2026'!$M:$M,'2026'!$J:$J,$B35&$C35,'2026'!$O:$O,J$4) -> 719.06395 | K35: =SUMIFS('2026'!$M:$M,'2026'!$J:$J,$B35&$C35,'2026'!$O:$O,K$4) -> 0 | ... O35: =SUMIFS('2026'!$M:$M,'2026'!$J:$J,$B35&$C35,'2026'!$O:$O,O$4) -> 0 | P35: =SUM(D35:O35) -> 4851.6905 | Q35: 5319.4948 | R35: =P35-Q35 -> -467.80435 | S35: =IF(ISERROR(R35/Q35),"",R35/Q35) -> -0.087941498 | U35: 5633.6246 | V35: 5218.5582 | W35: 6863.2057 | X35: 559.18895 | Y35: =P35/V35-1 -> -0.0703006 | Z35: =P35-V35 -> -366.86777 | AA35: UL | AB35: 4220.1904
A36: SP1 | B36: 2904 | C36: Sundaes | D36: =SUMIFS('2026'!$M:$M,'2026'!$J:$J,$B36&$C36,'2026'!$O:$O,D$4) -> 114.83226 | E36: =SUMIFS('2026'!$M:$M,'2026'!$J:$J,$B36&$C36,'2026'!$O:$O,E$4) -> 279.21359 | F36: =SUMIFS('2026'!$M:$M,'2026'!$J:$J,$B36&$C36,'2026'!$O:$O,F$4) -> 157.04035 | G36: =SUMIFS('2026'!$M:$M,'2026'!$J:$J,$B36&$C36,'2026'!$O:$O,G$4) -> 378.76608 | H36: =SUMIFS('2026'!$M:$M,'2026'!$J:$J,$B36&$C36,'2026'!$O:$O,H$4) -> 511.33421 | I36: =SUMIFS('2026'!$M:$M,'2026'!$J:$J,$B36&$C36,'2026'!$O:$O,I$4) -> 324.57843 | J36: =SUMIFS('2026'!$M:$M,'2026'!$J:$J,$B36&$C36,'2026'!$O:$O,J$4) -> 360.6427 | K36: =SUMIFS('2026'!$M:$M,'2026'!$J:$J,$B36&$C36,'2026'!$O:$O,K$4) -> 396.70697 | ... O36: =SUMIFS('2026'!$M:$M,'2026'!$J:$J,$B36&$C36,'2026'!$O:$O,O$4) -> 307.44 | P36: =SUM(D36:O36) -> 3805.1836 | Q36: 3920.0991 | R36: =P36-Q36 -> -114.91551 | S36: =IF(ISERROR(R36/Q36),"",R36/Q36) -> -0.029314439 | U36: 3285.9529 | V36: 3349.8628 | W36: 2829.8144 | X36: 0 | Y36: =P36/V36-1 -> 0.13592221 | Z36: =P36-V36 -> 455.32074 | AA36: UL | AB36: 4593.666
A37: YS PTS | B37: 2904 | C37: YS PTS | D37: =SUMIFS('2026'!$M:$M,'2026'!$J:$J,$B37&$C37,'2026'!$O:$O,D$4) -> -1.139328 | E37: =SUMIFS('2026'!$M:$M,'2026'!$J:$J,$B37&$C37,'2026'!$O:$O,E$4) -> 401.26867 | F37: =SUMIFS('2026'!$M:$M,'2026'!$J:$J,$B37&$C37,'2026'!$O:$O,F$4) -> -0.04968 | G37: =SUMIFS('2026'!$M:$M,'2026'!$J:$J,$B37&$C37,'2026'!$O:$O,G$4) -> 0 | H37: =SUMIFS('2026'!$M:$M,'2026'!$J:$J,$B37&$C37,'2026'!$O:$O,H$4) -> 0 | I37: =SUMIFS('2026'!$M:$M,'2026'!$J:$J,$B37&$C37,'2026'!$O:$O,I$4) -> 134.136 | J37: =SUMIFS('2026'!$M:$M,'2026'!$J:$J,$B37&$C37,'2026'!$O:$O,J$4) -> 248.4 | K37: =SUMIFS('2026'!$M:$M,'2026'!$J:$J,$B37&$C37,'2026'!$O:$O,K$4) -> 712.08 | ... O37: =SUMIFS('2026'!$M:$M,'2026'!$J:$J,$B37&$C37,'2026'!$O:$O,O$4) -> 529.92 | P37: =SUM(D37:O37) -> 3962.1357 | Q37: 2429.2232 | R37: =P37-Q37 -> 1532.9124 | S37: =IF(ISERROR(R37/Q37),"",R37/Q37) -> 0.63102988 | U37: 255.38501 | V37: 248.4 | W37: 331.2 | X37: - | Y37: =P37/V37-1 -> 14.950627 | Z37: =P37-V37 -> 3713.7357 | AA37: UL | AB37: 5216.4
A38: SP1 | B38: 2904 | C38: Topped | D38: =SUMIFS('2026'!$M:$M,'2026'!$J:$J,$B38&$C38,'2026'!$O:$O,D$4) -> 439.074 | E38: =SUMIFS('2026'!$M:$M,'2026'!$J:$J,$B38&$C38,'2026'!$O:$O,E$4) -> 586.2024 | F38: =SUMIFS('2026'!$M:$M,'2026'!$J:$J,$B38&$C38,'2026'!$O:$O,F$4) -> 763.146 | G38: =SUMIFS('2026'!$M:$M,'2026'!$J:$J,$B38&$C38,'2026'!$O:$O,G$4) -> 695.6928 | H38: =SUMIFS('2026'!$M:$M,'2026'!$J:$J,$B38&$C38,'2026'!$O:$O,H$4) -> 433.3824 | I38: =SUMIFS('2026'!$M:$M,'2026'!$J:$J,$B38&$C38,'2026'!$O:$O,I$4) -> 521.85956 | J38: =SUMIFS('2026'!$M:$M,'2026'!$J:$J,$B38&$C38,'2026'!$O:$O,J$4) -> 579.84395 | K38: =SUMIFS('2026'!$M:$M,'2026'!$J:$J,$B38&$C38,'2026'!$O:$O,K$4) -> 637.82835 | ... O38: =SUMIFS('2026'!$M:$M,'2026'!$J:$J,$B38&$C38,'2026'!$O:$O,O$4) -> 696.6 | P38: =SUM(D38:O38) -> 6944.7408 | Q38: 7358.2179 | R38: =P38-Q38 -> -413.47713 | S38: =IF(ISERROR(R38/Q38),"",R38/Q38) -> -0.056192563 | U38: 7855.812 | V38: 8411.904 | W38: 8926.794 | X38: 8435.9865 | Y38: =P38/V38-1 -> -0.17441512 | Z38: =P38-V38 -> -1467.1632 | AA38: UL | AB38: 8108.82
A39: TALENTI | B39: 2904 | C39: TALENTI | D39: =SUMIFS('2026'!$M:$M,'2026'!$J:$J,$B39&$C39,'2026'!$O:$O,D$4) -> 2929.5301 | E39: =SUMIFS('2026'!$M:$M,'2026'!$J:$J,$B39&$C39,'2026'!$O:$O,E$4) -> 3495.6159 | F39: =SUMIFS('2026'!$M:$M,'2026'!$J:$J,$B39&$C39,'2026'!$O:$O,F$4) -> 3895.6502 | G39: =SUMIFS('2026'!$M:$M,'2026'!$J:$J,$B39&$C39,'2026'!$O:$O,G$4) -> 4635.4176 | H39: =SUMIFS('2026'!$M:$M,'2026'!$J:$J,$B39&$C39,'2026'!$O:$O,H$4) -> 3426.1033 | I39: =SUMIFS('2026'!$M:$M,'2026'!$J:$J,$B39&$C39,'2026'!$O:$O,I$4) -> 3717.1425 | J39: =SUMIFS('2026'!$M:$M,'2026'!$J:$J,$B39&$C39,'2026'!$O:$O,J$4) -> 3717.1425 | K39: =SUMIFS('2026'!$M:$M,'2026'!$J:$J,$B39&$C39,'2026'!$O:$O,K$4) -> 4115.4078 | ... O39: =SUMIFS('2026'!$M:$M,'2026'!$J:$J,$B39&$C39,'2026'!$O:$O,O$4) -> 2504.5408 | P39: =SUM(D39:O39) -> 41109.492 | Q39: 40900.472 | R39: =P39-Q39 -> 209.01974 | S39: =IF(ISERROR(R39/Q39),"",R39/Q39) -> 0.0051104482 | U39: 39046.118 | V39: 39342.717 | W39: 41144.272 | X39: 42779.712 | Y39: =P39/V39-1 -> 0.044907274 | Z39: =P39-V39 -> 1766.7742 | AA39: UL | AB39: 41819.292
A40: PG | B40: 2904 | C40: PG | D40: =SUMIFS('2026'!$M:$M,'2026'!$J:$J,$B40&$C40,'2026'!$O:$O,D$4) -> 435.03144 | E40: =SUMIFS('2026'!$M:$M,'2026'!$J:$J,$B40&$C40,'2026'!$O:$O,E$4) -> 621.96115 | F40: =SUMIFS('2026'!$M:$M,'2026'!$J:$J,$B40&$C40,'2026'!$O:$O,F$4) -> 584.43192 | G40: =SUMIFS('2026'!$M:$M,'2026'!$J:$J,$B40&$C40,'2026'!$O:$O,G$4) -> 722.17958 | H40: =SUMIFS('2026'!$M:$M,'2026'!$J:$J,$B40&$C40,'2026'!$O:$O,H$4) -> 710.04211 | I40: =SUMIFS('2026'!$M:$M,'2026'!$J:$J,$B40&$C40,'2026'!$O:$O,I$4) -> 910.8372 | J40: =SUMIFS('2026'!$M:$M,'2026'!$J:$J,$B40&$C40,'2026'!$O:$O,J$4) -> 983.4039 | K40: =SUMIFS('2026'!$M:$M,'2026'!$J:$J,$B40&$C40,'2026'!$O:$O,K$4) -> 1005.9246 | ... O40: =SUMIFS('2026'!$M:$M,'2026'!$J:$J,$B40&$C40,'2026'!$O:$O,O$4) -> 0 | P40: =SUM(D40:O40) -> 8253.4072 | Q40: 8778.0821 | R40: =P40-Q40 -> -524.67489 | S40: =IF(ISERROR(R40/Q40),"",R40/Q40) -> -0.059771016 | U40: 9491.3661 | V40: 10854.005 | W40: 10753.95 | X40: 1152.4962 | Y40: =P40/V40-1 -> -0.23959802 | Z40: =P40-V40 -> -2600.5982 | AA40: UL | AB40: 11561.875
C41: Total Sikeston North | D41: =SUM(D26:D40) -> 15351.31 | E41: =SUM(E26:E40) -> 18340.165 | F41: =SUM(F26:F40) -> 21559.084 | G41: =SUM(G26:G40) -> 20900.209 | H41: =SUM(H26:H40) -> 17947.867 | I41: =SUM(I26:I40) -> 18050.123 | J41: =SUM(J26:J40) -> 18771.706 | K41: =SUM(K26:K40) -> 19707.735 | ... P41: =SUM(P26:P40) -> 203978.38 | Q41: 205006.34 | R41: =P41-Q41 -> -1027.956 | S41: =P41/Q41-1 -> -0.0050142644 | U41: 204666.46 | V41: 210852.95 | W41: 212920.34 | X41: 205930.96 | Y41: =P41/V41-1 -> -0.032603637 | Z41: =P41-V41 -> -6874.573 | AB41: 221182.96
C43: COVINGTON | R43: Vs PV | T43: Commentary
C44: Row Labels | D44: Jan | E44: Feb | F44: Mar | G44: Apr | H44: May | I44: Jun | J44: Jul | K44: Aug | L44: Sep | M44: Oct | N44: Nov | O44: Dec | P44: =P$4 -> 2026 MRF3 | Q44: 2026 MRF2 | R44: =R$4 -> Difference | S44: =S$4 -> % change | U44: 2025 Final | V44: 2025 MRF8 | W44: 2025 MRF7 | X44: 2024 MRF12 | AB44: 2026 MRF7
A45: 48oz | B45: 1352 | C45: 48oz | D45: =SUMIFS('2026'!$M:$M,'2026'!$J:$J,$B45&$C45,'2026'!$O:$O,D$4) -> 8083.4907 | E45: =SUMIFS('2026'!$M:$M,'2026'!$J:$J,$B45&$C45,'2026'!$O:$O,E$4) -> 9840.8244 | F45: =SUMIFS('2026'!$M:$M,'2026'!$J:$J,$B45&$C45,'2026'!$O:$O,F$4) -> 13439.113 | G45: =SUMIFS('2026'!$M:$M,'2026'!$J:$J,$B45&$C45,'2026'!$O:$O,G$4) -> 10126.516 | H45: =SUMIFS('2026'!$M:$M,'2026'!$J:$J,$B45&$C45,'2026'!$O:$O,H$4) -> 8326.9113 | I45: =SUMIFS('2026'!$M:$M,'2026'!$J:$J,$B45&$C45,'2026'!$O:$O,I$4) -> 8722.7698 | J45: =SUMIFS('2026'!$M:$M,'2026'!$J:$J,$B45&$C45,'2026'!$O:$O,J$4) -> 9045.8353 | K45: =SUMIFS('2026'!$M:$M,'2026'!$J:$J,$B45&$C45,'2026'!$O:$O,K$4) -> 10558.757 | ... O45: =SUMIFS('2026'!$M:$M,'2026'!$J:$J,$B45&$C45,'2026'!$O:$O,O$4) -> 4849.5728 | P45: =SUM(D45:O45) -> 101625.06 | Q45: 101374.21 | R45: =P45-Q45 -> 250.84671 | S45: =IF(ISERROR(R45/Q45),"",R45/Q45) -> 0.0024744627 | T45: No Major Change | U45: 106024.09 | V45: 106321.84 | W45: 103087.08 | X45: 107043.58 | Y45: =P45/V45-1 -> -0.044175134 | Z45: =P45-V45 -> -4696.7815 | AA45: UL | AB45: 104182.3
A46: Other | B46: 1352 | C46: 56oz | D46: =SUMIFS('2026'!$M:$M,'2026'!$J:$J,$B46&$C46,'2026'!$O:$O,D$4) -> 0 | E46: =SUMIFS('2026'!$M:$M,'2026'!$J:$J,$B46&$C46,'2026'!$O:$O,E$4) -> 0 | F46: =SUMIFS('2026'!$M:$M,'2026'!$J:$J,$B46&$C46,'2026'!$O:$O,F$4) -> 0 | G46: =SUMIFS('2026'!$M:$M,'2026'!$J:$J,$B46&$C46,'2026'!$O:$O,G$4) -> 0 | H46: =SUMIFS('2026'!$M:$M,'2026'!$J:$J,$B46&$C46,'2026'!$O:$O,H$4) -> 0 | I46: =SUMIFS('2026'!$M:$M,'2026'!$J:$J,$B46&$C46,'2026'!$O:$O,I$4) -> 0 | J46: =SUMIFS('2026'!$M:$M,'2026'!$J:$J,$B46&$C46,'2026'!$O:$O,J$4) -> 0 | K46: =SUMIFS('2026'!$M:$M,'2026'!$J:$J,$B46&$C46,'2026'!$O:$O,K$4) -> 0 | ... O46: =SUMIFS('2026'!$M:$M,'2026'!$J:$J,$B46&$C46,'2026'!$O:$O,O$4) -> 0 | P46: =SUM(D46:O46) -> 0 | Q46: 0 | S46: =IF(ISERROR(R46/Q46),"",R46/Q46) | U46: 0 | V46: 0 | W46: 0 | X46: 0 | Y46: =P46/V46-1 -> #DIV/0! | Z46: =P46-V46 -> 0 | AA46: UL | AB46: 0
A47: Other | B47: 1352 | C47: 64oz | D47: =SUMIFS('2026'!$M:$M,'2026'!$J:$J,$B47&$C47,'2026'!$O:$O,D$4) -> 0 | E47: =SUMIFS('2026'!$M:$M,'2026'!$J:$J,$B47&$C47,'2026'!$O:$O,E$4) -> 0 | F47: =SUMIFS('2026'!$M:$M,'2026'!$J:$J,$B47&$C47,'2026'!$O:$O,F$4) -> 0 | G47: =SUMIFS('2026'!$M:$M,'2026'!$J:$J,$B47&$C47,'2026'!$O:$O,G$4) -> 0 | H47: =SUMIFS('2026'!$M:$M,'2026'!$J:$J,$B47&$C47,'2026'!$O:$O,H$4) -> 0 | I47: =SUMIFS('2026'!$M:$M,'2026'!$J:$J,$B47&$C47,'2026'!$O:$O,I$4) -> 0 | J47: =SUMIFS('2026'!$M:$M,'2026'!$J:$J,$B47&$C47,'2026'!$O:$O,J$4) -> 0 | K47: =SUMIFS('2026'!$M:$M,'2026'!$J:$J,$B47&$C47,'2026'!$O:$O,K$4) -> 0 | ... O47: =SUMIFS('2026'!$M:$M,'2026'!$J:$J,$B47&$C47,'2026'!$O:$O,O$4) -> 0 | P47: =SUM(D47:O47) -> 0 | Q47: 0 | S47: =IF(ISERROR(R47/Q47),"",R47/Q47) | U47: 0 | V47: 0 | W47: 0 | X47: 0 | Y47: =P47/V47-1 -> #DIV/0! | Z47: =P47-V47 -> 0 | AA47: UL | AB47: 0
A48: EDF | B48: 1352 | C48: EDF | D48: =SUMIFS('2026'!$M:$M,'2026'!$J:$J,$B48&$C48,'2026'!$O:$O,D$4) -> 3466.1539 | E48: =SUMIFS('2026'!$M:$M,'2026'!$J:$J,$B48&$C48,'2026'!$O:$O,E$4) -> 4208.1738 | F48: =SUMIFS('2026'!$M:$M,'2026'!$J:$J,$B48&$C48,'2026'!$O:$O,F$4) -> 5113.4375 | G48: =SUMIFS('2026'!$M:$M,'2026'!$J:$J,$B48&$C48,'2026'!$O:$O,G$4) -> 4420.8014 | H48: =SUMIFS('2026'!$M:$M,'2026'!$J:$J,$B48&$C48,'2026'!$O:$O,H$4) -> 3815.095 | I48: =SUMIFS('2026'!$M:$M,'2026'!$J:$J,$B48&$C48,'2026'!$O:$O,I$4) -> 3788.0741 | J48: =SUMIFS('2026'!$M:$M,'2026'!$J:$J,$B48&$C48,'2026'!$O:$O,J$4) -> 3965.4695 | K48: =SUMIFS('2026'!$M:$M,'2026'!$J:$J,$B48&$C48,'2026'!$O:$O,K$4) -> 3613.1349 | ... O48: =SUMIFS('2026'!$M:$M,'2026'!$J:$J,$B48&$C48,'2026'!$O:$O,O$4) -> 430.92 | P48: =SUM(D48:O48) -> 40403.513 | Q48: 41403.048 | R48: =P48-Q48 -> -999.5351 | S48: =IF(ISERROR(R48/Q48),"",R48/Q48) -> -0.024141582 | T48: Demand Related | U48: 38052.41 | V48: 36720.387 | W48: 38520.095 | X48: 35425.172 | Y48: =P48/V48-1 -> 0.10030193 | Z48: =P48-V48 -> 3683.1257 | AA48: UL | AB48: 41657.898 | AI48: 340
A49: EFW | B49: 1352 | C49: EFW | D49: =SUMIFS('2026'!$M:$M,'2026'!$J:$J,$B49&$C49,'2026'!$O:$O,D$4) -> 0 | E49: =SUMIFS('2026'!$M:$M,'2026'!$J:$J,$B49&$C49,'2026'!$O:$O,E$4) -> 0 | F49: =SUMIFS('2026'!$M:$M,'2026'!$J:$J,$B49&$C49,'2026'!$O:$O,F$4) -> 0 | G49: =SUMIFS('2026'!$M:$M,'2026'!$J:$J,$B49&$C49,'2026'!$O:$O,G$4) -> 0 | H49: =SUMIFS('2026'!$M:$M,'2026'!$J:$J,$B49&$C49,'2026'!$O:$O,H$4) -> 0 | I49: =SUMIFS('2026'!$M:$M,'2026'!$J:$J,$B49&$C49,'2026'!$O:$O,I$4) -> 0 | J49: =SUMIFS('2026'!$M:$M,'2026'!$J:$J,$B49&$C49,'2026'!$O:$O,J$4) -> 0 | K49: =SUMIFS('2026'!$M:$M,'2026'!$J:$J,$B49&$C49,'2026'!$O:$O,K$4) -> 0 | ... O49: =SUMIFS('2026'!$M:$M,'2026'!$J:$J,$B49&$C49,'2026'!$O:$O,O$4) -> 0 | P49: =SUM(D49:O49) -> 0 | Q49: 0 | R49: =P49-Q49 -> 0 | S49: =IF(ISERROR(R49/Q49),"",R49/Q49) | U49: 1316.0332 | V49: 1368.0072 | W49: 1335.9596 | X49: 3481.05 | Y49: =P49/V49-1 -> -1 | Z49: =P49-V49 -> -1368.0072 | AA49: UL | AB49: 0 | AI49: 188
A50: MBG | B50: 1352 | C50: MBG | D50: =SUMIFS('2026'!$M:$M,'2026'!$J:$J,$B50&$C50,'2026'!$O:$O,D$4) -> 526.95611 | E50: =SUMIFS('2026'!$M:$M,'2026'!$J:$J,$B50&$C50,'2026'!$O:$O,E$4) -> 637.71868 | F50: =SUMIFS('2026'!$M:$M,'2026'!$J:$J,$B50&$C50,'2026'!$O:$O,F$4) -> 855.18062 | G50: =SUMIFS('2026'!$M:$M,'2026'!$J:$J,$B50&$C50,'2026'!$O:$O,G$4) -> 1229.4328 | H50: =SUMIFS('2026'!$M:$M,'2026'!$J:$J,$B50&$C50,'2026'!$O:$O,H$4) -> 1275.8139 | I50: =SUMIFS('2026'!$M:$M,'2026'!$J:$J,$B50&$C50,'2026'!$O:$O,I$4) -> 944.1024 | J50: =SUMIFS('2026'!$M:$M,'2026'!$J:$J,$B50&$C50,'2026'!$O:$O,J$4) -> 792.78792 | K50: =SUMIFS('2026'!$M:$M,'2026'!$J:$J,$B50&$C50,'2026'!$O:$O,K$4) -> 758.31888 | ... O50: =SUMIFS('2026'!$M:$M,'2026'!$J:$J,$B50&$C50,'2026'!$O:$O,O$4) -> 0 | P50: =SUM(D50:O50) -> 8163.9747 | Q50: 7985.6939 | R50: =P50-Q50 -> 178.28082 | S50: =IF(ISERROR(R50/Q50),"",R50/Q50) -> 0.022325025 | U50: 9749.947 | V50: 10276.947 | W50: 9716.3971 | X50: 8750.6407 | Y50: =P50/V50-1 -> -0.20560312 | Z50: =P50-V50 -> -2112.9724 | AA50: UL | AB50: 7164.952
A51: PG | B51: 1352 | C51: PG | D51: =SUMIFS('2026'!$M:$M,'2026'!$J:$J,$B51&$C51,'2026'!$O:$O,D$4) -> 790.79787 | E51: =SUMIFS('2026'!$M:$M,'2026'!$J:$J,$B51&$C51,'2026'!$O:$O,E$4) -> 1273.734 | F51: =SUMIFS('2026'!$M:$M,'2026'!$J:$J,$B51&$C51,'2026'!$O:$O,F$4) -> 1288.1502 | G51: =SUMIFS('2026'!$M:$M,'2026'!$J:$J,$B51&$C51,'2026'!$O:$O,G$4) -> 1159.0108 | H51: =SUMIFS('2026'!$M:$M,'2026'!$J:$J,$B51&$C51,'2026'!$O:$O,H$4) -> 1148.2595 | I51: =SUMIFS('2026'!$M:$M,'2026'!$J:$J,$B51&$C51,'2026'!$O:$O,I$4) -> 1251.15 | J51: =SUMIFS('2026'!$M:$M,'2026'!$J:$J,$B51&$C51,'2026'!$O:$O,J$4) -> 1732.0276 | K51: =SUMIFS('2026'!$M:$M,'2026'!$J:$J,$B51&$C51,'2026'!$O:$O,K$4) -> 1656.7221 | ... O51: =SUMIFS('2026'!$M:$M,'2026'!$J:$J,$B51&$C51,'2026'!$O:$O,O$4) -> 0 | P51: =SUM(D51:O51) -> 14506.617 | Q51: 15340.531 | R51: =P51-Q51 -> -833.91399 | S51: =IF(ISERROR(R51/Q51),"",R51/Q51) -> -0.054360176 | U51: 14553.699 | V51: 14906.472 | W51: 16355.432 | X51: 10881.7 | Y51: =P51/V51-1 -> -0.026824243 | Z51: =P51-V51 -> -399.85483 | AA51: UL | AB51: 17272.375
A52: TALENTI | B52: 1352 | C52: Talenti | D52: =SUMIFS('2026'!$M:$M,'2026'!$J:$J,$B52&$C52,'2026'!$O:$O,D$4) -> 0 | E52: =SUMIFS('2026'!$M:$M,'2026'!$J:$J,$B52&$C52,'2026'!$O:$O,E$4) -> 0 | F52: =SUMIFS('2026'!$M:$M,'2026'!$J:$J,$B52&$C52,'2026'!$O:$O,F$4) -> 0 | G52: =SUMIFS('2026'!$M:$M,'2026'!$J:$J,$B52&$C52,'2026'!$O:$O,G$4) -> 0 | H52: =SUMIFS('2026'!$M:$M,'2026'!$J:$J,$B52&$C52,'2026'!$O:$O,H$4) -> 0 | I52: =SUMIFS('2026'!$M:$M,'2026'!$J:$J,$B52&$C52,'2026'!$O:$O,I$4) -> 0 | J52: =SUMIFS('2026'!$M:$M,'2026'!$J:$J,$B52&$C52,'2026'!$O:$O,J$4) -> 0 | K52: =SUMIFS('2026'!$M:$M,'2026'!$J:$J,$B52&$C52,'2026'!$O:$O,K$4) -> 0 | ... O52: =SUMIFS('2026'!$M:$M,'2026'!$J:$J,$B52&$C52,'2026'!$O:$O,O$4) -> 0 | P52: =SUM(D52:O52) -> 0 | Q52: 0 | S52: =IF(ISERROR(R52/Q52),"",R52/Q52) | U52: 0 | V52: 0 | W52: 0 | X52: 0 | Y52: =P52/V52-1 -> #DIV/0! | Z52: =P52-V52 -> 0 | AA52: UL | AB52: 0
C53: Total Covington | D53: =SUM(D45:D52) -> 12867.399 | E53: =SUM(E45:E52) -> 15960.451 | F53: =SUM(F45:F52) -> 20695.881 | G53: =SUM(G45:G52) -> 16935.761 | H53: =SUM(H45:H52) -> 14566.08 | I53: =SUM(I45:I52) -> 14706.096 | J53: =SUM(J45:J52) -> 15536.12 | K53: =SUM(K45:K52) -> 16586.933 | ... P53: =SUM(P45:P52) -> 164699.16 | Q53: 166103.48 | R53: =SUM(R45:R52) -> -1404.3216 | S53: =IF(ISERROR(R53/Q53),"",R53/Q53) -> -0.0084544979 | U53: 169696.18 | V53: 169593.65 | W53: 169014.97 | X53: 165582.14 | Y53: =P53/V53-1 -> -0.028860102 | Z53: =P53-V53 -> -4894.4902 | AB53: 170277.52
C55: Schwann's | P55: =P3 -> 0 | Q55: 0 | R55: Vs PV | T55: Commentary | U55: 0 | V55: 0 | W55: 0 | AB55: 0
C56: Row Labels | D56: Jan | E56: Feb | F56: Mar | G56: Apr | H56: May | I56: Jun | J56: Jul | K56: Aug | L56: Sep | M56: Oct | N56: Nov | O56: Dec | P56: L Projection | Q56: L Projection | R56: Difference | S56: % change | U56: L Projection | V56: L Projection | W56: L Projection | X56: 2024 MRF12 | AB56: L Projection
A57: B&J Cups | B57: 1712 | C57: B&J Cups | D57: =SUMIFS('2026'!$M:$M,'2026'!$J:$J,$B57&$C57,'2026'!$O:$O,D$4) -> 168.33962 | E57: =SUMIFS('2026'!$M:$M,'2026'!$J:$J,$B57&$C57,'2026'!$O:$O,E$4) -> 90.16092 | F57: =SUMIFS('2026'!$M:$M,'2026'!$J:$J,$B57&$C57,'2026'!$O:$O,F$4) -> 275.94071 | G57: =SUMIFS('2026'!$M:$M,'2026'!$J:$J,$B57&$C57,'2026'!$O:$O,G$4) -> 160.02282 | H57: =SUMIFS('2026'!$M:$M,'2026'!$J:$J,$B57&$C57,'2026'!$O:$O,H$4) -> 0 | I57: =SUMIFS('2026'!$M:$M,'2026'!$J:$J,$B57&$C57,'2026'!$O:$O,I$4) -> 37.897114 | J57: =SUMIFS('2026'!$M:$M,'2026'!$J:$J,$B57&$C57,'2026'!$O:$O,J$4) -> 70.515878 | K57: =SUMIFS('2026'!$M:$M,'2026'!$J:$J,$B57&$C57,'2026'!$O:$O,K$4) -> 187.63799 | ... O57: =SUMIFS('2026'!$M:$M,'2026'!$J:$J,$B57&$C57,'2026'!$O:$O,O$4) -> 71.699904 | P57: =SUM(D57:O57) -> 1400.3165 | Q57: 1338.3819 | R57: =P57-Q57 -> 61.934569 | S57: =IF(ISERROR(R57/Q57),"",R57/Q57) -> 0.046275707 | T57: Inventory Reduction plan | U57: 2472.386 | V57: 3013.4835 | W57: 3221.9393 | X57: 944.80661 | Y57: =P57/V57-1 -> -0.53531636 | Z57: =P57-V57 -> -1613.167 | AA57: CM | AB57: 2537.1112
A58: ESS | B58: 1712 | C58: ESS | D58: =SUMIFS('2026'!$M:$M,'2026'!$J:$J,$B58&$C58,'2026'!$O:$O,D$4) -> 194.03912 | E58: =SUMIFS('2026'!$M:$M,'2026'!$J:$J,$B58&$C58,'2026'!$O:$O,E$4) -> 151.84492 | F58: =SUMIFS('2026'!$M:$M,'2026'!$J:$J,$B58&$C58,'2026'!$O:$O,F$4) -> 361.54439 | G58: =SUMIFS('2026'!$M:$M,'2026'!$J:$J,$B58&$C58,'2026'!$O:$O,G$4) -> 490.57298 | H58: =SUMIFS('2026'!$M:$M,'2026'!$J:$J,$B58&$C58,'2026'!$O:$O,H$4) -> 987.12346 | I58: =SUMIFS('2026'!$M:$M,'2026'!$J:$J,$B58&$C58,'2026'!$O:$O,I$4) -> 494.51535 | J58: =SUMIFS('2026'!$M:$M,'2026'!$J:$J,$B58&$C58,'2026'!$O:$O,J$4) -> 173.2608 | K58: =SUMIFS('2026'!$M:$M,'2026'!$J:$J,$B58&$C58,'2026'!$O:$O,K$4) -> 161.60809 | ... O58: =SUMIFS('2026'!$M:$M,'2026'!$J:$J,$B58&$C58,'2026'!$O:$O,O$4) -> 173.2608 | P58: =SUM(D58:O58) -> 4019.1158 | Q58: 4321.0178 | R58: =P58-Q58 -> -301.90207 | S58: =IF(ISERROR(R58/Q58),"",R58/Q58) -> -0.069868276 | U58: 4403.6899 | V58: 4475.1087 | W58: 4821.0957 | X58: 845.43808 | Y58: =P58/V58-1 -> -0.10189539 | Z58: =P58-V58 -> -455.99294 | AA58: CM | AB58: 9614.8143
A59: ESS | B59: 1712 | C59: KL Sandwich | D59: =SUMIFS('2026'!$M:$M,'2026'!$J:$J,$B59&$C59,'2026'!$O:$O,D$4) -> 0 | E59: =SUMIFS('2026'!$M:$M,'2026'!$J:$J,$B59&$C59,'2026'!$O:$O,E$4) -> 0 | F59: =SUMIFS('2026'!$M:$M,'2026'!$J:$J,$B59&$C59,'2026'!$O:$O,F$4) -> 0 | G59: =SUMIFS('2026'!$M:$M,'2026'!$J:$J,$B59&$C59,'2026'!$O:$O,G$4) -> 0 | H59: =SUMIFS('2026'!$M:$M,'2026'!$J:$J,$B59&$C59,'2026'!$O:$O,H$4) -> 0 | I59: =SUMIFS('2026'!$M:$M,'2026'!$J:$J,$B59&$C59,'2026'!$O:$O,I$4) -> 0 | J59: =SUMIFS('2026'!$M:$M,'2026'!$J:$J,$B59&$C59,'2026'!$O:$O,J$4) -> 0 | K59: =SUMIFS('2026'!$M:$M,'2026'!$J:$J,$B59&$C59,'2026'!$O:$O,K$4) -> 0 | ... O59: =SUMIFS('2026'!$M:$M,'2026'!$J:$J,$B59&$C59,'2026'!$O:$O,O$4) -> 0 | P59: =SUM(D59:O59) -> 0 | Q59: 0 | R59: =P59-Q59 -> 0 | S59: =IF(ISERROR(R59/Q59),"",R59/Q59) | U59: 0 | V59: 0 | W59: 0 | X59: 0 | Y59: =P59/V59-1 -> #DIV/0! | Z59: =P59-V59 -> 0 | AA59: CM | AB59: 0
C60: Total Schwann's | D60: =SUM(D57:D59) -> 362.37875 | E60: =SUM(E57:E59) -> 242.00584 | F60: =SUM(F57:F59) -> 637.4851 | G60: =SUM(G57:G59) -> 650.5958 | H60: =SUM(H57:H59) -> 987.12346 | I60: =SUM(I57:I59) -> 532.41247 | J60: =SUM(J57:J59) -> 243.77668 | K60: =SUM(K57:K59) -> 349.24608 | ... P60: =SUM(P57:P59) -> 5419.4323 | Q60: 5659.3998 | R60: =SUM(R57:R59) -> -239.9675 | S60: =IF(ISERROR(R60/Q60),"",R60/Q60) -> -0.042401581 | U60: 6876.0759 | V60: 7488.5922 | W60: 8043.035 | X60: 1790.2447 | Y60: =P60/V60-1 -> -0.27630827 | Z60: =P60-V60 -> -2069.16 | AB60: 12151.926
R61: Vs PV | T61: Commentary
C62: Row Labels | D62: Jan | E62: Feb | F62: Mar | G62: Apr | H62: May | I62: Jun | J62: Jul | K62: Aug | L62: Sep | M62: Oct | N62: Nov | O62: Dec | P62: =P$4 -> 2026 MRF3 | Q62: 2026 MRF2 | R62: =R$4 -> Difference | S62: =S$4 -> % change | U62: 2025 Final | V62: 2025 MRF8 | W62: 2025 MRF7 | X62: 2024 MRF12 | Z62: =P62-V62 -> #VALUE! | AB62: 2026 MRF7
A63: Other | B63: 6765 | C63: BR Minicups | D63: =SUMIFS('2026'!$M:$M,'2026'!$J:$J,$B63&$C63,'2026'!$O:$O,D$4) -> 76.881612 | E63: =SUMIFS('2026'!$M:$M,'2026'!$J:$J,$B63&$C63,'2026'!$O:$O,E$4) -> 0 | F63: =SUMIFS('2026'!$M:$M,'2026'!$J:$J,$B63&$C63,'2026'!$O:$O,F$4) -> 45.813905 | G63: =SUMIFS('2026'!$M:$M,'2026'!$J:$J,$B63&$C63,'2026'!$O:$O,G$4) -> 0 | H63: =SUMIFS('2026'!$M:$M,'2026'!$J:$J,$B63&$C63,'2026'!$O:$O,H$4) -> 0 | I63: =SUMIFS('2026'!$M:$M,'2026'!$J:$J,$B63&$C63,'2026'!$O:$O,I$4) -> 44.142797 | J63: =SUMIFS('2026'!$M:$M,'2026'!$J:$J,$B63&$C63,'2026'!$O:$O,J$4) -> 44.142797 | K63: =SUMIFS('2026'!$M:$M,'2026'!$J:$J,$B63&$C63,'2026'!$O:$O,K$4) -> 44.142797 | ... O63: =SUMIFS('2026'!$M:$M,'2026'!$J:$J,$B63&$C63,'2026'!$O:$O,O$4) -> 88.285594 | P63: =SUM(D63:O63) -> 475.83789 | Q63: 1248.413 | R63: =P63-Q63 -> -772.57516 | S63: =IF(ISERROR(R63/Q63),"",R63/Q63) -> -0.61884579 | U63: 413.95905 | V63: 901.7568 | W63: 0 | X63: 3197.7179 | Y63: =P63/V63-1 -> -0.47232126 | Z63: =P63-V63 -> -425.91891 | AA63: CM | AB63: 0
A64: Other | B64: 6764 | C64: Other | D64: =SUMIFS('2026'!$M:$M,'2026'!$J:$J,$B64&$C64,'2026'!$O:$O,D$4) -> 335.45606 | E64: =SUMIFS('2026'!$M:$M,'2026'!$J:$J,$B64&$C64,'2026'!$O:$O,E$4) -> 324.44525 | F64: =SUMIFS('2026'!$M:$M,'2026'!$J:$J,$B64&$C64,'2026'!$O:$O,F$4) -> 209.82146 | G64: =SUMIFS('2026'!$M:$M,'2026'!$J:$J,$B64&$C64,'2026'!$O:$O,G$4) -> 244.6848 | H64: =SUMIFS('2026'!$M:$M,'2026'!$J:$J,$B64&$C64,'2026'!$O:$O,H$4) -> 244.6848 | I64: =SUMIFS('2026'!$M:$M,'2026'!$J:$J,$B64&$C64,'2026'!$O:$O,I$4) -> 326.2464 | J64: =SUMIFS('2026'!$M:$M,'2026'!$J:$J,$B64&$C64,'2026'!$O:$O,J$4) -> 163.1232 | K64: =SUMIFS('2026'!$M:$M,'2026'!$J:$J,$B64&$C64,'2026'!$O:$O,K$4) -> 163.1232 | ... O64: =SUMIFS('2026'!$M:$M,'2026'!$J:$J,$B64&$C64,'2026'!$O:$O,O$4) -> 0 | P64: =SUM(D64:O64) -> 2256.27 | Q64: 3206.2482 | U64: 705.9959 | V64: 1191.965 | Y64: =P64/V64-1 -> 0.89289946 | Z64: =P64-V64 -> 1064.3049 | AB64: 0
A65: Other | B65: 6765 | C65: Other | D65: =SUMIFS('2026'!$M:$M,'2026'!$J:$J,$B65&$C65,'2026'!$O:$O,D$4) -> 0 | E65: =SUMIFS('2026'!$M:$M,'2026'!$J:$J,$B65&$C65,'2026'!$O:$O,E$4) -> 54.383 | F65: =SUMIFS('2026'!$M:$M,'2026'!$J:$J,$B65&$C65,'2026'!$O:$O,F$4) -> 143.91024 | G65: =SUMIFS('2026'!$M:$M,'2026'!$J:$J,$B65&$C65,'2026'!$O:$O,G$4) -> 103.68 | H65: =SUMIFS('2026'!$M:$M,'2026'!$J:$J,$B65&$C65,'2026'!$O:$O,H$4) -> 77.76 | I65: =SUMIFS('2026'!$M:$M,'2026'!$J:$J,$B65&$C65,'2026'!$O:$O,I$4) -> 77.76 | J65: =SUMIFS('2026'!$M:$M,'2026'!$J:$J,$B65&$C65,'2026'!$O:$O,J$4) -> 51.84 | K65: =SUMIFS('2026'!$M:$M,'2026'!$J:$J,$B65&$C65,'2026'!$O:$O,K$4) -> 31.104 | ... O65: =SUMIFS('2026'!$M:$M,'2026'!$J:$J,$B65&$C65,'2026'!$O:$O,O$4) -> 0 | P65: =SUM(D65:O65) -> 595.15724 | Q65: 707.62172 | R65: =P65-Q65 -> -112.46448 | S65: =IF(ISERROR(R65/Q65),"",R65/Q65) -> -0.15893305 | U65: 72.5904 | V65: 72.59892 | W65: 72.59892 | X65: 1726.6091 | Y65: =P65/V65-1 -> 7.1978801 | Z65: =P65-V65 -> 522.55832 | AA65: CM | AB65: 0
A66: ESS | B66: 6706 | C66: 48oz | D66: =SUMIFS('2026'!$M:$M,'2026'!$J:$J,$B66&$C66,'2026'!$O:$O,D$4) -> 0 | E66: =SUMIFS('2026'!$M:$M,'2026'!$J:$J,$B66&$C66,'2026'!$O:$O,E$4) -> 0 | F66: =SUMIFS('2026'!$M:$M,'2026'!$J:$J,$B66&$C66,'2026'!$O:$O,F$4) -> 0 | G66: =SUMIFS('2026'!$M:$M,'2026'!$J:$J,$B66&$C66,'2026'!$O:$O,G$4) -> 200.22 | H66: =SUMIFS('2026'!$M:$M,'2026'!$J:$J,$B66&$C66,'2026'!$O:$O,H$4) -> 681.6 | I66: =SUMIFS('2026'!$M:$M,'2026'!$J:$J,$B66&$C66,'2026'!$O:$O,I$4) -> 498.42 | J66: =SUMIFS('2026'!$M:$M,'2026'!$J:$J,$B66&$C66,'2026'!$O:$O,J$4) -> 468.6 | K66: =SUMIFS('2026'!$M:$M,'2026'!$J:$J,$B66&$C66,'2026'!$O:$O,K$4) -> 0 | ... O66: =SUMIFS('2026'!$M:$M,'2026'!$J:$J,$B66&$C66,'2026'!$O:$O,O$4) -> 0 | P66: =SUM(D66:O66) -> 1848.84 | Q66: 0 | R66: =P66-Q66 -> 1848.84 | S66: =IF(ISERROR(R66/Q66),"",R66/Q66) | U66: 1950.1548 | V66: 2155.0274 | W66: 2153.7827 | X66: 3618.7395 | Y66: =P66/V66-1 -> -0.14208051 | Z66: =P66-V66 -> -306.18739 | AA66: CM | AB66: 0
A67: Other | B67: 6706 | C67: FB Cones | D67: =SUMIFS('2026'!$M:$M,'2026'!$J:$J,$B67&$C67,'2026'!$O:$O,D$4) -> 0 | E67: =SUMIFS('2026'!$M:$M,'2026'!$J:$J,$B67&$C67,'2026'!$O:$O,E$4) -> 0 | F67: =SUMIFS('2026'!$M:$M,'2026'!$J:$J,$B67&$C67,'2026'!$O:$O,F$4) -> 0 | G67: =SUMIFS('2026'!$M:$M,'2026'!$J:$J,$B67&$C67,'2026'!$O:$O,G$4) -> 0 | H67: =SUMIFS('2026'!$M:$M,'2026'!$J:$J,$B67&$C67,'2026'!$O:$O,H$4) -> 0 | I67: =SUMIFS('2026'!$M:$M,'2026'!$J:$J,$B67&$C67,'2026'!$O:$O,I$4) -> 0 | J67: =SUMIFS('2026'!$M:$M,'2026'!$J:$J,$B67&$C67,'2026'!$O:$O,J$4) -> 0 | K67: =SUMIFS('2026'!$M:$M,'2026'!$J:$J,$B67&$C67,'2026'!$O:$O,K$4) -> 0 | ... O67: =SUMIFS('2026'!$M:$M,'2026'!$J:$J,$B67&$C67,'2026'!$O:$O,O$4) -> 0 | P67: =SUM(D67:O67) -> 0 | Q67: 0 | R67: =P67-Q67 -> 0 | S67: =IF(ISERROR(R67/Q67),"",R67/Q67) | U67: 1053.3256 | V67: 1291.324 | W67: 1643.8656 | X67: 2590.977 | Y67: =P67/V67-1 -> -1 | Z67: =P67-V67 -> -1291.324 | AA67: CM | AB67: 0
A68: Other | B68: 6706 | C68: BR Minicups | D68: =SUMIFS('2026'!$M:$M,'2026'!$J:$J,$B68&$C68,'2026'!$O:$O,D$4) -> 148.86166 | E68: =SUMIFS('2026'!$M:$M,'2026'!$J:$J,$B68&$C68,'2026'!$O:$O,E$4) -> 0 | F68: =SUMIFS('2026'!$M:$M,'2026'!$J:$J,$B68&$C68,'2026'!$O:$O,F$4) -> 0 | G68: =SUMIFS('2026'!$M:$M,'2026'!$J:$J,$B68&$C68,'2026'!$O:$O,G$4) -> 20.002205 | H68: =SUMIFS('2026'!$M:$M,'2026'!$J:$J,$B68&$C68,'2026'!$O:$O,H$4) -> 0 | I68: =SUMIFS('2026'!$M:$M,'2026'!$J:$J,$B68&$C68,'2026'!$O:$O,I$4) -> 0 | J68: =SUMIFS('2026'!$M:$M,'2026'!$J:$J,$B68&$C68,'2026'!$O:$O,J$4) -> 0 | K68: =SUMIFS('2026'!$M:$M,'2026'!$J:$J,$B68&$C68,'2026'!$O:$O,K$4) -> 0 | ... O68: =SUMIFS('2026'!$M:$M,'2026'!$J:$J,$B68&$C68,'2026'!$O:$O,O$4) -> 0 | P68: =SUM(D68:O68) -> 168.86387 | Q68: 171.12721 | R68: =P68-Q68 -> -2.2633402 | S68: =IF(ISERROR(R68/Q68),"",R68/Q68) -> -0.013226068 | U68: 824.26072 | V68: 66.978018 | W68: 66.978018 | X68: 190.06929 | Y68: =P68/V68-1 -> 1.5211834 | Z68: =P68-V68 -> 101.88585 | AA68: CM | AB68: 0
C69: Total Brothers 3PM | D69: =SUM(D63:D68) -> 561.19934 | E69: =SUM(E63:E68) -> 378.82825 | F69: =SUM(F63:F68) -> 399.54561 | G69: =SUM(G63:G68) -> 568.587 | H69: =SUM(H63:H68) -> 1004.0448 | I69: =SUM(I63:I68) -> 946.5692 | J69: =SUM(J63:J68) -> 727.706 | K69: =SUM(K63:K68) -> 238.37 | ... P69: =SUM(P63:P68) -> 5344.969 | Q69: 5333.4102 | R69: =P69-Q69 -> 11.558824 | S69: =IF(ISERROR(R69/Q69),"",R69/Q69) -> 0.0021672483 | U69: 5020.2865 | V69: 5679.6502 | W69: 3937.2252 | X69: 11324.113 | Y69: =P69/V69-1 -> -0.05892638 | Z69: =P69-V69 -> -334.68123 | AB69: 0
A71: Yasso Sticks | B71: 1715 | C71: Yasso Sticks | D71: =SUMIFS('2026'!$M:$M,'2026'!$J:$J,$B71&$C71,'2026'!$O:$O,D$4) -> 440.79072 | E71: =SUMIFS('2026'!$M:$M,'2026'!$J:$J,$B71&$C71,'2026'!$O:$O,E$4) -> 281.74207 | F71: =SUMIFS('2026'!$M:$M,'2026'!$J:$J,$B71&$C71,'2026'!$O:$O,F$4) -> 482.40274 | G71: =SUMIFS('2026'!$M:$M,'2026'!$J:$J,$B71&$C71,'2026'!$O:$O,G$4) -> 547.16756 | H71: =SUMIFS('2026'!$M:$M,'2026'!$J:$J,$B71&$C71,'2026'!$O:$O,H$4) -> 2761.033 | I71: =SUMIFS('2026'!$M:$M,'2026'!$J:$J,$B71&$C71,'2026'!$O:$O,I$4) -> 1150.128 | J71: =SUMIFS('2026'!$M:$M,'2026'!$J:$J,$B71&$C71,'2026'!$O:$O,J$4) -> 1023.9264 | K71: =SUMIFS('2026'!$M:$M,'2026'!$J:$J,$B71&$C71,'2026'!$O:$O,K$4) -> 1023.9264 | ... O71: =SUMIFS('2026'!$M:$M,'2026'!$J:$J,$B71&$C71,'2026'!$O:$O,O$4) -> 548.8128 | P71: =SUM(D71:O71) -> 10309.798 | Q71: 8769.4561 | R71: =P71-Q71 -> 1540.3424 | S71: =IF(ISERROR(R71/Q71),"",R71/Q71) -> 0.17564857 | U71: 8519.6248 | V71: 9488.0396 | W71: 10404.386 | X71: 7749.8195 | Y71: =P71/V71-1 -> 0.086609972 | Z71: =P71-V71 -> 821.75884 | AA71: CM | AB71: 7638.3
A72: Yasso Sticks | B72: 1716 | C72: Yasso Sticks | D72: =SUMIFS('2026'!$M:$M,'2026'!$J:$J,$B72&$C72,'2026'!$O:$O,D$4) -> 256.8191 | E72: =SUMIFS('2026'!$M:$M,'2026'!$J:$J,$B72&$C72,'2026'!$O:$O,E$4) -> 304.29039 | F72: =SUMIFS('2026'!$M:$M,'2026'!$J:$J,$B72&$C72,'2026'!$O:$O,F$4) -> 126.95558 | G72: =SUMIFS('2026'!$M:$M,'2026'!$J:$J,$B72&$C72,'2026'!$O:$O,G$4) -> 203.42901 | H72: =SUMIFS('2026'!$M:$M,'2026'!$J:$J,$B72&$C72,'2026'!$O:$O,H$4) -> 1100.6746 | I72: =SUMIFS('2026'!$M:$M,'2026'!$J:$J,$B72&$C72,'2026'!$O:$O,I$4) -> 156.33408 | J72: =SUMIFS('2026'!$M:$M,'2026'!$J:$J,$B72&$C72,'2026'!$O:$O,J$4) -> 334.3872 | K72: =SUMIFS('2026'!$M:$M,'2026'!$J:$J,$B72&$C72,'2026'!$O:$O,K$4) -> 67.30752 | ... O72: =SUMIFS('2026'!$M:$M,'2026'!$J:$J,$B72&$C72,'2026'!$O:$O,O$4) -> 172.224 | P72: =SUM(D72:O72) -> 3706.4564 | Q72: 6043.5363 | R72: =P72-Q72 -> -2337.0799 | S72: =IF(ISERROR(R72/Q72),"",R72/Q72) -> -0.38670735 | U72: 10547.617 | V72: 9297.3646 | W72: 9465.1164 | X72: 7749.8195 | Y72: =P72/V72-1 -> -0.60134333 | Z72: =P72-V72 -> -5590.9082 | AA72: CM | AB72: 13041
A73: Yasso Sticks | B73: 1717 | C73: Yasso Sticks | D73: =SUMIFS('2026'!$M:$M,'2026'!$J:$J,$B73&$C73,'2026'!$O:$O,D$4) -> 624.3239 | E73: =SUMIFS('2026'!$M:$M,'2026'!$J:$J,$B73&$C73,'2026'!$O:$O,E$4) -> 463.11981 | F73: =SUMIFS('2026'!$M:$M,'2026'!$J:$J,$B73&$C73,'2026'!$O:$O,F$4) -> 283.11952 | G73: =SUMIFS('2026'!$M:$M,'2026'!$J:$J,$B73&$C73,'2026'!$O:$O,G$4) -> 0 | H73: =SUMIFS('2026'!$M:$M,'2026'!$J:$J,$B73&$C73,'2026'!$O:$O,H$4) -> 0 | I73: =SUMIFS('2026'!$M:$M,'2026'!$J:$J,$B73&$C73,'2026'!$O:$O,I$4) -> 270.16704 | J73: =SUMIFS('2026'!$M:$M,'2026'!$J:$J,$B73&$C73,'2026'!$O:$O,J$4) -> 249.99936 | K73: =SUMIFS('2026'!$M:$M,'2026'!$J:$J,$B73&$C73,'2026'!$O:$O,K$4) -> 62.49984 | ... O73: =SUMIFS('2026'!$M:$M,'2026'!$J:$J,$B73&$C73,'2026'!$O:$O,O$4) -> 297.22368 | P73: =SUM(D73:O73) -> 3727.2498 | Q73: 4275.6365 | R73: =P73-Q73 -> -548.3867 | S73: =IF(ISERROR(R73/Q73),"",R73/Q73) -> -0.12825849 | U73: 5525.65 | V73: 5966.8931 | W73: 3161.1767 | X73: 7749.8195 | Y73: =P73/V73-1 -> -0.37534496 | Z73: =P73-V73 -> -2239.6432 | AA73: CM | AB73: 2670.3
A74: Yasso Club | B74: 1712 | C74: Yasso Club | D74: =SUMIFS('2026'!$M:$M,'2026'!$J:$J,$B74&$C74,'2026'!$O:$O,D$4) -> 185.04619 | E74: =SUMIFS('2026'!$M:$M,'2026'!$J:$J,$B74&$C74,'2026'!$O:$O,E$4) -> 454.44492 | F74: =SUMIFS('2026'!$M:$M,'2026'!$J:$J,$B74&$C74,'2026'!$O:$O,F$4) -> 557.78066 | G74: =SUMIFS('2026'!$M:$M,'2026'!$J:$J,$B74&$C74,'2026'!$O:$O,G$4) -> 170.86464 | H74: =SUMIFS('2026'!$M:$M,'2026'!$J:$J,$B74&$C74,'2026'!$O:$O,H$4) -> 280.79201 | I74: =SUMIFS('2026'!$M:$M,'2026'!$J:$J,$B74&$C74,'2026'!$O:$O,I$4) -> 341.72928 | J74: =SUMIFS('2026'!$M:$M,'2026'!$J:$J,$B74&$C74,'2026'!$O:$O,J$4) -> 170.86464 | K74: =SUMIFS('2026'!$M:$M,'2026'!$J:$J,$B74&$C74,'2026'!$O:$O,K$4) -> 683.45856 | ... O74: =SUMIFS('2026'!$M:$M,'2026'!$J:$J,$B74&$C74,'2026'!$O:$O,O$4) -> 512.59392 | P74: =SUM(D74:O74) -> 4917.3828 | Q74: 4736.6241 | R74: =P74-Q74 -> 180.7587 | S74: =IF(ISERROR(R74/Q74),"",R74/Q74) -> 0.038161927 | U74: 5075.7425 | V74: 4273.9515 | W74: 5066.9957 | X74: 2399.0012 | Y74: =P74/V74-1 -> 0.15054718 | Z74: =P74-V74 -> 643.43136 | AA74: CM | AB74: 3320.5404
A75: Yasso Poppables | B75: 1713 | C75: Yasso Poppables | D75: =SUMIFS('2026'!$M:$M,'2026'!$J:$J,$B75&$C75,'2026'!$O:$O,D$4) -> 0.19998 | E75: =SUMIFS('2026'!$M:$M,'2026'!$J:$J,$B75&$C75,'2026'!$O:$O,E$4) -> 41.97358 | F75: =SUMIFS('2026'!$M:$M,'2026'!$J:$J,$B75&$C75,'2026'!$O:$O,F$4) -> 0 | G75: =SUMIFS('2026'!$M:$M,'2026'!$J:$J,$B75&$C75,'2026'!$O:$O,G$4) -> 6.98112 | H75: =SUMIFS('2026'!$M:$M,'2026'!$J:$J,$B75&$C75,'2026'!$O:$O,H$4) -> 0 | I75: =SUMIFS('2026'!$M:$M,'2026'!$J:$J,$B75&$C75,'2026'!$O:$O,I$4) -> 42.6624 | J75: =SUMIFS('2026'!$M:$M,'2026'!$J:$J,$B75&$C75,'2026'!$O:$O,J$4) -> 21.3312 | K75: =SUMIFS('2026'!$M:$M,'2026'!$J:$J,$B75&$C75,'2026'!$O:$O,K$4) -> 17.06496 | ... O75: =SUMIFS('2026'!$M:$M,'2026'!$J:$J,$B75&$C75,'2026'!$O:$O,O$4) -> 0 | P75: =SUM(D75:O75) -> 172.87564 | Q75: 183.19606 | R75: =P75-Q75 -> -10.320422 | S75: =IF(ISERROR(R75/Q75),"",R75/Q75) -> -0.056335394 | U75: 685.5779 | V75: 988.28096 | W75: 1129.5537 | X75: 677.17066 | Y75: =P75/V75-1 -> -0.8250744 | Z75: =P75-V75 -> -815.40532 | AA75: CM | AB75: 1235.028
A76: Yasso Sandwich | B76: 1714 | C76: Yasso Sandwich | D76: =SUMIFS('2026'!$M:$M,'2026'!$J:$J,$B76&$C76,'2026'!$O:$O,D$4) -> 0 | E76: =SUMIFS('2026'!$M:$M,'2026'!$J:$J,$B76&$C76,'2026'!$O:$O,E$4) -> 0 | F76: =SUMIFS('2026'!$M:$M,'2026'!$J:$J,$B76&$C76,'2026'!$O:$O,F$4) -> 0 | G76: =SUMIFS('2026'!$M:$M,'2026'!$J:$J,$B76&$C76,'2026'!$O:$O,G$4) -> 0 | H76: =SUMIFS('2026'!$M:$M,'2026'!$J:$J,$B76&$C76,'2026'!$O:$O,H$4) -> 0 | I76: =SUMIFS('2026'!$M:$M,'2026'!$J:$J,$B76&$C76,'2026'!$O:$O,I$4) -> 0 | J76: =SUMIFS('2026'!$M:$M,'2026'!$J:$J,$B76&$C76,'2026'!$O:$O,J$4) -> 0 | K76: =SUMIFS('2026'!$M:$M,'2026'!$J:$J,$B76&$C76,'2026'!$O:$O,K$4) -> 0 | ... O76: =SUMIFS('2026'!$M:$M,'2026'!$J:$J,$B76&$C76,'2026'!$O:$O,O$4) -> 0 | P76: =SUM(D76:O76) -> 0 | Q76: 0 | R76: =P76-Q76 -> 0 | S76: =IF(ISERROR(R76/Q76),"",R76/Q76) | U76: 12.3039 | V76: 12.3039 | W76: 4.12776 | X76: 122.75099 | Y76: =P76/V76-1 -> -1 | Z76: =P76-V76 -> -12.3039 | AA76: CM | AB76: 0
C77: Total Yasso | D77: =SUM(D71:D76) -> 1507.1799 | E77: =SUM(E71:E76) -> 1545.5708 | F77: =SUM(F71:F76) -> 1450.2585 | G77: =SUM(G71:G76) -> 928.44233 | H77: =SUM(H71:H76) -> 4142.4995 | I77: =SUM(I71:I76) -> 1961.0208 | J77: =SUM(J71:J76) -> 1800.5088 | K77: =SUM(K71:K76) -> 1854.2573 | ... P77: =SUM(P71:P76) -> 22833.763 | Q77: 24008.449 | R77: =P77-Q77 -> -1174.6859 | S77: =IF(ISERROR(R77/Q77),"",R77/Q77) -> -0.048928021 | U77: 30366.516 | V77: 30026.834 | W77: 29231.356 | X77: =SUM(X71:X76) -> 26448.381 | Y77: =P77/V77-1 -> -0.23955474 | Z77: =P77-V77 -> -7193.0704 | AB77: 27905.168
R78: Vs PV | T78: Commentary
D79: Jan | E79: Feb | F79: Mar | G79: Apr | H79: May | I79: Jun | J79: Jul | K79: Aug | L79: Sep | M79: Oct | N79: Nov | O79: Dec | P79: =P$4 -> 2026 MRF3 | Q79: 2026 MRF2 | R79: =R$4 -> Difference | S79: =S$4 -> % change | U79: 2025 Final | V79: 2025 MRF8 | W79: 2025 MRF7 | X79: 2024 MRF12 | AB79: 2026 MRF7
A80: Dough Bites | B80: Rhino | C80: Dough Bites | D80: =SUMIFS('2026'!$M:$M,'2026'!$J:$J,$B80&$C80,'2026'!$O:$O,D$4) -> 120.96796 | E80: =SUMIFS('2026'!$M:$M,'2026'!$J:$J,$B80&$C80,'2026'!$O:$O,E$4) -> 86.299632 | F80: =SUMIFS('2026'!$M:$M,'2026'!$J:$J,$B80&$C80,'2026'!$O:$O,F$4) -> 70.689622 | G80: =SUMIFS('2026'!$M:$M,'2026'!$J:$J,$B80&$C80,'2026'!$O:$O,G$4) -> 92.547141 | H80: =SUMIFS('2026'!$M:$M,'2026'!$J:$J,$B80&$C80,'2026'!$O:$O,H$4) -> 75.614316 | I80: =SUMIFS('2026'!$M:$M,'2026'!$J:$J,$B80&$C80,'2026'!$O:$O,I$4) -> 61.581734 | J80: =SUMIFS('2026'!$M:$M,'2026'!$J:$J,$B80&$C80,'2026'!$O:$O,J$4) -> 67.746854 | K80: =SUMIFS('2026'!$M:$M,'2026'!$J:$J,$B80&$C80,'2026'!$O:$O,K$4) -> 51.600522 | ... O80: =SUMIFS('2026'!$M:$M,'2026'!$J:$J,$B80&$C80,'2026'!$O:$O,O$4) -> 31.902021 | P80: =SUM(D80:O80) -> 771.17468 | Q80: 730.62335 | R80: =P80-Q80 -> 40.551329 | S80: =IF(ISERROR(R80/Q80),"",R80/Q80) -> 0.055502372 | U80: 793.48547 | V80: 827.82833 | W80: 878.69086 | X80: 724.06357 | Y80: =P80/V80-1 -> -0.06843647 | Z80: =P80-V80 -> -56.653648 | AA80: CM | AB80: 688.13928
A81: ESS | B81: 6757 | C81: ESS | D81: =SUMIFS('2026'!$M:$M,'2026'!$J:$J,$B81&$C81,'2026'!$O:$O,D$4) -> 191.664 | E81: =SUMIFS('2026'!$M:$M,'2026'!$J:$J,$B81&$C81,'2026'!$O:$O,E$4) -> 301.644 | F81: =SUMIFS('2026'!$M:$M,'2026'!$J:$J,$B81&$C81,'2026'!$O:$O,F$4) -> 298.93032 | G81: =SUMIFS('2026'!$M:$M,'2026'!$J:$J,$B81&$C81,'2026'!$O:$O,G$4) -> 279.08352 | H81: =SUMIFS('2026'!$M:$M,'2026'!$J:$J,$B81&$C81,'2026'!$O:$O,H$4) -> 279.08352 | I81: =SUMIFS('2026'!$M:$M,'2026'!$J:$J,$B81&$C81,'2026'!$O:$O,I$4) -> 334.89792 | J81: =SUMIFS('2026'!$M:$M,'2026'!$J:$J,$B81&$C81,'2026'!$O:$O,J$4) -> 279.08352 | K81: =SUMIFS('2026'!$M:$M,'2026'!$J:$J,$B81&$C81,'2026'!$O:$O,K$4) -> 348.8544 | ... O81: =SUMIFS('2026'!$M:$M,'2026'!$J:$J,$B81&$C81,'2026'!$O:$O,O$4) -> 17.579213 | P81: =SUM(D81:O81) -> 2749.4457 | Q81: 2722.6978 | R81: =P81-Q81 -> 26.747933 | S81: =IF(ISERROR(R81/Q81),"",R81/Q81) -> 0.0098240551 | U81: 2158.9822 | V81: 3141.714 | W81: 3228.8844 | X81: 0 | Y81: =P81/V81-1 -> -0.12485806 | Z81: =P81-V81 -> -392.26831 | AA81: CM | AB81: 2610.5472
A82: Yasso Sandwich | B82: 6757 | C82: Yasso Sandwich | D82: =SUMIFS('2026'!$M:$M,'2026'!$J:$J,$B82&$C82,'2026'!$O:$O,D$4) -> 0 | E82: =SUMIFS('2026'!$M:$M,'2026'!$J:$J,$B82&$C82,'2026'!$O:$O,E$4) -> 84.076984 | F82: =SUMIFS('2026'!$M:$M,'2026'!$J:$J,$B82&$C82,'2026'!$O:$O,F$4) -> 85.418016 | G82: =SUMIFS('2026'!$M:$M,'2026'!$J:$J,$B82&$C82,'2026'!$O:$O,G$4) -> 0 | H82: =SUMIFS('2026'!$M:$M,'2026'!$J:$J,$B82&$C82,'2026'!$O:$O,H$4) -> 29.378304 | I82: =SUMIFS('2026'!$M:$M,'2026'!$J:$J,$B82&$C82,'2026'!$O:$O,I$4) -> 0 | J82: =SUMIFS('2026'!$M:$M,'2026'!$J:$J,$B82&$C82,'2026'!$O:$O,J$4) -> 0 | K82: =SUMIFS('2026'!$M:$M,'2026'!$J:$J,$B82&$C82,'2026'!$O:$O,K$4) -> 0 | ... O82: =SUMIFS('2026'!$M:$M,'2026'!$J:$J,$B82&$C82,'2026'!$O:$O,O$4) -> 0 | P82: =SUM(D82:O82) -> 216.45252 | Q82: 196.04654 | R82: =P82-Q82 -> 20.405979 | S82: =IF(ISERROR(R82/Q82),"",R82/Q82) -> 0.10408742 | U82: 421.19542 | V82: 353.50788 | W82: 1678.7444 | X82: 0 | Y82: =P82/V82-1 -> -0.38770101 | Z82: =P82-V82 -> -137.05536 | AA82: CM | AB82: 3766.4256
A83: Other | B83: 6757 | C83: BR Minicups | D83: =SUMIFS('2026'!$M:$M,'2026'!$J:$J,$B83&$C83,'2026'!$O:$O,D$4) -> 0 | E83: =SUMIFS('2026'!$M:$M,'2026'!$J:$J,$B83&$C83,'2026'!$O:$O,E$4) -> 0 | F83: =SUMIFS('2026'!$M:$M,'2026'!$J:$J,$B83&$C83,'2026'!$O:$O,F$4) -> 0 | G83: =SUMIFS('2026'!$M:$M,'2026'!$J:$J,$B83&$C83,'2026'!$O:$O,G$4) -> 0 | H83: =SUMIFS('2026'!$M:$M,'2026'!$J:$J,$B83&$C83,'2026'!$O:$O,H$4) -> 0 | I83: =SUMIFS('2026'!$M:$M,'2026'!$J:$J,$B83&$C83,'2026'!$O:$O,I$4) -> 0 | J83: =SUMIFS('2026'!$M:$M,'2026'!$J:$J,$B83&$C83,'2026'!$O:$O,J$4) -> 0 | K83: =SUMIFS('2026'!$M:$M,'2026'!$J:$J,$B83&$C83,'2026'!$O:$O,K$4) -> 0 | ... O83: =SUMIFS('2026'!$M:$M,'2026'!$J:$J,$B83&$C83,'2026'!$O:$O,O$4) -> 0 | P83: =SUM(D83:O83) -> 0 | Q83: 0 | U83: 0 | V83: 0 | W83: 299.79408 | Y83: =P83/V83-1 -> #DIV/0! | Z83: =P83-V83 -> 0 | AA83: CM | AB83: 105.57294
A84: Other | B84: 1717 | C84: Other | D84: =SUMIFS('2026'!$M:$M,'2026'!$J:$J,$B84&$C84,'2026'!$O:$O,D$4) -> 196.11169 | E84: =SUMIFS('2026'!$M:$M,'2026'!$J:$J,$B84&$C84,'2026'!$O:$O,E$4) -> 107.74061 | F84: =SUMIFS('2026'!$M:$M,'2026'!$J:$J,$B84&$C84,'2026'!$O:$O,F$4) -> 263.80318 | G84: =SUMIFS('2026'!$M:$M,'2026'!$J:$J,$B84&$C84,'2026'!$O:$O,G$4) -> 196.37315 | H84: =SUMIFS('2026'!$M:$M,'2026'!$J:$J,$B84&$C84,'2026'!$O:$O,H$4) -> 154.45048 | I84: =SUMIFS('2026'!$M:$M,'2026'!$J:$J,$B84&$C84,'2026'!$O:$O,I$4) -> 145.38899 | J84: =SUMIFS('2026'!$M:$M,'2026'!$J:$J,$B84&$C84,'2026'!$O:$O,J$4) -> 183.5136 | K84: =SUMIFS('2026'!$M:$M,'2026'!$J:$J,$B84&$C84,'2026'!$O:$O,K$4) -> 122.3424 | ... O84: =SUMIFS('2026'!$M:$M,'2026'!$J:$J,$B84&$C84,'2026'!$O:$O,O$4) -> 81.5616 | P84: =SUM(D84:O84) -> 1818.3129 | Q84: 1806.6683 | R84: =P84-Q84 -> 11.644618 | S84: =IF(ISERROR(R84/Q84),"",R84/Q84) -> 0.0064453545 | U84: 0 | V84: 0 | W84: 0 | Y84: =P84/V84-1 -> #DIV/0! | Z84: =P84-V84 -> 1818.3129 | AA84: CM | AB84: 1359.36
A85: YS PTS | B85: 1716 | C85: YS PTS | D85: =SUMIFS('2026'!$M:$M,'2026'!$J:$J,$B85&$C85,'2026'!$O:$O,D$4) -> 694.46347 | E85: =SUMIFS('2026'!$M:$M,'2026'!$J:$J,$B85&$C85,'2026'!$O:$O,E$4) -> 685.98475 | F85: =SUMIFS('2026'!$M:$M,'2026'!$J:$J,$B85&$C85,'2026'!$O:$O,F$4) -> 1036.3281 | G85: =SUMIFS('2026'!$M:$M,'2026'!$J:$J,$B85&$C85,'2026'!$O:$O,G$4) -> 749.1744 | H85: =SUMIFS('2026'!$M:$M,'2026'!$J:$J,$B85&$C85,'2026'!$O:$O,H$4) -> 416.51712 | I85: =SUMIFS('2026'!$M:$M,'2026'!$J:$J,$B85&$C85,'2026'!$O:$O,I$4) -> 257.54112 | J85: =SUMIFS('2026'!$M:$M,'2026'!$J:$J,$B85&$C85,'2026'!$O:$O,J$4) -> 515.08224 | K85: =SUMIFS('2026'!$M:$M,'2026'!$J:$J,$B85&$C85,'2026'!$O:$O,K$4) -> 257.54112 | ... O85: =SUMIFS('2026'!$M:$M,'2026'!$J:$J,$B85&$C85,'2026'!$O:$O,O$4) -> 168.51456 | P85: =SUM(D85:O85) -> 5890.7994 | Q85: 5563.7267 | R85: =P85-Q85 -> 327.07272 | S85: =IF(ISERROR(R85/Q85),"",R85/Q85) -> 0.058786626 | U85: 599.25341 | V85: 789.63048 | W85: 1052.2224 | Y85: =P85/V85-1 -> 6.4601976 | Z85: =P85-V85 -> 5101.1689 | AA85: CM | AB85: 0
A86: SP1 | B86: 1716 | C86: PTS | D86: =SUMIFS('2026'!$M:$M,'2026'!$J:$J,$B86&$C86,'2026'!$O:$O,D$4) -> 0 | E86: =SUMIFS('2026'!$M:$M,'2026'!$J:$J,$B86&$C86,'2026'!$O:$O,E$4) -> 0 | F86: =SUMIFS('2026'!$M:$M,'2026'!$J:$J,$B86&$C86,'2026'!$O:$O,F$4) -> 0 | G86: =SUMIFS('2026'!$M:$M,'2026'!$J:$J,$B86&$C86,'2026'!$O:$O,G$4) -> 0 | H86: =SUMIFS('2026'!$M:$M,'2026'!$J:$J,$B86&$C86,'2026'!$O:$O,H$4) -> 0 | I86: =SUMIFS('2026'!$M:$M,'2026'!$J:$J,$B86&$C86,'2026'!$O:$O,I$4) -> 0 | J86: =SUMIFS('2026'!$M:$M,'2026'!$J:$J,$B86&$C86,'2026'!$O:$O,J$4) -> 0 | K86: =SUMIFS('2026'!$M:$M,'2026'!$J:$J,$B86&$C86,'2026'!$O:$O,K$4) -> 0 | ... O86: =SUMIFS('2026'!$M:$M,'2026'!$J:$J,$B86&$C86,'2026'!$O:$O,O$4) -> 340.56 | P86: =SUM(D86:O86) -> 340.56 | Q86: 0 | R86: =P86-Q86 -> 340.56 | S86: =IF(ISERROR(R86/Q86),"",R86/Q86) | U86: 0 | V86: 0 | W86: 0 | X86: 0 | Y86: =P86/V86-1 -> #DIV/0! | Z86: =P86-V86 -> 340.56 | AA86: CM | AB86: 0
A87: BJ Pts | B87: 1716 | C87: BJ PTS | D87: =SUMIFS('2026'!$M:$M,'2026'!$J:$J,$B87&$C87,'2026'!$O:$O,D$4) -> 0 | E87: =SUMIFS('2026'!$M:$M,'2026'!$J:$J,$B87&$C87,'2026'!$O:$O,E$4) -> 0 | F87: =SUMIFS('2026'!$M:$M,'2026'!$J:$J,$B87&$C87,'2026'!$O:$O,F$4) -> 0 | G87: =SUMIFS('2026'!$M:$M,'2026'!$J:$J,$B87&$C87,'2026'!$O:$O,G$4) -> 0 | H87: =SUMIFS('2026'!$M:$M,'2026'!$J:$J,$B87&$C87,'2026'!$O:$O,H$4) -> 0 | I87: =SUMIFS('2026'!$M:$M,'2026'!$J:$J,$B87&$C87,'2026'!$O:$O,I$4) -> 0 | J87: =SUMIFS('2026'!$M:$M,'2026'!$J:$J,$B87&$C87,'2026'!$O:$O,J$4) -> 0 | K87: =SUMIFS('2026'!$M:$M,'2026'!$J:$J,$B87&$C87,'2026'!$O:$O,K$4) -> 0 | ... O87: =SUMIFS('2026'!$M:$M,'2026'!$J:$J,$B87&$C87,'2026'!$O:$O,O$4) -> 0 | P87: =SUM(D87:O87) -> 0 | Q87: 0 | R87: =P87-Q87 -> 0 | S87: =IF(ISERROR(R87/Q87),"",R87/Q87) | U87: 2054.5864 | V87: 2298.3198 | W87: 2298.3198 | X87: 0 | Y87: =P87/V87-1 -> -1 | Z87: =P87-V87 -> -2298.3198 | AA87: CM | AB87: 0
A88: BJ Bars | B88: 1716 | C88: BJ Bars | D88: =SUMIFS('2026'!$M:$M,'2026'!$J:$J,$B88&$C88,'2026'!$O:$O,D$4) -> 216.1728 | E88: =SUMIFS('2026'!$M:$M,'2026'!$J:$J,$B88&$C88,'2026'!$O:$O,E$4) -> 520.608 | F88: =SUMIFS('2026'!$M:$M,'2026'!$J:$J,$B88&$C88,'2026'!$O:$O,F$4) -> 684.76176 | G88: =SUMIFS('2026'!$M:$M,'2026'!$J:$J,$B88&$C88,'2026'!$O:$O,G$4) -> 770.6903 | H88: =SUMIFS('2026'!$M:$M,'2026'!$J:$J,$B88&$C88,'2026'!$O:$O,H$4) -> 1128.0707 | I88: =SUMIFS('2026'!$M:$M,'2026'!$J:$J,$B88&$C88,'2026'!$O:$O,I$4) -> 774.144 | J88: =SUMIFS('2026'!$M:$M,'2026'!$J:$J,$B88&$C88,'2026'!$O:$O,J$4) -> 258.048 | K88: =SUMIFS('2026'!$M:$M,'2026'!$J:$J,$B88&$C88,'2026'!$O:$O,K$4) -> 516.096 | ... O88: =SUMIFS('2026'!$M:$M,'2026'!$J:$J,$B88&$C88,'2026'!$O:$O,O$4) -> 193.536 | P88: =SUM(D88:O88) -> 6739.4395 | Q88: 5967.1823 | R88: =P88-Q88 -> 772.25722 | S88: =IF(ISERROR(R88/Q88),"",R88/Q88) -> 0.1294174 | U88: 555.9312 | V88: 912 | W88: 1125.6 | Y88: =P88/V88-1 -> 6.3897363 | Z88: =P88-V88 -> 5827.4395 | AA88: CM | AB88: 772.9578
A89: ESS | B89: Turkey Hill | C89: ESS | D89: =SUMIFS('2026'!$M:$M,'2026'!$J:$J,$B89&$C89,'2026'!$O:$O,D$4) -> 0 | E89: =SUMIFS('2026'!$M:$M,'2026'!$J:$J,$B89&$C89,'2026'!$O:$O,E$4) -> 0 | F89: =SUMIFS('2026'!$M:$M,'2026'!$J:$J,$B89&$C89,'2026'!$O:$O,F$4) -> 0 | G89: =SUMIFS('2026'!$M:$M,'2026'!$J:$J,$B89&$C89,'2026'!$O:$O,G$4) -> 222.22222 | H89: =SUMIFS('2026'!$M:$M,'2026'!$J:$J,$B89&$C89,'2026'!$O:$O,H$4) -> 420 | I89: =SUMIFS('2026'!$M:$M,'2026'!$J:$J,$B89&$C89,'2026'!$O:$O,I$4) -> 372.22222 | J89: =SUMIFS('2026'!$M:$M,'2026'!$J:$J,$B89&$C89,'2026'!$O:$O,J$4) -> 372.20722 | K89: =SUMIFS('2026'!$M:$M,'2026'!$J:$J,$B89&$C89,'2026'!$O:$O,K$4) -> 372.20722 | ... O89: =SUMIFS('2026'!$M:$M,'2026'!$J:$J,$B89&$C89,'2026'!$O:$O,O$4) -> 272.22222 | P89: =SUM(D89:O89) -> 2972.7478 | Q89: 2972.7478 | R89: =P89-Q89 -> 0 | S89: =IF(ISERROR(R89/Q89),"",R89/Q89) -> 0 | U89: 0 | V89: 0 | W89: 0 | Y89: =P89/V89-1 -> #DIV/0! | Z89: =P89-V89 -> 2972.7478 | AA89: CM | AB89: 0
A90: Other | B90: Glacier Point | C90: Other | D90: =SUMIFS('2026'!$M:$M,'2026'!$J:$J,$B90&$C90,'2026'!$O:$O,D$4) -> 0 | E90: =SUMIFS('2026'!$M:$M,'2026'!$J:$J,$B90&$C90,'2026'!$O:$O,E$4) -> 0 | F90: =SUMIFS('2026'!$M:$M,'2026'!$J:$J,$B90&$C90,'2026'!$O:$O,F$4) -> 0 | G90: =SUMIFS('2026'!$M:$M,'2026'!$J:$J,$B90&$C90,'2026'!$O:$O,G$4) -> 0 | H90: =SUMIFS('2026'!$M:$M,'2026'!$J:$J,$B90&$C90,'2026'!$O:$O,H$4) -> 0 | I90: =SUMIFS('2026'!$M:$M,'2026'!$J:$J,$B90&$C90,'2026'!$O:$O,I$4) -> 0 | J90: =SUMIFS('2026'!$M:$M,'2026'!$J:$J,$B90&$C90,'2026'!$O:$O,J$4) -> 0 | K90: =SUMIFS('2026'!$M:$M,'2026'!$J:$J,$B90&$C90,'2026'!$O:$O,K$4) -> 0 | ... O90: =SUMIFS('2026'!$M:$M,'2026'!$J:$J,$B90&$C90,'2026'!$O:$O,O$4) -> 0 | P90: =SUM(D90:O90) -> 0 | Q90: 0 | R90: =P90-Q90 -> 0 | S90: =IF(ISERROR(R90/Q90),"",R90/Q90) | U90: 836.1209 | V90: 836.1209 | W90: 836.1209 | X90: 0 | Y90: =P90/V90-1 -> -1 | Z90: =P90-V90 -> -836.1209 | AA90: CM | AB90: 0
C92: Imports/Others | R92: Vs PV | T92: Commentary
C93: Row Labels | D93: Jan | E93: Feb | F93: Mar | G93: Apr | H93: May | I93: Jun | J93: Jul | K93: Aug | L93: Sep | M93: Oct | N93: Nov | O93: Dec | P93: =P$4 -> 2026 MRF3 | Q93: 2026 MRF2 | R93: =R$4 -> Difference | S93: =S$4 -> % change | U93: 2025 Final | V93: 2025 MRF8 | W93: 2025 MRF7 | X93: 2024 | AB93: 2026 MRF7
A94: Other | B94: St Iria | C94: King Cone (PT) | D94: =SUMIFS('2026'!$M:$M,'2026'!$J:$J,$B94&$C94,'2026'!$O:$O,D$4) -> 0 | E94: =SUMIFS('2026'!$M:$M,'2026'!$J:$J,$B94&$C94,'2026'!$O:$O,E$4) -> 0 | F94: =SUMIFS('2026'!$M:$M,'2026'!$J:$J,$B94&$C94,'2026'!$O:$O,F$4) -> 0 | G94: =SUMIFS('2026'!$M:$M,'2026'!$J:$J,$B94&$C94,'2026'!$O:$O,G$4) -> 0 | H94: =SUMIFS('2026'!$M:$M,'2026'!$J:$J,$B94&$C94,'2026'!$O:$O,H$4) -> 0 | I94: =SUMIFS('2026'!$M:$M,'2026'!$J:$J,$B94&$C94,'2026'!$O:$O,I$4) -> 0 | J94: =SUMIFS('2026'!$M:$M,'2026'!$J:$J,$B94&$C94,'2026'!$O:$O,J$4) -> 0 | K94: =SUMIFS('2026'!$M:$M,'2026'!$J:$J,$B94&$C94,'2026'!$O:$O,K$4) -> 0 | ... O94: =SUMIFS('2026'!$M:$M,'2026'!$J:$J,$B94&$C94,'2026'!$O:$O,O$4) -> 0 | P94: =SUM(D94:O94) -> 0 | Q94: 0 | R94: =P94-Q94 -> 0 | S94: =IF(ISERROR(R94/Q94),"",R94/Q94) | U94: 0 | V94: 0 | W94: 0 | X94: 0 | Y94: =P94/V94-1 -> #DIV/0! | Z94: =P94-V94 -> 0 | AA94: Import | AB94: 0
A95: MG Sticks | B95: St Iria | C95: MG Sticks | D95: =SUMIFS('2026'!$M:$M,'2026'!$J:$J,$B95&$C95,'2026'!$O:$O,D$4) -> 0 | E95: =SUMIFS('2026'!$M:$M,'2026'!$J:$J,$B95&$C95,'2026'!$O:$O,E$4) -> 0 | F95: =SUMIFS('2026'!$M:$M,'2026'!$J:$J,$B95&$C95,'2026'!$O:$O,F$4) -> 0 | G95: =SUMIFS('2026'!$M:$M,'2026'!$J:$J,$B95&$C95,'2026'!$O:$O,G$4) -> 0 | H95: =SUMIFS('2026'!$M:$M,'2026'!$J:$J,$B95&$C95,'2026'!$O:$O,H$4) -> 0 | I95: =SUMIFS('2026'!$M:$M,'2026'!$J:$J,$B95&$C95,'2026'!$O:$O,I$4) -> 0 | J95: =SUMIFS('2026'!$M:$M,'2026'!$J:$J,$B95&$C95,'2026'!$O:$O,J$4) -> 0 | K95: =SUMIFS('2026'!$M:$M,'2026'!$J:$J,$B95&$C95,'2026'!$O:$O,K$4) -> 0 | ... O95: =SUMIFS('2026'!$M:$M,'2026'!$J:$J,$B95&$C95,'2026'!$O:$O,O$4) -> 0 | P95: =SUM(D95:O95) -> 0 | Q95: 0 | R95: =P95-Q95 -> 0 | S95: =IF(ISERROR(R95/Q95),"",R95/Q95) | U95: 0 | V95: 0 | W95: 0 | X95: 0 | Y95: =P95/V95-1 -> #DIV/0! | Z95: =P95-V95 -> 0 | AA95: Import | AB95: 0
A96: PG | B96: Tultitlan | C96: PG | D96: =SUMIFS('2026'!$M:$M,'2026'!$J:$J,$B96&$C96,'2026'!$O:$O,D$4) -> 0 | E96: =SUMIFS('2026'!$M:$M,'2026'!$J:$J,$B96&$C96,'2026'!$O:$O,E$4) -> 0 | F96: =SUMIFS('2026'!$M:$M,'2026'!$J:$J,$B96&$C96,'2026'!$O:$O,F$4) -> 0 | G96: =SUMIFS('2026'!$M:$M,'2026'!$J:$J,$B96&$C96,'2026'!$O:$O,G$4) -> 0 | H96: =SUMIFS('2026'!$M:$M,'2026'!$J:$J,$B96&$C96,'2026'!$O:$O,H$4) -> 0 | I96: =SUMIFS('2026'!$M:$M,'2026'!$J:$J,$B96&$C96,'2026'!$O:$O,I$4) -> 0 | J96: =SUMIFS('2026'!$M:$M,'2026'!$J:$J,$B96&$C96,'2026'!$O:$O,J$4) -> 0 | K96: =SUMIFS('2026'!$M:$M,'2026'!$J:$J,$B96&$C96,'2026'!$O:$O,K$4) -> 0 | ... O96: =SUMIFS('2026'!$M:$M,'2026'!$J:$J,$B96&$C96,'2026'!$O:$O,O$4) -> 0 | P96: =SUM(D96:O96) -> 0 | Q96: 0 | R96: =P96-Q96 -> 0 | S96: =IF(ISERROR(R96/Q96),"",R96/Q96) | U96: 0 | V96: 0 | W96: 0 | X96: 0 | Y96: =P96/V96-1 -> #DIV/0! | Z96: =P96-V96 -> 0 | AA96: Import | AB96: 0
A97: Other | B97: Tultitlan | C97: Other | D97: =SUMIFS('2026'!$M:$M,'2026'!$J:$J,$B97&$C97,'2026'!$O:$O,D$4) -> 19.83904 | E97: =SUMIFS('2026'!$M:$M,'2026'!$J:$J,$B97&$C97,'2026'!$O:$O,E$4) -> 59.78336 | F97: =SUMIFS('2026'!$M:$M,'2026'!$J:$J,$B97&$C97,'2026'!$O:$O,F$4) -> 55.001496 | G97: =SUMIFS('2026'!$M:$M,'2026'!$J:$J,$B97&$C97,'2026'!$O:$O,G$4) -> 20.358766 | H97: =SUMIFS('2026'!$M:$M,'2026'!$J:$J,$B97&$C97,'2026'!$O:$O,H$4) -> 9.090455 | I97: =SUMIFS('2026'!$M:$M,'2026'!$J:$J,$B97&$C97,'2026'!$O:$O,I$4) -> 11.631698 | J97: =SUMIFS('2026'!$M:$M,'2026'!$J:$J,$B97&$C97,'2026'!$O:$O,J$4) -> 5.7118464 | K97: =SUMIFS('2026'!$M:$M,'2026'!$J:$J,$B97&$C97,'2026'!$O:$O,K$4) -> 13.742638 | ... O97: =SUMIFS('2026'!$M:$M,'2026'!$J:$J,$B97&$C97,'2026'!$O:$O,O$4) -> 0 | P97: =SUM(D97:O97) -> 204.79686 | Q97: 168.06437 | R97: =P97-Q97 -> 36.732481 | S97: =IF(ISERROR(R97/Q97),"",R97/Q97) -> 0.21856197 | U97: 567.5384 | V97: 275.29872 | W97: 341.91484 | Y97: =P97/V97-1 -> -0.25609224 | Z97: =P97-V97 -> -70.501865 | AA97: Import | AB97: 146.07384
A98: ESS | B98: Tultitlan | C98: KL Sandwiches | D98: =SUMIFS('2026'!$M:$M,'2026'!$J:$J,$B98&$C98,'2026'!$O:$O,D$4) -> 0 | E98: =SUMIFS('2026'!$M:$M,'2026'!$J:$J,$B98&$C98,'2026'!$O:$O,E$4) -> 0 | F98: =SUMIFS('2026'!$M:$M,'2026'!$J:$J,$B98&$C98,'2026'!$O:$O,F$4) -> 0 | G98: =SUMIFS('2026'!$M:$M,'2026'!$J:$J,$B98&$C98,'2026'!$O:$O,G$4) -> 0 | H98: =SUMIFS('2026'!$M:$M,'2026'!$J:$J,$B98&$C98,'2026'!$O:$O,H$4) -> 0 | I98: =SUMIFS('2026'!$M:$M,'2026'!$J:$J,$B98&$C98,'2026'!$O:$O,I$4) -> 0 | J98: =SUMIFS('2026'!$M:$M,'2026'!$J:$J,$B98&$C98,'2026'!$O:$O,J$4) -> 0 | K98: =SUMIFS('2026'!$M:$M,'2026'!$J:$J,$B98&$C98,'2026'!$O:$O,K$4) -> 0 | ... O98: =SUMIFS('2026'!$M:$M,'2026'!$J:$J,$B98&$C98,'2026'!$O:$O,O$4) -> 0 | P98: =SUM(D98:O98) -> 0 | Q98: 0 | R98: =P98-Q98 -> 0 | S98: =IF(ISERROR(R98/Q98),"",R98/Q98) | U98: 0 | V98: 0 | W98: 0 | X98: 141.492 | Y98: =P98/V98-1 -> #DIV/0! | Z98: =P98-V98 -> 0 | AA98: Import | AB98: 0
A99: KL Mini Cones | B99: Tultitlan | C99: KL Mini Cones | D99: =SUMIFS('2026'!$M:$M,'2026'!$J:$J,$B99&$C99,'2026'!$O:$O,D$4) -> 20.715264 | E99: =SUMIFS('2026'!$M:$M,'2026'!$J:$J,$B99&$C99,'2026'!$O:$O,E$4) -> 45.954 | F99: =SUMIFS('2026'!$M:$M,'2026'!$J:$J,$B99&$C99,'2026'!$O:$O,F$4) -> 32.803782 | G99: =SUMIFS('2026'!$M:$M,'2026'!$J:$J,$B99&$C99,'2026'!$O:$O,G$4) -> 0 | H99: =SUMIFS('2026'!$M:$M,'2026'!$J:$J,$B99&$C99,'2026'!$O:$O,H$4) -> 39.314678 | I99: =SUMIFS('2026'!$M:$M,'2026'!$J:$J,$B99&$C99,'2026'!$O:$O,I$4) -> 0 | J99: =SUMIFS('2026'!$M:$M,'2026'!$J:$J,$B99&$C99,'2026'!$O:$O,J$4) -> 0 | K99: =SUMIFS('2026'!$M:$M,'2026'!$J:$J,$B99&$C99,'2026'!$O:$O,K$4) -> 0 | ... O99: =SUMIFS('2026'!$M:$M,'2026'!$J:$J,$B99&$C99,'2026'!$O:$O,O$4) -> 0 | P99: =SUM(D99:O99) -> 138.78772 | Q99: 182.96816 | R99: =P99-Q99 -> -44.180438 | S99: =IF(ISERROR(R99/Q99),"",R99/Q99) -> -0.24146517 | U99: 566.51026 | V99: 164.62987 | W99: 522.082 | X99: 761.56301 | Y99: =P99/V99-1 -> -0.1569712 | Z99: =P99-V99 -> -25.842148 | AA99: Import | AB99: 0
A100: MG Sticks | B100: Tultitlan | C100: MG Sticks | D100: =SUMIFS('2026'!$M:$M,'2026'!$J:$J,$B100&$C100,'2026'!$O:$O,D$4) -> 0 | E100: =SUMIFS('2026'!$M:$M,'2026'!$J:$J,$B100&$C100,'2026'!$O:$O,E$4) -> 0 | F100: =SUMIFS('2026'!$M:$M,'2026'!$J:$J,$B100&$C100,'2026'!$O:$O,F$4) -> 0 | G100: =SUMIFS('2026'!$M:$M,'2026'!$J:$J,$B100&$C100,'2026'!$O:$O,G$4) -> 0 | H100: =SUMIFS('2026'!$M:$M,'2026'!$J:$J,$B100&$C100,'2026'!$O:$O,H$4) -> 0 | I100: =SUMIFS('2026'!$M:$M,'2026'!$J:$J,$B100&$C100,'2026'!$O:$O,I$4) -> 0 | J100: =SUMIFS('2026'!$M:$M,'2026'!$J:$J,$B100&$C100,'2026'!$O:$O,J$4) -> 0 | K100: =SUMIFS('2026'!$M:$M,'2026'!$J:$J,$B100&$C100,'2026'!$O:$O,K$4) -> 0 | ... O100: =SUMIFS('2026'!$M:$M,'2026'!$J:$J,$B100&$C100,'2026'!$O:$O,O$4) -> 0 | P100: =SUM(D100:O100) -> 0 | Q100: 0 | R100: =P100-Q100 -> 0 | S100: =IF(ISERROR(R100/Q100),"",R100/Q100) | U100: 3.04488 | V100: 3.04488 | W100: 3.04488 | X100: 390.48678 | Y100: =P100/V100-1 -> -1 | Z100: =P100-V100 -> -3.04488 | AA100: Import | AB100: 0
A101: 48oz | B101: 3910 | C101: 48oz | D101: =SUMIFS('2026'!$M:$M,'2026'!$J:$J,$B101&$C101,'2026'!$O:$O,D$4) -> 0 | E101: =SUMIFS('2026'!$M:$M,'2026'!$J:$J,$B101&$C101,'2026'!$O:$O,E$4) -> 0 | F101: =SUMIFS('2026'!$M:$M,'2026'!$J:$J,$B101&$C101,'2026'!$O:$O,F$4) -> 0 | G101: =SUMIFS('2026'!$M:$M,'2026'!$J:$J,$B101&$C101,'2026'!$O:$O,G$4) -> 190.8576 | H101: =SUMIFS('2026'!$M:$M,'2026'!$J:$J,$B101&$C101,'2026'!$O:$O,H$4) -> 668.0016 | I101: =SUMIFS('2026'!$M:$M,'2026'!$J:$J,$B101&$C101,'2026'!$O:$O,I$4) -> 1813.1472 | J101: =SUMIFS('2026'!$M:$M,'2026'!$J:$J,$B101&$C101,'2026'!$O:$O,J$4) -> 1526.8608 | K101: =SUMIFS('2026'!$M:$M,'2026'!$J:$J,$B101&$C101,'2026'!$O:$O,K$4) -> 0 | ... O101: =SUMIFS('2026'!$M:$M,'2026'!$J:$J,$B101&$C101,'2026'!$O:$O,O$4) -> 0 | P101: =SUM(D101:O101) -> 4198.8672 | Q101: 3834 | R101: =P101-Q101 -> 364.8672 | S101: =IF(ISERROR(R101/Q101),"",R101/Q101) -> 0.095166197 | U101: 0 | V101: 0 | W101: 0 | X101: 0 | Y101: =P101/V101-1 -> #DIV/0! | Z101: =P101-V101 -> 4198.8672 | AA101: SIM | AB101: 5112
A102: ESS | B102: 3910 | C102: ESS | D102: =SUMIFS('2026'!$M:$M,'2026'!$J:$J,$B102&$C102,'2026'!$O:$O,D$4) -> 174.40769 | E102: =SUMIFS('2026'!$M:$M,'2026'!$J:$J,$B102&$C102,'2026'!$O:$O,E$4) -> 43.830072 | F102: =SUMIFS('2026'!$M:$M,'2026'!$J:$J,$B102&$C102,'2026'!$O:$O,F$4) -> 0 | G102: =SUMIFS('2026'!$M:$M,'2026'!$J:$J,$B102&$C102,'2026'!$O:$O,G$4) -> 45.47702 | H102: =SUMIFS('2026'!$M:$M,'2026'!$J:$J,$B102&$C102,'2026'!$O:$O,H$4) -> 0 | I102: =SUMIFS('2026'!$M:$M,'2026'!$J:$J,$B102&$C102,'2026'!$O:$O,I$4) -> 111.49229 | J102: =SUMIFS('2026'!$M:$M,'2026'!$J:$J,$B102&$C102,'2026'!$O:$O,J$4) -> 0 | K102: =SUMIFS('2026'!$M:$M,'2026'!$J:$J,$B102&$C102,'2026'!$O:$O,K$4) -> 52.473485 | ... O102: =SUMIFS('2026'!$M:$M,'2026'!$J:$J,$B102&$C102,'2026'!$O:$O,O$4) -> 0 | P102: =SUM(D102:O102) -> 598.19164 | Q102: 377.83776 | R102: =P102-Q102 -> 220.35388 | S102: =IF(ISERROR(R102/Q102),"",R102/Q102) -> 0.5831971 | U102: 1414.445 | V102: 1537.929 | W102: 1897.9768 | X102: 434.2249 | Y102: =P102/V102-1 -> -0.61104078 | Z102: =P102-V102 -> -939.73732 | AA102: SIM | AB102: 1555.6018
A103: MG Sticks | B103: 3910 | C103: MG Sticks | D103: =SUMIFS('2026'!$M:$M,'2026'!$J:$J,$B103&$C103,'2026'!$O:$O,D$4) -> 0 | E103: =SUMIFS('2026'!$M:$M,'2026'!$J:$J,$B103&$C103,'2026'!$O:$O,E$4) -> 0 | F103: =SUMIFS('2026'!$M:$M,'2026'!$J:$J,$B103&$C103,'2026'!$O:$O,F$4) -> 0 | G103: =SUMIFS('2026'!$M:$M,'2026'!$J:$J,$B103&$C103,'2026'!$O:$O,G$4) -> 0 | H103: =SUMIFS('2026'!$M:$M,'2026'!$J:$J,$B103&$C103,'2026'!$O:$O,H$4) -> 0 | I103: =SUMIFS('2026'!$M:$M,'2026'!$J:$J,$B103&$C103,'2026'!$O:$O,I$4) -> 0 | J103: =SUMIFS('2026'!$M:$M,'2026'!$J:$J,$B103&$C103,'2026'!$O:$O,J$4) -> 0 | K103: =SUMIFS('2026'!$M:$M,'2026'!$J:$J,$B103&$C103,'2026'!$O:$O,K$4) -> 0 | ... O103: =SUMIFS('2026'!$M:$M,'2026'!$J:$J,$B103&$C103,'2026'!$O:$O,O$4) -> 0 | P103: =SUM(D103:O103) -> 0 | Q103: 0 | R103: =P103-Q103 -> 0 | S103: =IF(ISERROR(R103/Q103),"",R103/Q103) | U103: 0 | V103: 16.335432 | W103: 16.335432 | X103: 118.88748 | Y103: =P103/V103-1 -> -1 | Z103: =P103-V103 -> -16.335432 | AA103: SIM | AB103: 0
A104: PG | B104: 3910 | C104: PG | D104: =SUMIFS('2026'!$M:$M,'2026'!$J:$J,$B104&$C104,'2026'!$O:$O,D$4) -> 0 | E104: =SUMIFS('2026'!$M:$M,'2026'!$J:$J,$B104&$C104,'2026'!$O:$O,E$4) -> 0 | F104: =SUMIFS('2026'!$M:$M,'2026'!$J:$J,$B104&$C104,'2026'!$O:$O,F$4) -> 0 | G104: =SUMIFS('2026'!$M:$M,'2026'!$J:$J,$B104&$C104,'2026'!$O:$O,G$4) -> 0 | H104: =SUMIFS('2026'!$M:$M,'2026'!$J:$J,$B104&$C104,'2026'!$O:$O,H$4) -> 0 | I104: =SUMIFS('2026'!$M:$M,'2026'!$J:$J,$B104&$C104,'2026'!$O:$O,I$4) -> 0 | J104: =SUMIFS('2026'!$M:$M,'2026'!$J:$J,$B104&$C104,'2026'!$O:$O,J$4) -> 0 | K104: =SUMIFS('2026'!$M:$M,'2026'!$J:$J,$B104&$C104,'2026'!$O:$O,K$4) -> 0 | ... O104: =SUMIFS('2026'!$M:$M,'2026'!$J:$J,$B104&$C104,'2026'!$O:$O,O$4) -> 0 | P104: =SUM(D104:O104) -> 0 | Q104: 0 | R104: =P104-Q104 -> 0 | S104: =IF(ISERROR(R104/Q104),"",R104/Q104) | U104: 0 | V104: 91.441944 | W104: 91.441944 | X104: 60.197436 | Y104: =P104/V104-1 -> -1 | Z104: =P104-V104 -> -91.441944 | AA104: SIM | AB104: 0
A105: EFW | B105: 3910 | C105: EFW | D105: =SUMIFS('2026'!$M:$M,'2026'!$J:$J,$B105&$C105,'2026'!$O:$O,D$4) -> 0 | E105: =SUMIFS('2026'!$M:$M,'2026'!$J:$J,$B105&$C105,'2026'!$O:$O,E$4) -> 37.625616 | F105: =SUMIFS('2026'!$M:$M,'2026'!$J:$J,$B105&$C105,'2026'!$O:$O,F$4) -> 0.93888 | G105: =SUMIFS('2026'!$M:$M,'2026'!$J:$J,$B105&$C105,'2026'!$O:$O,G$4) -> 69.202483 | H105: =SUMIFS('2026'!$M:$M,'2026'!$J:$J,$B105&$C105,'2026'!$O:$O,H$4) -> 147.35002 | I105: =SUMIFS('2026'!$M:$M,'2026'!$J:$J,$B105&$C105,'2026'!$O:$O,I$4) -> 475.19846 | J105: =SUMIFS('2026'!$M:$M,'2026'!$J:$J,$B105&$C105,'2026'!$O:$O,J$4) -> 526.5408 | K105: =SUMIFS('2026'!$M:$M,'2026'!$J:$J,$B105&$C105,'2026'!$O:$O,K$4) -> 398.49293 | ... O105: =SUMIFS('2026'!$M:$M,'2026'!$J:$J,$B105&$C105,'2026'!$O:$O,O$4) -> 78.24 | P105: =SUM(D105:O105) -> 2438.7914 | Q105: 1877.76 | R105: =P105-Q105 -> 561.03136 | S105: =IF(ISERROR(R105/Q105),"",R105/Q105) -> 0.29877693 | U105: 0 | V105: 0 | W105: 0 | X105: 918.63106 | Y105: =P105/V105-1 -> #DIV/0! | Z105: =P105-V105 -> 2438.7914 | AA105: SIM | AB105: 3223.7858
A106: MG Sticks | B106: Heppenheim | C106: MG Sticks | D106: =SUMIFS('2026'!$M:$M,'2026'!$J:$J,$B106&$C106,'2026'!$O:$O,D$4) -> 0 | E106: =SUMIFS('2026'!$M:$M,'2026'!$J:$J,$B106&$C106,'2026'!$O:$O,E$4) -> 0 | F106: =SUMIFS('2026'!$M:$M,'2026'!$J:$J,$B106&$C106,'2026'!$O:$O,F$4) -> 0 | G106: =SUMIFS('2026'!$M:$M,'2026'!$J:$J,$B106&$C106,'2026'!$O:$O,G$4) -> 0 | H106: =SUMIFS('2026'!$M:$M,'2026'!$J:$J,$B106&$C106,'2026'!$O:$O,H$4) -> 0 | I106: =SUMIFS('2026'!$M:$M,'2026'!$J:$J,$B106&$C106,'2026'!$O:$O,I$4) -> 0 | J106: =SUMIFS('2026'!$M:$M,'2026'!$J:$J,$B106&$C106,'2026'!$O:$O,J$4) -> 0 | K106: =SUMIFS('2026'!$M:$M,'2026'!$J:$J,$B106&$C106,'2026'!$O:$O,K$4) -> 0 | ... O106: =SUMIFS('2026'!$M:$M,'2026'!$J:$J,$B106&$C106,'2026'!$O:$O,O$4) -> 0 | P106: =SUM(D106:O106) -> 0 | Q106: 0 | R106: =P106-Q106 -> 0 | S106: =IF(ISERROR(R106/Q106),"",R106/Q106) | U106: 224.53002 | V106: 0 | W106: 0 | X106: 0 | Y106: =P106/V106-1 -> #DIV/0! | Z106: =P106-V106 -> 0 | AA106: Import | AB106: 0
A107: BJ PTS | B107: 3910 | C107: BJ PTS | D107: =SUMIFS('2026'!$M:$M,'2026'!$J:$J,$B107&$C107,'2026'!$O:$O,D$4) -> 0 | E107: =SUMIFS('2026'!$M:$M,'2026'!$J:$J,$B107&$C107,'2026'!$O:$O,E$4) -> 0 | F107: =SUMIFS('2026'!$M:$M,'2026'!$J:$J,$B107&$C107,'2026'!$O:$O,F$4) -> 0 | G107: =SUMIFS('2026'!$M:$M,'2026'!$J:$J,$B107&$C107,'2026'!$O:$O,G$4) -> 0 | H107: =SUMIFS('2026'!$M:$M,'2026'!$J:$J,$B107&$C107,'2026'!$O:$O,H$4) -> 0 | I107: =SUMIFS('2026'!$M:$M,'2026'!$J:$J,$B107&$C107,'2026'!$O:$O,I$4) -> 0 | J107: =SUMIFS('2026'!$M:$M,'2026'!$J:$J,$B107&$C107,'2026'!$O:$O,J$4) -> 0 | K107: =SUMIFS('2026'!$M:$M,'2026'!$J:$J,$B107&$C107,'2026'!$O:$O,K$4) -> 0 | ... O107: =SUMIFS('2026'!$M:$M,'2026'!$J:$J,$B107&$C107,'2026'!$O:$O,O$4) -> 0 | P107: =SUM(D107:O107) -> 0 | Q107: 0 | R107: =P107-Q107 -> 0 | S107: =IF(ISERROR(R107/Q107),"",R107/Q107) | U107: 438.38018 | V107: 438.38018 | W107: 438.38018 | X107: 1160.409 | Y107: =P107/V107-1 -> -1 | Z107: =P107-V107 -> -438.38018 | AA107: SIM | AB107: 0
...

Sheet Pallets post Attain
B3: PLANT | C3: STA ALBANS | R3: Vs Last Cycle
A4: Tech Rollup | C4: Row Labels | D4: Jan | E4: Feb | F4: Mar | G4: Apr | H4: May | I4: Jun | J4: Jul | K4: Aug | L4: Sep | M4: Oct | N4: Nov | O4: Dec | P4: 2026 MRF3 | Q4: 2026 MRF2 | R4: Difference | S4: % change | T4: 2025 Final
A5: 2.4 Gal | B5: 5914 | C5: 2.4 Gal | D5: =SUMIFS('2026'!$N:$N,'2026'!$J:$J,$B5&$C5,'2026'!$O:$O,D$4) -> 326.96 | E5: =SUMIFS('2026'!$N:$N,'2026'!$J:$J,$B5&$C5,'2026'!$O:$O,E$4) -> 675.584 | F5: =SUMIFS('2026'!$N:$N,'2026'!$J:$J,$B5&$C5,'2026'!$O:$O,F$4) -> 508.112 | G5: =SUMIFS('2026'!$N:$N,'2026'!$J:$J,$B5&$C5,'2026'!$O:$O,G$4) -> 509.184 | H5: =SUMIFS('2026'!$N:$N,'2026'!$J:$J,$B5&$C5,'2026'!$O:$O,H$4) -> 774.316 | I5: =SUMIFS('2026'!$N:$N,'2026'!$J:$J,$B5&$C5,'2026'!$O:$O,I$4) -> 219.232 | J5: =SUMIFS('2026'!$N:$N,'2026'!$J:$J,$B5&$C5,'2026'!$O:$O,J$4) -> 406.64 | K5: =SUMIFS('2026'!$N:$N,'2026'!$J:$J,$B5&$C5,'2026'!$O:$O,K$4) -> 424.32 | ... O5: =SUMIFS('2026'!$N:$N,'2026'!$J:$J,$B5&$C5,'2026'!$O:$O,O$4) -> 0 | P5: =SUM(D5:O5) -> 4537.404 | Q5: =SUM(E5:P5) -> 8747.848 | R5: =P5-Q5 -> -4210.444 | S5: =IF(ISERROR(R5/Q5),"",R5/Q5) -> -0.48131198 | T5: 3756.68
A6: Other | B6: 5914 | C6: Quarts | D6: =SUMIFS('2026'!$N:$N,'2026'!$J:$J,$B6&$C6,'2026'!$O:$O,D$4) -> 0 | E6: =SUMIFS('2026'!$N:$N,'2026'!$J:$J,$B6&$C6,'2026'!$O:$O,E$4) -> 0 | F6: =SUMIFS('2026'!$N:$N,'2026'!$J:$J,$B6&$C6,'2026'!$O:$O,F$4) -> 0 | G6: =SUMIFS('2026'!$N:$N,'2026'!$J:$J,$B6&$C6,'2026'!$O:$O,G$4) -> 0 | H6: =SUMIFS('2026'!$N:$N,'2026'!$J:$J,$B6&$C6,'2026'!$O:$O,H$4) -> 0 | I6: =SUMIFS('2026'!$N:$N,'2026'!$J:$J,$B6&$C6,'2026'!$O:$O,I$4) -> 0 | J6: =SUMIFS('2026'!$N:$N,'2026'!$J:$J,$B6&$C6,'2026'!$O:$O,J$4) -> 0 | K6: =SUMIFS('2026'!$N:$N,'2026'!$J:$J,$B6&$C6,'2026'!$O:$O,K$4) -> 0 | ... O6: =SUMIFS('2026'!$N:$N,'2026'!$J:$J,$B6&$C6,'2026'!$O:$O,O$4) -> 0 | P6: =SUM(D6:O6) -> 0 | Q6: =SUM(E6:P6) -> 0 | R6: =P6-Q6 -> 0 | S6: =IF(ISERROR(R6/Q6),"",R6/Q6) | T6: 1765.033
A7: BJ PTS | B7: 5914 | C7: PTS Exports | D7: =SUMIFS('2026'!$N:$N,'2026'!$J:$J,$B7&$C7,'2026'!$O:$O,D$4) -> 235.09167 | E7: =SUMIFS('2026'!$N:$N,'2026'!$J:$J,$B7&$C7,'2026'!$O:$O,E$4) -> 0 | F7: =SUMIFS('2026'!$N:$N,'2026'!$J:$J,$B7&$C7,'2026'!$O:$O,F$4) -> 319.04583 | G7: =SUMIFS('2026'!$N:$N,'2026'!$J:$J,$B7&$C7,'2026'!$O:$O,G$4) -> 136.8 | H7: =SUMIFS('2026'!$N:$N,'2026'!$J:$J,$B7&$C7,'2026'!$O:$O,H$4) -> 261.6 | I7: =SUMIFS('2026'!$N:$N,'2026'!$J:$J,$B7&$C7,'2026'!$O:$O,I$4) -> 0 | J7: =SUMIFS('2026'!$N:$N,'2026'!$J:$J,$B7&$C7,'2026'!$O:$O,J$4) -> 0 | K7: =SUMIFS('2026'!$N:$N,'2026'!$J:$J,$B7&$C7,'2026'!$O:$O,K$4) -> 0 | ... O7: =SUMIFS('2026'!$N:$N,'2026'!$J:$J,$B7&$C7,'2026'!$O:$O,O$4) -> 0 | P7: =SUM(D7:O7) -> 952.5375 | Q7: =SUM(E7:P7) -> 1669.9833 | R7: =P7-Q7 -> -717.44583 | S7: =IF(ISERROR(R7/Q7),"",R7/Q7) -> -0.42961257 | T7: 1861.2125
A8: B&J Cups | B8: 5914 | C8: Cup Exports | D8: =SUMIFS('2026'!$N:$N,'2026'!$J:$J,$B8&$C8,'2026'!$O:$O,D$4) -> 0 | E8: =SUMIFS('2026'!$N:$N,'2026'!$J:$J,$B8&$C8,'2026'!$O:$O,E$4) -> 0 | F8: =SUMIFS('2026'!$N:$N,'2026'!$J:$J,$B8&$C8,'2026'!$O:$O,F$4) -> 0 | G8: =SUMIFS('2026'!$N:$N,'2026'!$J:$J,$B8&$C8,'2026'!$O:$O,G$4) -> 0 | H8: =SUMIFS('2026'!$N:$N,'2026'!$J:$J,$B8&$C8,'2026'!$O:$O,H$4) -> 0 | I8: =SUMIFS('2026'!$N:$N,'2026'!$J:$J,$B8&$C8,'2026'!$O:$O,I$4) -> 0 | J8: =SUMIFS('2026'!$N:$N,'2026'!$J:$J,$B8&$C8,'2026'!$O:$O,J$4) -> 0 | K8: =SUMIFS('2026'!$N:$N,'2026'!$J:$J,$B8&$C8,'2026'!$O:$O,K$4) -> 0 | ... O8: =SUMIFS('2026'!$N:$N,'2026'!$J:$J,$B8&$C8,'2026'!$O:$O,O$4) -> 0 | P8: =SUM(D8:O8) -> 0 | Q8: =SUM(E8:P8) -> 0 | R8: =P8-Q8 -> 0 | S8: =IF(ISERROR(R8/Q8),"",R8/Q8) | T8: 0
A9: 2.4 Gal | B9: 5914 | C9: Bulk Exports | D9: =SUMIFS('2026'!$N:$N,'2026'!$J:$J,$B9&$C9,'2026'!$O:$O,D$4) -> 0 | E9: =SUMIFS('2026'!$N:$N,'2026'!$J:$J,$B9&$C9,'2026'!$O:$O,E$4) -> 0 | F9: =SUMIFS('2026'!$N:$N,'2026'!$J:$J,$B9&$C9,'2026'!$O:$O,F$4) -> 0 | G9: =SUMIFS('2026'!$N:$N,'2026'!$J:$J,$B9&$C9,'2026'!$O:$O,G$4) -> 0 | H9: =SUMIFS('2026'!$N:$N,'2026'!$J:$J,$B9&$C9,'2026'!$O:$O,H$4) -> 0 | I9: =SUMIFS('2026'!$N:$N,'2026'!$J:$J,$B9&$C9,'2026'!$O:$O,I$4) -> 0 | J9: =SUMIFS('2026'!$N:$N,'2026'!$J:$J,$B9&$C9,'2026'!$O:$O,J$4) -> 0 | K9: =SUMIFS('2026'!$N:$N,'2026'!$J:$J,$B9&$C9,'2026'!$O:$O,K$4) -> 0 | ... O9: =SUMIFS('2026'!$N:$N,'2026'!$J:$J,$B9&$C9,'2026'!$O:$O,O$4) -> 0 | P9: =SUM(D9:O9) -> 0 | Q9: =SUM(E9:P9) -> 0 | R9: =P9-Q9 -> 0 | S9: =IF(ISERROR(R9/Q9),"",R9/Q9) | T9: 0
A10: B&J Cups | B10: 5914 | C10: B&J Cups | D10: =SUMIFS('2026'!$N:$N,'2026'!$J:$J,$B10&$C10,'2026'!$O:$O,D$4) -> 0 | E10: =SUMIFS('2026'!$N:$N,'2026'!$J:$J,$B10&$C10,'2026'!$O:$O,E$4) -> 0 | F10: =SUMIFS('2026'!$N:$N,'2026'!$J:$J,$B10&$C10,'2026'!$O:$O,F$4) -> 0 | G10: =SUMIFS('2026'!$N:$N,'2026'!$J:$J,$B10&$C10,'2026'!$O:$O,G$4) -> 0 | H10: =SUMIFS('2026'!$N:$N,'2026'!$J:$J,$B10&$C10,'2026'!$O:$O,H$4) -> 0 | I10: =SUMIFS('2026'!$N:$N,'2026'!$J:$J,$B10&$C10,'2026'!$O:$O,I$4) -> 0 | J10: =SUMIFS('2026'!$N:$N,'2026'!$J:$J,$B10&$C10,'2026'!$O:$O,J$4) -> 0 | K10: =SUMIFS('2026'!$N:$N,'2026'!$J:$J,$B10&$C10,'2026'!$O:$O,K$4) -> 0 | ... O10: =SUMIFS('2026'!$N:$N,'2026'!$J:$J,$B10&$C10,'2026'!$O:$O,O$4) -> 0 | P10: =SUM(D10:O10) -> 0 | Q10: =SUM(E10:P10) -> 0 | R10: =P10-Q10 -> 0 | S10: =IF(ISERROR(R10/Q10),"",R10/Q10) | T10: 0
A11: B&J Cups | B11: 5914 | C11: B&J Dog Treat | D11: =SUMIFS('2026'!$N:$N,'2026'!$J:$J,$B11&$C11,'2026'!$O:$O,D$4) -> 0 | E11: =SUMIFS('2026'!$N:$N,'2026'!$J:$J,$B11&$C11,'2026'!$O:$O,E$4) -> 0 | F11: =SUMIFS('2026'!$N:$N,'2026'!$J:$J,$B11&$C11,'2026'!$O:$O,F$4) -> 0 | G11: =SUMIFS('2026'!$N:$N,'2026'!$J:$J,$B11&$C11,'2026'!$O:$O,G$4) -> 0 | H11: =SUMIFS('2026'!$N:$N,'2026'!$J:$J,$B11&$C11,'2026'!$O:$O,H$4) -> 0 | I11: =SUMIFS('2026'!$N:$N,'2026'!$J:$J,$B11&$C11,'2026'!$O:$O,I$4) -> 0 | J11: =SUMIFS('2026'!$N:$N,'2026'!$J:$J,$B11&$C11,'2026'!$O:$O,J$4) -> 0 | K11: =SUMIFS('2026'!$N:$N,'2026'!$J:$J,$B11&$C11,'2026'!$O:$O,K$4) -> 0 | ... O11: =SUMIFS('2026'!$N:$N,'2026'!$J:$J,$B11&$C11,'2026'!$O:$O,O$4) -> 0 | P11: =SUM(D11:O11) -> 0 | Q11: =SUM(E11:P11) -> 0 | R11: =P11-Q11 -> 0 | S11: =IF(ISERROR(R11/Q11),"",R11/Q11) | T11: 0
A12: SP1 | B12: 5914 | C12: PTS - BR | D12: =SUMIFS('2026'!$N:$N,'2026'!$J:$J,$B12&$C12,'2026'!$O:$O,D$4) -> 0 | E12: =SUMIFS('2026'!$N:$N,'2026'!$J:$J,$B12&$C12,'2026'!$O:$O,E$4) -> 0 | F12: =SUMIFS('2026'!$N:$N,'2026'!$J:$J,$B12&$C12,'2026'!$O:$O,F$4) -> 0 | G12: =SUMIFS('2026'!$N:$N,'2026'!$J:$J,$B12&$C12,'2026'!$O:$O,G$4) -> 0 | H12: =SUMIFS('2026'!$N:$N,'2026'!$J:$J,$B12&$C12,'2026'!$O:$O,H$4) -> 0 | I12: =SUMIFS('2026'!$N:$N,'2026'!$J:$J,$B12&$C12,'2026'!$O:$O,I$4) -> 0 | J12: =SUMIFS('2026'!$N:$N,'2026'!$J:$J,$B12&$C12,'2026'!$O:$O,J$4) -> 0 | K12: =SUMIFS('2026'!$N:$N,'2026'!$J:$J,$B12&$C12,'2026'!$O:$O,K$4) -> 0 | ... O12: =SUMIFS('2026'!$N:$N,'2026'!$J:$J,$B12&$C12,'2026'!$O:$O,O$4) -> 0 | P12: =SUM(D12:O12) -> 0 | Q12: =SUM(E12:P12) -> 0 | R12: =P12-Q12 -> 0 | S12: =IF(ISERROR(R12/Q12),"",R12/Q12) | T12: 0
A13: BJ PTS | B13: 5914 | C13: BJ PTS | D13: =SUMIFS('2026'!$N:$N,'2026'!$J:$J,$B13&$C13,'2026'!$O:$O,D$4) -> 4455.675 | E13: =SUMIFS('2026'!$N:$N,'2026'!$J:$J,$B13&$C13,'2026'!$O:$O,E$4) -> 6318.6208 | F13: =SUMIFS('2026'!$N:$N,'2026'!$J:$J,$B13&$C13,'2026'!$O:$O,F$4) -> 7433.8933 | G13: =SUMIFS('2026'!$N:$N,'2026'!$J:$J,$B13&$C13,'2026'!$O:$O,G$4) -> 5202.9917 | H13: =SUMIFS('2026'!$N:$N,'2026'!$J:$J,$B13&$C13,'2026'!$O:$O,H$4) -> 4206.2833 | I13: =SUMIFS('2026'!$N:$N,'2026'!$J:$J,$B13&$C13,'2026'!$O:$O,I$4) -> 5012.96 | J13: =SUMIFS('2026'!$N:$N,'2026'!$J:$J,$B13&$C13,'2026'!$O:$O,J$4) -> 5276.8 | K13: =SUMIFS('2026'!$N:$N,'2026'!$J:$J,$B13&$C13,'2026'!$O:$O,K$4) -> 5804.48 | ... O13: =SUMIFS('2026'!$N:$N,'2026'!$J:$J,$B13&$C13,'2026'!$O:$O,O$4) -> 4609.44 | P13: =SUM(D13:O13) -> 63484.184 | Q13: =SUM(E13:P13) -> 122512.69 | R13: =P13-Q13 -> -59028.509 | S13: =IF(ISERROR(R13/Q13),"",R13/Q13) -> -0.48181546 | T13: 63791.5
C14: Total St. Albans | D14: =SUM(D5:D13) -> 5017.7267 | E14: =SUM(E5:E13) -> 6994.2048 | F14: =SUM(F5:F13) -> 8261.0512 | G14: =SUM(G5:G13) -> 5848.9757 | H14: =SUM(H5:H13) -> 5242.1993 | I14: =SUM(I5:I13) -> 5232.192 | J14: =SUM(J5:J13) -> 5683.44 | K14: =SUM(K5:K13) -> 6228.8 | ... R14: =SUM(R5:R13) -> -63956.399 | S14: =IF(ISERROR(R14/Q14),"",R14/Q14) -> -0.48112651 | T14: 71174.425
C16: WATERBURY | R16: Vs Last Cycle
C17: Row Labels | D17: Jan | E17: Feb | F17: Mar | G17: Apr | H17: May | I17: Jun | J17: Jul | K17: Aug | L17: Sep | M17: Oct | N17: Nov | O17: Dec | P17: =P$4 -> 2026 MRF3 | Q17: =Q$4 -> 2026 MRF2 | R17: =R$4 -> Difference | S17: =S$4 -> % change | T17: 2025 Final
A18: Other | B18: 5911 | C18: 1 Gal | D18: =SUMIFS('2026'!$N:$N,'2026'!$J:$J,$B18&$C18,'2026'!$O:$O,D$4) -> 0 | E18: =SUMIFS('2026'!$N:$N,'2026'!$J:$J,$B18&$C18,'2026'!$O:$O,E$4) -> 0 | F18: =SUMIFS('2026'!$N:$N,'2026'!$J:$J,$B18&$C18,'2026'!$O:$O,F$4) -> 0 | G18: =SUMIFS('2026'!$N:$N,'2026'!$J:$J,$B18&$C18,'2026'!$O:$O,G$4) -> 0 | H18: =SUMIFS('2026'!$N:$N,'2026'!$J:$J,$B18&$C18,'2026'!$O:$O,H$4) -> 0 | I18: =SUMIFS('2026'!$N:$N,'2026'!$J:$J,$B18&$C18,'2026'!$O:$O,I$4) -> 0 | J18: =SUMIFS('2026'!$N:$N,'2026'!$J:$J,$B18&$C18,'2026'!$O:$O,J$4) -> 0 | K18: =SUMIFS('2026'!$N:$N,'2026'!$J:$J,$B18&$C18,'2026'!$O:$O,K$4) -> 0 | ... O18: =SUMIFS('2026'!$N:$N,'2026'!$J:$J,$B18&$C18,'2026'!$O:$O,O$4) -> 0 | P18: =SUM(D18:O18) -> 0 | Q18: =SUM(E18:P18) -> 0 | R18: =P18-Q18 -> 0 | S18: =IF(ISERROR(R18/Q18),"",R18/Q18) | T18: 0
A19: Other | B19: 5911 | C19: QTS | D19: =SUMIFS('2026'!$N:$N,'2026'!$J:$J,$B19&$C19,'2026'!$O:$O,D$4) -> 0 | E19: =SUMIFS('2026'!$N:$N,'2026'!$J:$J,$B19&$C19,'2026'!$O:$O,E$4) -> 0 | F19: =SUMIFS('2026'!$N:$N,'2026'!$J:$J,$B19&$C19,'2026'!$O:$O,F$4) -> 0 | G19: =SUMIFS('2026'!$N:$N,'2026'!$J:$J,$B19&$C19,'2026'!$O:$O,G$4) -> 0 | H19: =SUMIFS('2026'!$N:$N,'2026'!$J:$J,$B19&$C19,'2026'!$O:$O,H$4) -> 0 | I19: =SUMIFS('2026'!$N:$N,'2026'!$J:$J,$B19&$C19,'2026'!$O:$O,I$4) -> 0 | J19: =SUMIFS('2026'!$N:$N,'2026'!$J:$J,$B19&$C19,'2026'!$O:$O,J$4) -> 0 | K19: =SUMIFS('2026'!$N:$N,'2026'!$J:$J,$B19&$C19,'2026'!$O:$O,K$4) -> 0 | ... O19: =SUMIFS('2026'!$N:$N,'2026'!$J:$J,$B19&$C19,'2026'!$O:$O,O$4) -> 0 | P19: =SUM(D19:O19) -> 0 | Q19: =SUM(E19:P19) -> 0 | R19: =P19-Q19 -> 0 | S19: =IF(ISERROR(R19/Q19),"",R19/Q19) | T19: 0
A20: BJ PTS | B20: 5911 | C20: PTS Exports | D20: =SUMIFS('2026'!$N:$N,'2026'!$J:$J,$B20&$C20,'2026'!$O:$O,D$4) -> 47.958333 | E20: =SUMIFS('2026'!$N:$N,'2026'!$J:$J,$B20&$C20,'2026'!$O:$O,E$4) -> 36.766667 | F20: =SUMIFS('2026'!$N:$N,'2026'!$J:$J,$B20&$C20,'2026'!$O:$O,F$4) -> 56.4375 | G20: =SUMIFS('2026'!$N:$N,'2026'!$J:$J,$B20&$C20,'2026'!$O:$O,G$4) -> 48 | H20: =SUMIFS('2026'!$N:$N,'2026'!$J:$J,$B20&$C20,'2026'!$O:$O,H$4) -> 0 | I20: =SUMIFS('2026'!$N:$N,'2026'!$J:$J,$B20&$C20,'2026'!$O:$O,I$4) -> 0 | J20: =SUMIFS('2026'!$N:$N,'2026'!$J:$J,$B20&$C20,'2026'!$O:$O,J$4) -> 0 | K20: =SUMIFS('2026'!$N:$N,'2026'!$J:$J,$B20&$C20,'2026'!$O:$O,K$4) -> 0 | ... O20: =SUMIFS('2026'!$N:$N,'2026'!$J:$J,$B20&$C20,'2026'!$O:$O,O$4) -> 0 | P20: =SUM(D20:O20) -> 189.1625 | Q20: =SUM(E20:P20) -> 330.36667 | R20: =P20-Q20 -> -141.20417 | S20: =IF(ISERROR(R20/Q20),"",R20/Q20) -> -0.42741651 | T20: 1132.8208
